Workbook
Name AIC_List: NEC_Data!$Y$46:$Y$57
Name Ampacity_Al: NEC_Data!$BA$6:$BA$25
Name Ampacity_CM: NEC_Data!$BB$6:$BB$25
Name Ampacity_Cu: NEC_Data!$AZ$6:$AZ$25
Name Ampacity_Size: NEC_Data!$AY$6:$AY$25
Name ATS_List: NEC_Data!$DF$6:$DF$23
Name ATS_WCR: NEC_Data!$DG$6:$DG$23
Name Brace_List: NEC_Data!$DE$6:$DE$19
Name BranchAmpCol: Dashboard!$C$90
Name BranchCcol: Dashboard!$C$94
Name BranchCol60: NEC_Data!$AB$13
Name BranchK: Dashboard!$C$92
Name Bus_List: NEC_Data!$DD$6:$DD$22
Name Cfg_BranchMat: Dashboard!$C$47
Name Cfg_Class: Dashboard!$C$43
Name Cfg_Conduit: Dashboard!$C$50
Name Cfg_Energy_Code: 'Load Calc'!$C$14
Name Cfg_FeederMat: Dashboard!$C$48
Name Cfg_LPD_Method: 'Load Calc'!$C$15
Name Cfg_MaxNodes: NEC_Data!$CD$10
Name Cfg_MotorMult: NEC_Data!$CD$12
Name Cfg_MotorMultMCC: NEC_Data!$CD$13
Name Cfg_NEC: Dashboard!$B$14
Name Cfg_Phase: Dashboard!$C$40
Name Cfg_SCA: Dashboard!$C$72
Name Cfg_Temp: Dashboard!$C$49
Name Cfg_UtilFLA: Dashboard!$C$73
Name Cfg_UtilIscInf: Dashboard!$C$74
Name Cfg_UtilKVA: Dashboard!$C$67
Name Cfg_UtilPriV: Dashboard!$C$68
Name Cfg_UtilProvider: Dashboard!$C$65
Name Cfg_UtilTag: Dashboard!$C$64
Name Cfg_UtilXR: Dashboard!$C$71
Name Cfg_UtilZ: Dashboard!$C$70
Name Cfg_VDFeeder: NEC_Data!$CD$15
Name Cfg_VDTotal: NEC_Data!$CD$16
Name Cfg_VLN: Dashboard!$C$42
Name Cfg_Volt: Dashboard!$C$39
Name Class_List: NEC_Data!$K$46:$K$57
Name Class_Table: NEC_Data!$K$46:$N$57
Name Cond_Size: NEC_Data!$J$6:$J$28
Name Cond_Table: NEC_Data!$J$6:$U$28
Name EGC_Al: NEC_Data!$BE$6:$BE$22
Name EGC_Cu: NEC_Data!$BD$6:$BD$22
Name EGC_OCPD: NEC_Data!$BC$6:$BC$22
Name EGC_Table: NEC_Data!$W$6:$Y$24
Name Elev_DF: NEC_Data!$P$56:$Q$65
Name Equip_Demand: Dashboard!$F$101:$F$350
Name Equip_EmLen: Dashboard!$T$101:$T$350
Name Equip_FdrExist: Dashboard!$W$101:$W$350
Name Equip_FdrLen: Dashboard!$R$101:$R$350
Name Equip_FdrMat: Dashboard!$U$101:$U$350
Name Equip_FdrRace: Dashboard!$V$101:$V$350
Name Equip_FedFrom: Dashboard!$D$101:$D$350
Name Equip_List: Dashboard!$A$101:$A$350
Name Equip_Registry: Dashboard!$A$101:$J$350
Name Equip_Type: Dashboard!$B$101:$B$350
Name Equip_Volt: Dashboard!$C$101:$C$350
Name Equip_XfPriLen: Dashboard!$S$101:$S$350
Name Exist_LogBoard: IF(TRIM('Logging Demand'!$C$14&"")<>"",TRIM('Logging Demand'!$C$14&""),Exist_ServiceBoard)

Sheet Instructions
A1: INSTRUCTIONS
A2: Cradle-to-grave electrical design toolkit. Everything the ribbon does, every cell you type in, and every number it calculates — in order. Keep this tab with the project.
A3: Version 2.10 · SÄZÄN PowerCalc add-in · One chapter per ribbon section, in ribbon order. Ribbon ▸ Help ▸ Instructions jumps to any chapter; the CONTENTS links below do the same.
A4: CONTENTS
A5: 01 | B5: Getting Started | C5: How the tool is built, installing it, a ten-step quick start and the colour / cell conventions used on every sheet.
A6: 02 | B6: Project | C6: Ribbon ▸ Setup ▸ Project. The project shell, the Dashboard and its Design QA panel.
A7: 03 | B7: Load Calc | C7: Ribbon ▸ Setup ▸ Load Calc. Building loads, sections, and sending loads to the panel schedules.
A8: 04 | B8: Existing Demand | C8: Ribbon ▸ Setup ▸ Existing Demand. NEC 220.87 from utility bills or a 30-day logging study.
A9: 05 | B9: Panel Schedules | C9: Ribbon ▸ Distribution ▸ Panel Schedules. Switchboards, MCCs and panelboards; linking is done in the Distribution Map (chapter 14).
A10: 06 | B10: Transformers | C10: Ribbon ▸ Distribution ▸ Transformers. Rows derive themselves wherever a feed changes voltage.
A11: 07 | B11: Backup Power | C11: Ribbon ▸ Distribution ▸ Backup Power. Generators, transfer switches and UPS systems.
A12: 08 | B12: Feeders | C12: Ribbon ▸ Studies ▸ Feeders. One derived row per feeder: conductor, conduit, OCPD and EGC.
A13: 09 | B13: Voltage Drop | C13: Ribbon ▸ Studies ▸ Voltage Drop. Run and cumulative %VD per bus.
A14: 10 | B14: Short Circuit | C14: Ribbon ▸ Studies ▸ Short Circuit. Available fault current and AIC adequacy at every bus.
A15: 11 | B15: Arc Flash | C15: Ribbon ▸ Safety & Review ▸ Arc Flash. IEEE 1584 incident energy and PPE category per bus.
A16: 12 | B16: Studies | C16: Ribbon ▸ Safety & Review ▸ Studies. The combined read-only study view and the full refresh.
... A19: 15 | B19: Reference & Troubleshooting | C19: How the engine works, rules, troubleshooting, the code basis and the appendices.
A21: CHAPTER 01 · GETTING STARTED
A22: How the tool is built, installing it, a ten-step quick start and the colour / cell conventions used on every sheet.
B23: What this is, and how it is built
B24: Purpose | C24: A single tool that carries an electrical design from first load estimate to issued schedules: NEC Article 220 load calc, existing-building demand, panel/switchboard/MCC schedules, transformers, generator and UPS sizing, short circuit, voltage drop, arc flash, feeder sizing, a combined Studies view, and a printable report.
B25: How it ships | C25: Two parts, and neither one holds your project data. (1) THE ADD-IN — a ribbon tab and a dockable task pane, loaded by Excel from a hosted manifest. It holds the commands. (2) THE PROJECT TEMPLATE — sazan-project-template.xlsx, which holds all 19 calculation sheets with every cross-sheet formula intact and no project data. You start a project from the template; the add-in drives it. There is a third file, SGI_PowerCalc_Master_v1.xlsm, but it is the AUTHORING master that the template is generated from — only the maintainer opens it.
B26: The add-in | C26: SAZAN Panel Tree, an Office web add-in. Excel loads it from a manifest pointing at static files hosted over HTTPS, so there is nothing to install per machine beyond registering the catalog once. It adds the SÄZÄN POWERCALC ribbon tab and a task pane you can dock, float and resize. It runs on Excel for Windows, Mac and the web, and it contains no VBA — a task pane cannot run macros. See section 2 to install it.
B27: The project workbook | C27: A copy of sazan-project-template.xlsx saved under your project name. It opens WHOLE — all 19 calculation sheets, every cross-sheet formula and every defined name already in place. Nothing is copied in on demand, because the Dashboard and the modules reference each other in both directions and no single one of them works alone. It stays a plain .xlsx with no macros, so it emails and archives cleanly.
B28: The code engines | C28: NEC_Data holds the voltage systems, NEC 240.6 OCPD and fuse sizes, the NEMA receptacle library, NEC Chapter 9 Table 8 conductor properties, K and C constants, load classifications and demand factors, and standard transformer kVA. Energy_Code_Data holds lighting power densities and space types. Every dropdown and every calc in the workbook reads from these two sheets — nothing is hardcoded in a formula. Both ship inside the project template, so each project carries its own copy of the code data.
B29: The device templates | C29: TPL_Switchboard, TPL_Panelboard and TPL_MCC are master layouts, and all three travel inside the project template. When you create a device, the add-in copies the matching template within your own workbook, renames it to your device tag, and registers it on the Dashboard. Editing a template changes every device created afterwards — never devices already created.
B30: GEO_MAP | C30: Each template carries a small GEO_MAP block (far right of the sheet, grey 8 pt) listing where its name, voltage, AIC, fault, demand and voltage-drop cells live. The commands read addresses from GEO_MAP instead of hardcoding them, so a template can be re-laid-out without breaking the code. See Appendix A.
B31: The registry is the spine | C31: Every device you create gets one row in the Dashboard EQUIPMENT REGISTRY, keyed by its tag. Studies, links, roll-ups and reconciliation all find equipment by that tag — never by sheet position. If a device is not in the registry, it does not exist to the rest of the tool.
B32: Install and first-time setup
A33: 1 | B33: What you need | C33: Excel 365 on Windows, Mac or the web. The add-in's manifest.xml, and one folder your team can reach — a network share works, and a plain local folder is fine for solo testing. You do NOT need admin rights, you do NOT need macros enabled, and there is nothing to unblock.
A34: 2 | B34: Register the catalog — once per machine | C34: Put manifest.xml in that folder. Then File ▸ Options ▸ Trust Center ▸ Trust Center Settings ▸ Trusted Add-in Catalogs. Paste the FOLDER path, not the path to the manifest file itself — this is the step people get wrong. Add catalog, tick Show in Menu, OK, then restart Excel. For a team-wide rollout the maintainer can instead upload manifest.xml in the M365 admin center ▸ Settings ▸ Integrated apps, which pushes it to everyone with no per-machine step.
A35: 3 | B35: Insert the add-in | C35: Insert ▸ My Add-ins ▸ SHARED FOLDER tab ▸ SAZAN Panel Tree ▸ Add. The task pane opens docked on the right. Drag its inner edge to resize, drag the header out to float, drag it back to redock — Excel manages the dock itself.
A36: 4 | B36: Confirm it loaded | C36: You should see a top-level ribbon tab named SÄZÄN POWERCALC, and the task pane should show the black PANEL TREE band. If the tab is missing, the catalog path is wrong or Excel has not been restarted since — see section 13.
A37: 5 | B37: Get the project template | C37: Download sazan-project-template.xlsx from the repository and keep one clean copy somewhere the team can reach. Start every project by COPYING that file. Do not work from an email attachment or a Downloads folder.
A38: 6 | B38: Keep the template pristine | C38: Never type project data into the clean copy of the template — it is the source every project starts from, and if it gets polluted every future project inherits it. The same rule applies to the authoring master, SGI_PowerCalc_Master_v1.xlsm, which only the maintainer opens.
B39: Quick start — a project in ten steps
A40: 1 | B40: Start from the template | C40: Copy sazan-project-template.xlsx and save it under your project name. It already contains all 19 calculation sheets, every formula and every defined name — there is nothing to build and nothing to import.
A41: 2 | B41: Fill the project block | C41: Dashboard ▸ PROJECT INFORMATION: project name, number, client, location, engineer / PE of record, date, revision. Blue-on-grey cells only.
A42: 3 | B42: Set the system voltage | C42: Dashboard ▸ ELECTRICAL SYSTEM ▸ System Voltage (dropdown). Everything downstream — nominal V, phase, wires, L-N voltage, voltage class — derives from this one selection. Nothing calculates correctly until it is set.
A43: 4 | B43: Set design defaults | C43: Dashboard ▸ DESIGN DEFAULTS: branch and feeder conductor material (Cu/Al), termination temperature rating (60/75/90 °C), conduit type. Then UTILITY SOURCES: one column per service transformer (up to four) — tag, provider, kVA, %Z, X/R and the available fault current from each utility letter. Then BUS TIES for split-bus / main-tie-main boards.
A44: 5 | B44: Build the load calc | C44: Ribbon ▸ Load Calc. Areas and W/SF allowances first, then itemized equipment across the twelve category tables. This produces the connected load, the NEC 220 demand load, and the suggested service size.
A45: 6 | B45: Existing building? Run 220.87 | C45: Ribbon ▸ Existing Demand — 12-month utility bills, or 30-day logging. The 125 % existing demand feeds the Load Calc renovation line and the spare-capacity check.
A46: 7 | B46: Create the distribution equipment | C46: Ribbon ▸ Panel Schedules ▸ New Switchboard / Panelboard / MCC. Work top-down: service equipment first, then subpanels. Each device gets its own tab and a registry row.
A47: 8 | B47: Link it together | C47: Ribbon ▸ Panel Schedules ▸ Distribution Map. Select a board, set Fed from, Feed type (Sub-Feed / Feed-Through / Tap) and circuit, then Apply to schedules. Child demand rolls up to the parent, and the parent's fault current propagates down. Crossing a voltage boundary automatically adds and sizes a transformer.
A48: 9 | B48: Run the studies | C48: Ribbon ▸ Studies ▸ Refresh Studies. One click does both halves now — it rebuilds Arc Flash and then recalculates the Feeder Schedule. Short Circuit and Voltage Drop need no rebuild at all; they derive themselves from the registry the moment a device appears. Enter the per-bus arc-flash inputs, then run it again.
A49: 10 | B49: Check QA and issue | C49: Dashboard ▸ DESIGN QA reads 13 checks. Clear every ✘ and review every ⚠. Then Ribbon ▸ Reports ▸ New Report for the printable summary, and save as .xlsx.
B50: Cell conventions — colour, type and layout
B51: Blue text on grey fill | C51: YOUR INPUT. These are the only cells you should ever type in. Blue #0000FF on grey #D9D9D9.
B52: Red text | C52: CALCULATED or LINKED. Never type here. This covers both formulas on the same sheet and cross-sheet links. If a red cell is wrong, the error is upstream — find the blue cell feeding it.
B53: Teal banner #458A96 | C53: Primary section banner, 16 pt, row height 30.
B54: Dark / mid grey banner | C54: #606262 and #7E868C — secondary headers and sub-labels.
B55: Gold #F1B92A | C55: Attention. A gold fill or flag means a value needs to be confirmed, or a limit has been approached.
B56: Green / ochre | C56: #4DAB51 and #CA7F39 — secondary accents and chart series.
B57: Typography | C57: Segoe UI throughout. Header rows 16 pt at row height 30; data rows 10 pt at row height 15.
B58: Number formats | C58: Currency and kVA use thousands separators; zeros display as an em-dash rather than 0; percentages one decimal (0.0%); multiples 0.0x; negatives in parentheses. Years are text, never 2,024.
B59: Do not restyle | C59: The colors carry meaning for reviewers and for the next engineer to open the file. Do not repaint cells to taste.
B60: The ribbon at a glance
B61: Tab | C61: SÄZÄN PowerCalc. Groups left to right: SETUP (Project, Load Calc, Existing Demand) · DISTRIBUTION (Panel Schedules, Transformers, Backup Power) · STUDIES (Feeders, Voltage Drop, Short Circuit) · SAFETY & REVIEW (Arc Flash, Studies) · OUTPUT (Reports) · MAP (Distribution Map) · HELP (Instructions). Each section is one large button with a dropdown of its commands; this manual has one chapter per section, in the same order.
B62: New … / Go To … | C62: "New …" creates the module if it is missing and then opens it; "Go To …" only navigates.
A64: CHAPTER 02 · PROJECT
A65: Ribbon ▸ Setup ▸ Project. The project shell, the Dashboard and its Design QA panel.
B66: Ribbon ▸ Project
B67: New Project | C67: New Project
B68: Instructions | C68: Instructions
B69: Dashboard | C69: Dashboard
B70: Module — Project Dashboard
B71: PROJECT DASHBOARD | C71: Command centre. Project information, the system voltage that drives everything, design defaults, live module status, the 13-point design QA panel, the utility sources and bus ties, the engine constants, the equipment registry, and panel load reconciliation.
B72: You enter | C72: PROJECT INFORMATION (B7:B13 labels / C-column values); B14 NEC Edition (2020 / 2023 / 2026, default 2023, name Cfg_NEC) - every code citation on the calculation sheets, templates and Report is a formula that reads NEC_Data CX:DB through NECREF("2023 number"), so choosing 2026 turns 220.87 into 120.87, Article 220 into 120, and so on. Choosing 2026 also enables Load Calc C38 (load being removed, subtracted in the 120.87 renovation check). The 2026 column of the map comes from published summaries - check it against NFPA 70-2026 and edit NEC_Data DA directly; this Instructions tab is written to 2023 numbering. ELECTRICAL SYSTEM: System Voltage dropdown at C37 — this is the single most important input in the workbook. DESIGN DEFAULTS C46:C49 — branch conductor material, feeder conductor material, termination temperature rating (60/75/90), conduit type. CALCULATION MODULES C53:C56 — ON/OFF for breaker sizing (always on), wire sizing, voltage drop, short circuit; C57:C58 — Standby Generator / UPS status (Tog_Gen / Tog_UPS), read-only, set by ribbon ▸ New Generator / New UPS. Neither module is in a project by default: until deployed, the Gen / UPS column in every Load Calc section, the connected-loads block at the foot of the Load Calc and the module tab stay hidden. Pressing the button again offers go to / remove / add another copy; removal is refused while any load is still tagged to it. UTILITY SOURCES C63:F77 — one column per service transformer; row 71 is the available symmetrical RMS fault current from the utility letter, row 74 is the fault duty including bus ties that the Short Circuit study starts from. BUS TIES B82:F85 — tie tag, Bus A, Bus B, normal position and transfer type; the sheet traces each bus to its source, checks that either source can carry both buses, and reports the tie fault duty. Main boards are linked by setting their registry Fed From to a source tag.
B73: It calculates | C73: C38:C42 derive nominal L-L voltage, phase, wires, L-N voltage and voltage class from C37 by lookup into Volt_Table. ENGINE CONSTANTS C65:C70 derive the ampacity table column, the K constant for voltage drop and the C column for short circuit from your conductor material and termination temperature — these are read-only and must not be typed over.
B74: Feeds | C74: Everything. Every module, every device tab and every study reads these values through defined names (Cfg_Volt, Cfg_BranchMat, Cfg_FeederMat, Cfg_Temp, Cfg_SCA, Tog_VD, Tog_SC, BranchK, FeederK …).
B75: Equipment registry | C75: Header row 74; data rows 75:324 — capacity 250 devices, set by Cfg_MaxNodes on NEC_Data. Columns: Tag, Type, Voltage, Fed From, Mains, Demand kVA, Sheet Link, Notes, Feed Type, Feeder Ckt / Space. Type straight into the next unshaded row; the table is only ever as long as the project. Rows are also written automatically when a schedule is created from the ribbon. Voltage MUST be picked from the dropdown or the Transformer, Feeder, Short Circuit and Voltage Drop schedules cannot resolve that device and will silently skip it. Fed From must match another Tag exactly, or read Source for the service entrance. Sheet order is irrelevant — everything is matched by Tag.
B76: Design QA | C76: Rows 21:33, thirteen checks. See section 8.
B77: Note | C77: Do not insert or delete rows on the Dashboard. Roughly thirty defined names point at fixed addresses on this sheet.
B78: The Design QA panel
A79: Dashboard rows 19:33. The counter at row 19 tallies pass / review / fail / pending. Nothing is issued until every ✘ is cleared and every ⚠ has been reviewed and accepted with a reason.
A80: 1 | B80: System voltage configured | C80: Dashboard config. Fails until C37 is set. Nothing downstream is valid before this.
A81: 2 | B81: Building area entered | C81: NEC 220. Requires the LC_Areas table to be populated.
A82: 3 | B82: New load calculated | C82: NEC 220. Requires demand load > 0 on the Load Calc.
A83: 4 | B83: Suggested service size | C83: NEC 240.6. Confirms a standard rating was found for the design load.
A84: 5 | B84: Design amps within service | C84: NEC 240.4. Design amps must not exceed the selected service rating.
A85: 6 | B85: Existing service spare (renovation) | C85: NEC 220.87. Only applies where an existing-demand module has been run; reports the spare capacity for new load.
A86: 7 | B86: Short-circuit AIC margin | C86: NEC 110.9 / 110.10. Reports the MINIMUM margin across every bus in the Short Circuit table. Negative at any bus is a fail.
A87: 8 | B87: Voltage drop within limit | C87: NEC 210.19 / 215.2 informational notes. Checks the project maximum %VD against 3 %.
A88: 9 | B88: Arc-flash incident energy | C88: IEEE 1584. Reports the worst-case cal/cm² across all buses against a 40 cal/cm² practical limit.
A89: 10 | B89: Feeder conductor / OCPD sizing | C89: NEC 310.16 / 240.6. Counts sized feeders on the Feeder Schedule.
A90: 11 | B90: Generator sizing | C90: NEC 700 / 701 / 702. Requires standby loads to have been entered or rolled up.
A91: 12 | B91: UPS sizing | C91: Critical power. Requires UPS loads to have been entered or rolled up.
A92: 13 | B92: Panel load reconciliation | C92: Every Load Calc Panel Tag must reconcile to the kVA entered on that panel's schedule, within the tolerance at Dashboard K362.
A94: CHAPTER 03 · LOAD CALC
A95: Ribbon ▸ Setup ▸ Load Calc. Building loads, sections, and sending loads to the panel schedules.
B96: Ribbon ▸ Load Calc
B97: New Load Calc | C97: New Load Calc
B98: Go To Load Calc | C98: Go To Load Calc
B99: Add Row | C99: Adds one row to the Load Calc section your cursor is in, keeping the section formatting.
B100: Trim Empty Rows | C100: Removes empty rows from the bottom of the Load Calc section your cursor is in.
B101: Add / Remove Section | C101: Load Calc: adds or removes an optional section (Refrigeration, Kitchen, Elevators, EV, Fire, Process). Logging Demand: adds or removes the interval-data blocks and load duration curve.
B102: Send to Panel | C102: Places the selected Load Calc rows on a panel, switchboard or MCC at the circuit you choose, as live links. Ckts / Placed / Status track what has been moved.
B103: Refresh Placement | C103: Rescans every schedule and updates the Ckts / Placed / Status columns on Load Calc (picks up circuits cleared or moved on a panel).
B104: Send to Panel — branch length | C104: The Send to Panel dialog has an optional Branch circuit length (ft). It is written to Length Ft on every circuit placed so the schedule's VD % works straight away. Length Ft stays a manual entry on the schedule, even on rows linked from the Load Calc (those are otherwise locked).
B105: Module — Load Calc
...

Sheet Dashboard
A1: PROJECT DASHBOARD — CRADLE-TO-GRAVE ELECTRICAL DESIGN
A2: Blue text on grey = your inputs. Red = auto-calculated (do not type).
A4: PROJECT INFORMATION
F6: Module | G6: Status | H6: Key Result | I6: Sheet
A7: Project Name | F7: Load Calculation | G7: =IFERROR(IF(N(LC_DemandTotal)>0,"● Active","○ Pending"),"○ Pending") -> ○ Pending | H7: =IFERROR(IF(N(LC_DemandTotal)>0,TEXT(LC_DemandTotal,"#,##0.0")&" kVA"&IF(ISNUMBER(LC_DemandAmps)," / "&TEXT(LC_DemandAmps,"#,##0")&" A demand",""),"—"),"—") -> — | I7: Load Calc
A8: Project Number | F8: {="Utility Bills "&NECREF("220.87")&" (12-Month)"} -> Utility Bills 220.87 (12-Month) | G8: =IFERROR(IF(N('Utility Demand'!$G$36)>0,"● Active","○ Pending"),"○ Pending") -> ○ Pending | H8: =IFERROR(IF(N('Utility Demand'!$G$36)>0,TEXT('Utility Demand'!$G$36,"#,##0.0")&" kW peak / "&TEXT('Utility Demand'!$G$42,"#,##0.0")&" kVA spare","—"),"—") -> — | I8: Utility Demand
A9: Client | F9: {="Logging "&NECREF("220.87")&" (30-Day)"} -> Logging 220.87 (30-Day) | G9: =IFERROR(IF(N('Logging Demand'!$C$45)>0,"● Active","○ Pending"),"○ Pending") -> ○ Pending | H9: {=IFERROR(IF(N('Logging Demand'!$C$45)>0,TEXT('Logging Demand'!$C$45,"#,##0.0")&" kW peak / "&TEXT('Logging Demand'!$C$48,"#,##0.0")&(" kVA per "&NECREF("220.87")),"—"),"—")} -> — | I9: Logging Demand
A10: Location | F10: Generator Sizing | G10: =IF(Tog_Gen<>"ON","— not in project",IF(N(Generator!$D$40)>0,"● Active","◐ Incomplete")) -> — not in project | H10: =IF(Tog_Gen<>"ON",IF(N(LC_GenTotal)>0,TEXT(LC_GenTotal,"#,##0.0")&" kVA tagged Gen — add Generator (ribbon)","— not in project"),IF(N(Generator!$D$40)>0,IF(ISNUMBER(Generator!$D$45),TEXT(Generator!$D$45,"#,##0")&" kW gen","—")&IF(COUNTIF(Generator!$B$62:$B$69,"?*")>0," · "&COUNTIF(Generator!$B$62:$B$69,"?*")&" transfer switch(es)",""),IF(COUNTIF(Generator!$B$53:$B$58,"?*")=0,"Missing: generator unit tag (Generator ▸ Units)","Missing: loads — tag Gen on Load Calc or add manual loads"))) -> — not in project | I10: Generator
A11: Engineer / PE of Record | F11: UPS Sizing | G11: =IF(Tog_UPS<>"ON","— not in project",IF(OR(N(UPS!$C$38)>0,COUNT(UPS!$L$57:$L$64)>0),"● Active","◐ Incomplete")) -> — not in project | H11: =IF(Tog_UPS<>"ON",IF(N(LC_UPSTotal)>0,TEXT(LC_UPSTotal,"#,##0.0")&" kVA tagged UPS — add UPS (ribbon)","— not in project"),IF(OR(N(UPS!$C$38)>0,COUNT(UPS!$L$57:$L$64)>0),IF(ISNUMBER(UPS!$C$41),TEXT(UPS!$C$41,"#,##0")&" kVA module",IF(COUNT(UPS!$L$57:$L$64)>0,TEXT(SUM(UPS!$L$57:$L$64),"#,##0")&" kVA placed","—"))&IF(COUNTIF(UPS!$B$57:$B$64,"?*")>0," · "&COUNTIF(UPS!$B$57:$B$64,"?*")&" UPS system(s)",""),IF(COUNTIF(UPS!$B$48:$B$53,"?*")=0,"Missing: UPS unit tag (UPS ▸ Units)","Missing: loads — tag UPS on Load Calc, add manual loads, or place a UPS system"))) -> — not in project | I11: UPS
A12: Date | F12: Panel Schedules | G12: =IF(COUNTA(Equip_List)>0,"● Active","○ Pending") -> ○ Pending | H12: =COUNTA(Equip_List)&" equipment in registry" -> 0 equipment in registry | I12: (registry below)
A13: Revision | F13: Short Circuit / AIC | G13: =IFERROR(_xlfn.LET(_xlpm.b,COUNTA(Equip_List),_xlpm.n,COUNTIFS('Short Circuit'!$A$6:$A$255,"?*",'Short Circuit'!$C$6:$C$255,"<>0")-COUNTIFS('Short Circuit'!$A$6:$A$255,"T-*",'Short Circuit'!$R$6:$R$255,""),_xlpm.s,COUNT('Short Circuit'!$S$6:$S$255),IF(_xlpm.b=0,"○ Pending",IF(AND(_xlpm.s>0,_xlpm.s>=_xlpm.n),"● Active","◐ Incomplete"))),"◐ Incomplete") -> ○ Pending | H13: =IFERROR(_xlfn.LET(_xlpm.b,COUNTA(Equip_List),_xlpm.n,COUNTIFS('Short Circuit'!$A$6:$A$255,"?*",'Short Circuit'!$C$6:$C$255,"<>0")-COUNTIFS('Short Circuit'!$A$6:$A$255,"T-*",'Short Circuit'!$R$6:$R$255,""),_xlpm.s,COUNT('Short Circuit'!$S$6:$S$255),_xlpm.fm,COUNTIF('Short Circuit'!$T$6:$T$255,"*feeder data missing*"),IF(_xlpm.b=0,"— no equipment yet",IF(_xlpm.s>0,TEXT(MIN('Short Circuit'!$S$6:$S$255),"#,##0")&" A min AIC margin"&IF(_xlpm.s<_xlpm.n," · "&(_xlpm.n-_xlpm.s)&" of "&_xlpm.n&" bus(es) missing data",""),IF(COUNT(Util_SCAEff)=0,"Missing: utility fault current (Dashboard ▸ Utility Sources)",IF(_xlpm.n=0,"Missing: Fed From on equipment (Distribution Map)",IF(_xlpm.fm>0,"Missing: feeder load / length on "&_xlpm.fm&" feeder(s) (Feeder Schedule)","Missing: device AIC on "&_xlpm.n&" bus(es)")))))),"—") -> — no equipment yet | I13: Short Circuit
A14: NEC Edition | B14: 2023 | F14: Voltage Drop | G14: =IFERROR(IF(COUNTIFS('Voltage Drop'!$A$6:$A$255,"<>",'Voltage Drop'!$C$6:$C$255,">0")>0,"● Active","○ Pending"),"○ Pending") -> ○ Pending | H14: =IFERROR(IF(COUNTIFS('Voltage Drop'!$A$6:$A$255,"<>",'Voltage Drop'!$C$6:$C$255,">0")=0,"—",TEXT(MAX('Voltage Drop'!$H$6:$H$255),"0.00%")&" worst cumulative VD"),"—") -> — | I14: Voltage Drop
F15: Arc Flash (IEEE 1584) | G15: =IFERROR(_xlfn.LET(_xlpm.b,COUNTA(Equip_List),_xlpm.n,COUNTIFS('Short Circuit'!$A$6:$A$255,"?*",'Short Circuit'!$C$6:$C$255,"<>0"),_xlpm.r,COUNT('Arc Flash'!$B$24:$B$296),_xlpm.m,COUNT('Arc Flash'!$M$24:$M$296),IF(_xlpm.b=0,"○ Pending",IF(AND(_xlpm.m>0,_xlpm.m>=_xlpm.r,_xlpm.r>=_xlpm.n),"● Active","◐ Incomplete"))),"◐ Incomplete") -> ○ Pending | H15: =IFERROR(_xlfn.LET(_xlpm.b,COUNTA(Equip_List),_xlpm.n,COUNTIFS('Short Circuit'!$A$6:$A$255,"?*",'Short Circuit'!$C$6:$C$255,"<>0"),_xlpm.r,COUNT('Arc Flash'!$B$24:$B$296),_xlpm.m,COUNT('Arc Flash'!$M$24:$M$296),_xlpm.c,COUNT('Arc Flash'!$C$24:$C$296),IF(_xlpm.b=0,"— no equipment yet",IF(_xlpm.m>0,TEXT(MAX('Arc Flash'!$M$24:$M$296),"0.00")&" cal/cm² worst case"&IF(_xlpm.r<_xlpm.n," · run Refresh Studies ("&_xlpm.r&" of "&_xlpm.n&" buses listed)",IF(_xlpm.m<_xlpm.r," · "&(_xlpm.r-_xlpm.m)&" bus(es) missing data","")),IF(_xlpm.r<_xlpm.n,"Missing: run Refresh Studies ("&_xlpm.r&" of "&_xlpm.n&" buses listed)",IF(_xlpm.c<_xlpm.r,"Missing: bus fault from Short Circuit on "&(_xlpm.r-_xlpm.c)&" bus(es)","Missing: equipment class / clearing time (Arc Flash)"))))),"—") -> — no equipment yet | I15: Arc Flash
A17: DESIGN QA — CHECKS & VALIDATION
A18: =COUNTIF($E$21:$E$34,"✔*")&" pass · "&COUNTIF($E$21:$E$34,"⚠*")&" review · "&COUNTIF($E$21:$E$34,"✘*")&" fail · "&COUNTIF($E$21:$E$34,"—*")&" pending" -> 0 pass · 2 review · 0 fail · 12 pending
A20: # | B20: Check | C20: NEC / Basis | E20: Result
A21: 1 | B21: System voltage configured | C21: Dashboard config | E21: =IF(N(Cfg_Volt)>0,"✔ "&TEXT(Cfg_Volt,"#,##0")&" V set","⚠ Set System Voltage on Dashboard") -> ⚠ Set System Voltage on Dashboard
A22: 2 | B22: Building area entered | C22: {="NEC "&NECREF("220")} -> NEC 220 | E22: =IF(N(LC_TotalSF)>0,"✔ "&TEXT(LC_TotalSF,"#,##0")&" SF","⚠ Enter areas on Load Calc") -> ⚠ Enter areas on Load Calc
A23: 3 | B23: New load calculated | C23: {="NEC "&NECREF("220")} -> NEC 220 | E23: =IF(N(LC_AdjustedDemand)>0,"✔ "&TEXT(LC_AdjustedDemand,"#,##0.0")&" kVA adj. demand","— No load entered yet") -> — No load entered yet
A24: 4 | B24: Suggested service size | C24: {="NEC "&NECREF("240.6")} -> NEC 240.6 | E24: =IF(N(LC_ServiceSize)>0,"✔ "&TEXT(LC_ServiceSize,"#,##0")&" A","— pending load") -> — pending load
A25: 5 | B25: Design amps within service | C25: {="NEC "&NECREF("240.4")} -> NEC 240.4 | E25: =IF(N(LC_ServiceSize)=0,"— n/a",IF(LC_DesignAmps<=LC_ServiceSize,"✔ "&TEXT(LC_DesignAmps,"#,##0")&" A ≤ service","✘ "&TEXT(LC_DesignAmps,"#,##0")&" A exceeds service")) -> — n/a
A26: 6 | B26: Existing service spare (renovation) | C26: {="NEC "&NECREF("220.87")} -> NEC 220.87 | E26: =IF(N(LC_ExistingLoad125)=0,"— n/a (new building)",IF(LC_ExistingSpare>=0,"✔ "&TEXT(LC_ExistingSpare,"#,##0.0")&" kVA spare","✘ Existing service overloaded")) -> — n/a (new building)
A27: 7 | B27: Short-circuit AIC margin | C27: {="NEC "&NECREF("110.9")&" / "&NECREF("110.10")} -> NEC 110.9 / 110.10 | E27: =IFERROR(IF(COUNT('Short Circuit'!$S$6:$S$255)=0,IF(COUNTA(Equip_List)=0,"— no equipment yet","⚠ "&$H$13),IF(MIN('Short Circuit'!$S$6:$S$255)>=0,"✔ "&TEXT(MIN('Short Circuit'!$S$6:$S$255),"#,##0")&" A min margin ("&COUNT('Short Circuit'!$S$6:$S$255)&" buses)"&IF(COUNT('Short Circuit'!$S$6:$S$255)<(COUNTIFS('Short Circuit'!$A$6:$A$255,"?*",'Short Circuit'!$C$6:$C$255,"<>0")-COUNTIFS('Short Circuit'!$A$6:$A$255,"T-*",'Short Circuit'!$R$6:$R$255,""))," · ⚠ "&((COUNTIFS('Short Circuit'!$A$6:$A$255,"?*",'Short Circuit'!$C$6:$C$255,"<>0")-COUNTIFS('Short Circuit'!$A$6:$A$255,"T-*",'Short Circuit'!$R$6:$R$255,""))-COUNT('Short Circuit'!$S$6:$S$255))&" missing",""),"✘ AIC exceeded at "&COUNTIF('Short Circuit'!$S$6:$S$255,"<0")&" bus(es)")),"— run study") -> — no equipment yet
A28: 8 | B28: Voltage drop within limit | C28: {="NEC "&NECREF("210.19")&" / "&NECREF("215.2")&" IN"} -> NEC 210.19 / 215.2 IN | E28: =IFERROR(_xlfn.LET(_xlpm.n,COUNTIFS('Voltage Drop'!$A$6:$A$255,"?*",'Voltage Drop'!$C$6:$C$255,">0"),_xlpm.m,COUNT('Voltage Drop'!$H$6:$H$255)-COUNTIFS('Voltage Drop'!$C$6:$C$255,0),_xlpm.w,MAX('Voltage Drop'!$H$6:$H$255),IF(_xlpm.n=0,IF(COUNTA(Equip_List)=0,"— no equipment yet","— run study"),IF(_xlpm.m<=0,"⚠ Missing: feeder load / length (Feeder Schedule)",IF(_xlpm.w<=Cfg_VDTotal,"✔ "&TEXT(_xlpm.w,"0.0%")&" worst cumulative ≤ "&TEXT(Cfg_VDTotal,"0%"),"⚠ "&TEXT(_xlpm.w,"0.0%")&" worst cumulative > "&TEXT(Cfg_VDTotal,"0%"))&IF(_xlpm.m<_xlpm.n," · "&(_xlpm.n-_xlpm.m)&" bus(es) missing data","")))),"— run study") -> — no equipment yet
A29: 9 | B29: Arc-flash incident energy | C29: IEEE 1584 | E29: =IFERROR(IF(COUNT('Arc Flash'!$M$24:$M$296)=0,IF(COUNTA(Equip_List)=0,"— no equipment yet","⚠ "&$H$15),IF(MAX('Arc Flash'!$M$24:$M$296)<=40,"✔ "&TEXT(MAX('Arc Flash'!$M$24:$M$296),"0.0")&" cal/cm² worst case","✘ "&TEXT(MAX('Arc Flash'!$M$24:$M$296),"0.0")&" cal/cm² >40")),"— run study") -> — no equipment yet
A30: 10 | B30: Feeder conductor / OCPD sizing | C30: {="NEC "&NECREF("310.16")&" / "&NECREF("240.6")} -> NEC 310.16 / 240.6 | E30: =IF('Feeder Schedule'!$B$5="","— add feeders",IF(N('Feeder Schedule'!$I$5)=0,"— enter feeder load","✔ "&COUNT('Feeder Schedule'!$I$5:$I$254)&" feeder(s) · first "&'Feeder Schedule'!$P$5&" / "&TEXT('Feeder Schedule'!$R$5,"#,##0")&" A")) -> — add feeders
A31: 11 | B31: Generator sizing | C31: {="NEC "&NECREF("700")&" / 701 / 702"} -> NEC 700 / 701 / 702 | E31: =IF(Tog_Gen<>"ON",IF(N(LC_GenTotal)>0,"⚠ "&TEXT(LC_GenTotal,"#,##0.0")&" kVA tagged Gen — add Generator (ribbon)","— not in project"),IFERROR(IF(N(Generator!$D$40)=0,"⚠ "&$H$10,IF(ISNUMBER(Generator!$D$45),"✔ "&TEXT(Generator!$D$45,"#,##0")&" kW","⚠ above largest standard size")),"— n/a")) -> — not in project
A32: 12 | B32: UPS sizing | C32: Critical power | E32: =IF(Tog_UPS<>"ON",IF(N(LC_UPSTotal)>0,"⚠ "&TEXT(LC_UPSTotal,"#,##0.0")&" kVA tagged UPS — add UPS (ribbon)","— not in project"),IFERROR(IF($G$11="◐ Incomplete","⚠ "&$H$11,"✔ "&$H$11),"— n/a")) -> — not in project
A33: 13 | B33: Panel load reconciliation | C33: Dashboard § Panel Load Reconciliation | E33: =_xlfn.LET(_xlpm.f,$F$359:$F$398,_xlpm.n,COUNTIF(_xlpm.f,"OK")+COUNTIF(_xlpm.f,"CHECK")+COUNTIF(_xlpm.f,"link not set"),_xlpm.bad,COUNTIF(_xlpm.f,"CHECK"),_xlpm.uns,COUNTIF(_xlpm.f,"link not set"),IF(_xlpm.n=0,"— no panels yet",IF(_xlpm.bad>0,"✘ "&_xlpm.bad&" panel(s) mismatch",IF(_xlpm.uns>0,"⚠ "&_xlpm.uns&" panel link(s) not set","✔ "&_xlpm.n&" panels reconcile")))) -> — no panels yet
A34: 14 | B34: Load Calc loads placed on panels | C34: Load Calc ▸ Send to Panel | E34: =_xlfn.LET(_xlpm.n,SUM('Load Calc'!$AG$7:$AG$40),_xlpm.k,SUM('Load Calc'!$AH$7:$AH$40),_xlpm.p,COUNTIF('Load Calc'!$X$41:$X$601,"Placed"),IF(_xlpm.n>0,"⚠ "&_xlpm.n&" load(s) not fully placed — "&TEXT(_xlpm.k,"#,##0.0")&" kVA",IF(_xlpm.p>0,"✔ "&_xlpm.p&" load(s) placed on panels","— no loads entered"))) -> — no loads entered
A36: ELECTRICAL SYSTEM
B38: System Voltage (select)
B39: Nominal Voltage (L-L) | C39: =IFERROR(VLOOKUP($C$38,Volt_Table,2,FALSE),"")
B40: Phase | C40: =IFERROR(VLOOKUP($C$38,Volt_Table,3,FALSE),"")
B41: Wires | C41: =IFERROR(VLOOKUP($C$38,Volt_Table,4,FALSE),"")
B42: Voltage (L-N) | C42: =IFERROR(VLOOKUP($C$38,Volt_Table,5,FALSE),"")
B43: Voltage Class | C43: =IFERROR(VLOOKUP($C$38,Volt_Table,6,FALSE),"")
A45: DESIGN DEFAULTS
B47: Branch Conductor Material | C47: Cu
B48: Feeder Conductor Material | C48: Cu
B49: Termination Temp Rating | C49: 75
B50: Conduit Type | C50: Steel
A52: CALCULATION MODULES
B54: Breaker Sizing | C54: ON | D54: (always on – core function)
B55: Wire Sizing | C55: ON
B56: Voltage Drop | C56: ON
B57: Short Circuit / AIC | C57: ON
B58: Standby Generator | C58: OFF | D58: (status only – set by ribbon ▸ New Generator)
B59: UPS | C59: OFF | D59: (status only – set by ribbon ▸ New UPS)
A61: UTILITY SOURCES — SHORT-CIRCUIT
B63: Parameter | C63: Source 1 | D63: Source 2 | E63: Source 3 | F63: Source 4
B64: Source Tag
B65: Utility / Provider
B66: Ownership
B67: Transformer Size (kVA)
B68: Primary Voltage (V)
B69: Secondary Voltage (L-L) | C69: =IF(OR(C$64="",Cfg_Volt=""),"",Cfg_Volt) | D69: =IF(OR(D$64="",Cfg_Volt=""),"",Cfg_Volt) | E69: =IF(OR(E$64="",Cfg_Volt=""),"",Cfg_Volt) | F69: =IF(OR(F$64="",Cfg_Volt=""),"",Cfg_Volt)
B70: Impedance (%Z)
B71: X/R Ratio
B72: Available Fault Current at Secondary (A)
B73: Secondary FLA (A) | C73: =IF(OR(C$64="",C$67="",C$69=""),"",C$67*1000/(IF(Cfg_Phase=1,1,SQRT(3))*C$69)) | D73: =IF(OR(D$64="",D$67="",D$69=""),"",D$67*1000/(IF(Cfg_Phase=1,1,SQRT(3))*D$69)) | E73: =IF(OR(E$64="",E$67="",E$69=""),"",E$67*1000/(IF(Cfg_Phase=1,1,SQRT(3))*E$69)) | F73: =IF(OR(F$64="",F$67="",F$69=""),"",F$67*1000/(IF(Cfg_Phase=1,1,SQRT(3))*F$69))
B74: Infinite-Bus Fault at Secondary (A) | C74: =IF(OR(C$64="",C$67="",C$69="",C$70="",C$70=0),"",C$67*1000/(IF(Cfg_Phase=1,1,SQRT(3))*C$69*C$70/100)) | D74: =IF(OR(D$64="",D$67="",D$69="",D$70="",D$70=0),"",D$67*1000/(IF(Cfg_Phase=1,1,SQRT(3))*D$69*D$70/100)) | E74: =IF(OR(E$64="",E$67="",E$69="",E$70="",E$70=0),"",E$67*1000/(IF(Cfg_Phase=1,1,SQRT(3))*E$69*E$70/100)) | F74: =IF(OR(F$64="",F$67="",F$69="",F$70="",F$70=0),"",F$67*1000/(IF(Cfg_Phase=1,1,SQRT(3))*F$69*F$70/100))
B75: Fault Duty incl. Bus Ties (A) | C75: {=IF(OR(C$64="",C$72=""),"",_xlfn.LET(_xlpm.s,C$64,_xlpm.own,C$72,_xlpm.a,Tie_SrcA,_xlpm.b,Tie_SrcB,_xlpm.act,(Tie_Tags<>"")*(_xlpm.a<>"")*(_xlpm.b<>"")*(_xlpm.a<>_xlpm.b)*((_xlpm.a=_xlpm.s)+(_xlpm.b=_xlpm.s)),_xlpm.oth,IF(_xlpm.a=_xlpm.s,_xlpm.b,_xlpm.a),_xlpm.os,IFERROR(_xlfn.XLOOKUP(_xlpm.oth,Util_Tags,Util_SCA),0),_xlpm.o,IF(ISNUMBER(_xlpm.os),_xlpm.os,0),_xlpm.par,Tie_Par*1,MAX(_xlpm.own+SUM(_xlpm.act*_xlpm.par*_xlpm.o),MAX(_xlpm.act*(1-_xlpm.par)*_xlpm.o))))} | D75: {=IF(OR(D$64="",D$72=""),"",_xlfn.LET(_xlpm.s,D$64,_xlpm.own,D$72,_xlpm.a,Tie_SrcA,_xlpm.b,Tie_SrcB,_xlpm.act,(Tie_Tags<>"")*(_xlpm.a<>"")*(_xlpm.b<>"")*(_xlpm.a<>_xlpm.b)*((_xlpm.a=_xlpm.s)+(_xlpm.b=_xlpm.s)),_xlpm.oth,IF(_xlpm.a=_xlpm.s,_xlpm.b,_xlpm.a),_xlpm.os,IFERROR(_xlfn.XLOOKUP(_xlpm.oth,Util_Tags,Util_SCA),0),_xlpm.o,IF(ISNUMBER(_xlpm.os),_xlpm.os,0),_xlpm.par,Tie_Par*1,MAX(_xlpm.own+SUM(_xlpm.act*_xlpm.par*_xlpm.o),MAX(_xlpm.act*(1-_xlpm.par)*_xlpm.o))))} | E75: {=IF(OR(E$64="",E$72=""),"",_xlfn.LET(_xlpm.s,E$64,_xlpm.own,E$72,_xlpm.a,Tie_SrcA,_xlpm.b,Tie_SrcB,_xlpm.act,(Tie_Tags<>"")*(_xlpm.a<>"")*(_xlpm.b<>"")*(_xlpm.a<>_xlpm.b)*((_xlpm.a=_xlpm.s)+(_xlpm.b=_xlpm.s)),_xlpm.oth,IF(_xlpm.a=_xlpm.s,_xlpm.b,_xlpm.a),_xlpm.os,IFERROR(_xlfn.XLOOKUP(_xlpm.oth,Util_Tags,Util_SCA),0),_xlpm.o,IF(ISNUMBER(_xlpm.os),_xlpm.os,0),_xlpm.par,Tie_Par*1,MAX(_xlpm.own+SUM(_xlpm.act*_xlpm.par*_xlpm.o),MAX(_xlpm.act*(1-_xlpm.par)*_xlpm.o))))} | F75: {=IF(OR(F$64="",F$72=""),"",_xlfn.LET(_xlpm.s,F$64,_xlpm.own,F$72,_xlpm.a,Tie_SrcA,_xlpm.b,Tie_SrcB,_xlpm.act,(Tie_Tags<>"")*(_xlpm.a<>"")*(_xlpm.b<>"")*(_xlpm.a<>_xlpm.b)*((_xlpm.a=_xlpm.s)+(_xlpm.b=_xlpm.s)),_xlpm.oth,IF(_xlpm.a=_xlpm.s,_xlpm.b,_xlpm.a),_xlpm.os,IFERROR(_xlfn.XLOOKUP(_xlpm.oth,Util_Tags,Util_SCA),0),_xlpm.o,IF(ISNUMBER(_xlpm.os),_xlpm.os,0),_xlpm.par,Tie_Par*1,MAX(_xlpm.own+SUM(_xlpm.act*_xlpm.par*_xlpm.o),MAX(_xlpm.act*(1-_xlpm.par)*_xlpm.o))))}
B76: Boards Served | C76: =IF(C$64="","",_xlfn.LET(_xlpm.n,COUNTIF(Equip_FedFrom,C$64),IF(_xlpm.n=0,"— none linked",_xlpm.n&" board"&IF(_xlpm.n=1,"","s")))) | D76: =IF(D$64="","",_xlfn.LET(_xlpm.n,COUNTIF(Equip_FedFrom,D$64),IF(_xlpm.n=0,"— none linked",_xlpm.n&" board"&IF(_xlpm.n=1,"","s")))) | E76: =IF(E$64="","",_xlfn.LET(_xlpm.n,COUNTIF(Equip_FedFrom,E$64),IF(_xlpm.n=0,"— none linked",_xlpm.n&" board"&IF(_xlpm.n=1,"","s")))) | F76: =IF(F$64="","",_xlfn.LET(_xlpm.n,COUNTIF(Equip_FedFrom,F$64),IF(_xlpm.n=0,"— none linked",_xlpm.n&" board"&IF(_xlpm.n=1,"","s"))))
B77: Source Check | C77: =IF(C$64="","",IF(C$72="","⚠ enter fault A",IF(C$74="","—",IF(C$72>C$74*1.001,"⚠ > infinite bus","✔ ≤ infinite bus")))) | D77: =IF(D$64="","",IF(D$72="","⚠ enter fault A",IF(D$74="","—",IF(D$72>D$74*1.001,"⚠ > infinite bus","✔ ≤ infinite bus")))) | E77: =IF(E$64="","",IF(E$72="","⚠ enter fault A",IF(E$74="","—",IF(E$72>E$74*1.001,"⚠ > infinite bus","✔ ≤ infinite bus")))) | F77: =IF(F$64="","",IF(F$72="","⚠ enter fault A",IF(F$74="","—",IF(F$72>F$74*1.001,"⚠ > infinite bus","✔ ≤ infinite bus"))))
B78: {="Multiple Services (NEC "&NECREF("230.2")&")"} -> Multiple Services (NEC 230.2) | C78: {=_xlfn.LET(_xlpm.n,COUNTIFS($C$64:$F$64,"<>",$C$66:$F$66,"<>Owner"),IF(_xlpm.n=0,"— no source tagged",IF(_xlpm.n=1,"✔ single service","⚠ "&_xlpm.n&(" services — confirm "&NECREF("230.2")&"(A)–(D) condition + "&NECREF("230.2")&"(E) directory"))))} -> — no source tagged
A80: BUS TIES — SPLIT-BUS / MAIN-TIE-MAIN
A82: # | B82: Tie Breaker Tag | C82: Bus A | D82: Bus B | E82: Normal | F82: Transfer | G82: Sources | H82: Check | I82: Fault Duty (A) | J82: Combined kVA
A83: 1 | G83: {=IF($B83="","",_xlfn.LET(_xlpm.a,INDEX(Tie_SrcA,$A83),_xlpm.b,INDEX(Tie_SrcB,$A83),IF(_xlpm.a="","?",_xlpm.a)&" ↔ "&IF(_xlpm.b="","?",_xlpm.b)))} | H83: {=IF($B83="","",_xlfn.LET(_xlpm.a,INDEX(Tie_SrcA,$A83),_xlpm.b,INDEX(Tie_SrcB,$A83),IF(OR($C83="",$D83=""),"⚠ select Bus A and Bus B",IF(OR(_xlpm.a="",_xlpm.b=""),"⚠ a bus does not trace back to a utility source",IF(_xlpm.a=_xlpm.b,"⚠ both buses on "&_xlpm.a&" — no source redundancy",_xlfn.LET(_xlpm.ka,N(_xlfn.XLOOKUP(_xlpm.a,Util_Tags,Util_KVA)),_xlpm.kb,N(_xlfn.XLOOKUP(_xlpm.b,Util_Tags,Util_KVA)),IF(OR(_xlpm.ka=0,_xlpm.kb=0),"⚠ enter source kVA",IF(MIN(_xlpm.ka,_xlpm.kb)>=N($J83),"✔ either source carries both buses","⚠ "&IF(_xlpm.ka=_xlpm.kb,_xlpm.a&" / "&_xlpm.b,IF(_xlpm.ka<_xlpm.kb,_xlpm.a,_xlpm.b))&" "&TEXT(MIN(_xlpm.ka,_xlpm.kb),"#,##0")&" kVA < "&TEXT($J83,"#,##0")&" kVA combined"))))))))} | I83: {=IF($B83="","",_xlfn.LET(_xlpm.a,INDEX(Tie_SrcA,$A83),_xlpm.b,INDEX(Tie_SrcB,$A83),_xlpm.fa,N(IFERROR(_xlfn.XLOOKUP(_xlpm.a,Util_Tags,Util_SCA),0)),_xlpm.fb,N(IFERROR(_xlfn.XLOOKUP(_xlpm.b,Util_Tags,Util_SCA),0)),IF(OR(_xlpm.a="",_xlpm.b="",_xlpm.a=_xlpm.b,_xlpm.fa=0,_xlpm.fb=0),"",IF(INDEX(Tie_Par,$A83),_xlpm.fa+_xlpm.fb,MAX(_xlpm.fa,_xlpm.fb)))))} | J83: =IF(OR($B83="",$C83="",$D83=""),"",SUMIFS(Equip_Demand,Equip_List,$C83)+SUMIFS(Equip_Demand,Equip_List,$D83))
A84: 2 | G84: {=IF($B84="","",_xlfn.LET(_xlpm.a,INDEX(Tie_SrcA,$A84),_xlpm.b,INDEX(Tie_SrcB,$A84),IF(_xlpm.a="","?",_xlpm.a)&" ↔ "&IF(_xlpm.b="","?",_xlpm.b)))} | H84: {=IF($B84="","",_xlfn.LET(_xlpm.a,INDEX(Tie_SrcA,$A84),_xlpm.b,INDEX(Tie_SrcB,$A84),IF(OR($C84="",$D84=""),"⚠ select Bus A and Bus B",IF(OR(_xlpm.a="",_xlpm.b=""),"⚠ a bus does not trace back to a utility source",IF(_xlpm.a=_xlpm.b,"⚠ both buses on "&_xlpm.a&" — no source redundancy",_xlfn.LET(_xlpm.ka,N(_xlfn.XLOOKUP(_xlpm.a,Util_Tags,Util_KVA)),_xlpm.kb,N(_xlfn.XLOOKUP(_xlpm.b,Util_Tags,Util_KVA)),IF(OR(_xlpm.ka=0,_xlpm.kb=0),"⚠ enter source kVA",IF(MIN(_xlpm.ka,_xlpm.kb)>=N($J84),"✔ either source carries both buses","⚠ "&IF(_xlpm.ka=_xlpm.kb,_xlpm.a&" / "&_xlpm.b,IF(_xlpm.ka<_xlpm.kb,_xlpm.a,_xlpm.b))&" "&TEXT(MIN(_xlpm.ka,_xlpm.kb),"#,##0")&" kVA < "&TEXT($J84,"#,##0")&" kVA combined"))))))))} | I84: {=IF($B84="","",_xlfn.LET(_xlpm.a,INDEX(Tie_SrcA,$A84),_xlpm.b,INDEX(Tie_SrcB,$A84),_xlpm.fa,N(IFERROR(_xlfn.XLOOKUP(_xlpm.a,Util_Tags,Util_SCA),0)),_xlpm.fb,N(IFERROR(_xlfn.XLOOKUP(_xlpm.b,Util_Tags,Util_SCA),0)),IF(OR(_xlpm.a="",_xlpm.b="",_xlpm.a=_xlpm.b,_xlpm.fa=0,_xlpm.fb=0),"",IF(INDEX(Tie_Par,$A84),_xlpm.fa+_xlpm.fb,MAX(_xlpm.fa,_xlpm.fb)))))} | J84: =IF(OR($B84="",$C84="",$D84=""),"",SUMIFS(Equip_Demand,Equip_List,$C84)+SUMIFS(Equip_Demand,Equip_List,$D84))
A85: 3 | G85: {=IF($B85="","",_xlfn.LET(_xlpm.a,INDEX(Tie_SrcA,$A85),_xlpm.b,INDEX(Tie_SrcB,$A85),IF(_xlpm.a="","?",_xlpm.a)&" ↔ "&IF(_xlpm.b="","?",_xlpm.b)))} | H85: {=IF($B85="","",_xlfn.LET(_xlpm.a,INDEX(Tie_SrcA,$A85),_xlpm.b,INDEX(Tie_SrcB,$A85),IF(OR($C85="",$D85=""),"⚠ select Bus A and Bus B",IF(OR(_xlpm.a="",_xlpm.b=""),"⚠ a bus does not trace back to a utility source",IF(_xlpm.a=_xlpm.b,"⚠ both buses on "&_xlpm.a&" — no source redundancy",_xlfn.LET(_xlpm.ka,N(_xlfn.XLOOKUP(_xlpm.a,Util_Tags,Util_KVA)),_xlpm.kb,N(_xlfn.XLOOKUP(_xlpm.b,Util_Tags,Util_KVA)),IF(OR(_xlpm.ka=0,_xlpm.kb=0),"⚠ enter source kVA",IF(MIN(_xlpm.ka,_xlpm.kb)>=N($J85),"✔ either source carries both buses","⚠ "&IF(_xlpm.ka=_xlpm.kb,_xlpm.a&" / "&_xlpm.b,IF(_xlpm.ka<_xlpm.kb,_xlpm.a,_xlpm.b))&" "&TEXT(MIN(_xlpm.ka,_xlpm.kb),"#,##0")&" kVA < "&TEXT($J85,"#,##0")&" kVA combined"))))))))} | I85: {=IF($B85="","",_xlfn.LET(_xlpm.a,INDEX(Tie_SrcA,$A85),_xlpm.b,INDEX(Tie_SrcB,$A85),_xlpm.fa,N(IFERROR(_xlfn.XLOOKUP(_xlpm.a,Util_Tags,Util_SCA),0)),_xlpm.fb,N(IFERROR(_xlfn.XLOOKUP(_xlpm.b,Util_Tags,Util_SCA),0)),IF(OR(_xlpm.a="",_xlpm.b="",_xlpm.a=_xlpm.b,_xlpm.fa=0,_xlpm.fb=0),"",IF(INDEX(Tie_Par,$A85),_xlpm.fa+_xlpm.fb,MAX(_xlpm.fa,_xlpm.fb)))))} | J85: =IF(OR($B85="",$C85="",$D85=""),"",SUMIFS(Equip_Demand,Equip_List,$C85)+SUMIFS(Equip_Demand,Equip_List,$D85))
A86: 4 | G86: {=IF($B86="","",_xlfn.LET(_xlpm.a,INDEX(Tie_SrcA,$A86),_xlpm.b,INDEX(Tie_SrcB,$A86),IF(_xlpm.a="","?",_xlpm.a)&" ↔ "&IF(_xlpm.b="","?",_xlpm.b)))} | H86: {=IF($B86="","",_xlfn.LET(_xlpm.a,INDEX(Tie_SrcA,$A86),_xlpm.b,INDEX(Tie_SrcB,$A86),IF(OR($C86="",$D86=""),"⚠ select Bus A and Bus B",IF(OR(_xlpm.a="",_xlpm.b=""),"⚠ a bus does not trace back to a utility source",IF(_xlpm.a=_xlpm.b,"⚠ both buses on "&_xlpm.a&" — no source redundancy",_xlfn.LET(_xlpm.ka,N(_xlfn.XLOOKUP(_xlpm.a,Util_Tags,Util_KVA)),_xlpm.kb,N(_xlfn.XLOOKUP(_xlpm.b,Util_Tags,Util_KVA)),IF(OR(_xlpm.ka=0,_xlpm.kb=0),"⚠ enter source kVA",IF(MIN(_xlpm.ka,_xlpm.kb)>=N($J86),"✔ either source carries both buses","⚠ "&IF(_xlpm.ka=_xlpm.kb,_xlpm.a&" / "&_xlpm.b,IF(_xlpm.ka<_xlpm.kb,_xlpm.a,_xlpm.b))&" "&TEXT(MIN(_xlpm.ka,_xlpm.kb),"#,##0")&" kVA < "&TEXT($J86,"#,##0")&" kVA combined"))))))))} | I86: {=IF($B86="","",_xlfn.LET(_xlpm.a,INDEX(Tie_SrcA,$A86),_xlpm.b,INDEX(Tie_SrcB,$A86),_xlpm.fa,N(IFERROR(_xlfn.XLOOKUP(_xlpm.a,Util_Tags,Util_SCA),0)),_xlpm.fb,N(IFERROR(_xlfn.XLOOKUP(_xlpm.b,Util_Tags,Util_SCA),0)),IF(OR(_xlpm.a="",_xlpm.b="",_xlpm.a=_xlpm.b,_xlpm.fa=0,_xlpm.fb=0),"",IF(INDEX(Tie_Par,$A86),_xlpm.fa+_xlpm.fb,MAX(_xlpm.fa,_xlpm.fb)))))} | J86: =IF(OR($B86="",$C86="",$D86=""),"",SUMIFS(Equip_Demand,Equip_List,$C86)+SUMIFS(Equip_Demand,Equip_List,$D86))
A88: ENGINE CONSTANTS (auto – do not edit)
B90: Branch ampacity column (>100 A) | C90: =IF(Cfg_BranchMat="Cu",IF(Cfg_Temp=60,3,IF(Cfg_Temp=75,4,5)),IF(Cfg_Temp=60,6,IF(Cfg_Temp=75,7,8))) -> 4
B91: Feeder ampacity column (>100 A) | C91: =IF(Cfg_FeederMat="Cu",IF(Cfg_Temp=60,3,IF(Cfg_Temp=75,4,5)),IF(Cfg_Temp=60,6,IF(Cfg_Temp=75,7,8))) -> 4
B92: Branch K (VD) | C92: =IF(Cfg_BranchMat="Cu",K_Cu,K_Al) -> 12.9
B93: Feeder K (VD) | C93: =IF(Cfg_FeederMat="Cu",K_Cu,K_Al) -> 12.9
B94: Branch C column (SC) | C94: =IF(Cfg_BranchMat="Cu",IF($C$96=1,9,11),IF($C$96=1,10,12)) -> 9
B95: Feeder C column (SC) | C95: =IF(Cfg_FeederMat="Cu",IF($C$96=1,9,11),IF($C$96=1,10,12)) -> 9
B96: Raceway magnetic? (SC) | C96: =IF(IFERROR(_xlfn.XLOOKUP(Cfg_Conduit,Race_Raceway,Race_Mag),"Y")="Y",1,0) -> 1
A98: EQUIPMENT REGISTRY
A100: Tag | B100: Type | C100: Voltage | D100: Fed From | E100: Mains | F100: Demand kVA | G100: Sheet Link | H100: Notes | I100: Feed Type | J100: Feeder Ckt / Space | K100: Std AIC (A) | L100: Alt Source | M100: Panel Conn. kVA | N100: Out Voltage | O100: Rating Ovr (A) | P100: Rating (A) | Q100: Demand (A) | R100: Feeder Length (ft) | S100: Xfmr Pri. Length (ft) | T100: Emerg. Feeder Length (ft) | U100: Feeder Material | V100: Conduit Type | W100: Existing Feeder?
A352: Type equipment straight into the next row — the shaded row is the one waiting for input. Rows appear as you add devices, so the table is only ever as long as the project. Tag, Type, Voltage, Fed From, Mains and Demand kVA are also written here automatically when a schedule is created from the ribbon. Voltage must be picked from the dropdown, or the Transformer, Feeder, Short Circuit and Voltage Drop schedules cannot resolve that device and will skip it. Fed From must match another Tag exactly, or say Source for the service entrance — the Feeder Schedule names any device whose Fed From does not resolve. Capacity is 250 devices (Cfg_MaxNodes on NEC_Data).
A354: PANEL LOAD RECONCILIATION
A355: What this does: every Panel Tag used anywhere on the Load Calc sheet is listed automatically, and the kVA assigned to it there is compared against the Connected kVA total on that panel's own schedule — catching loads assigned to a panel that were never built into it, and panels carrying loads the calc does not know about. HOW TO USE IT: set Type in column B, then copy the formula text that appears in column G and paste it into column D on the same row; that links the panel's own Connected total back here. A gold cell in column D means the link is not set yet. Status reads OK within the tolerance in K362, or CHECK when the two disagree — a CHECK row is highlighted across its full width. Feeds QA check #13 above. | J355: Connected-total cell by type (helper)
A357: Panel Tag | B357: Type | C357: Assigned kVA (Load Calc) | D357: Entered on Panel kVA | E357: Δ Assigned − Entered | F357: Status | G357: Link to paste into column D | H357: Notes
J358: Type | K358: Cell
A359: {=_xlfn.LET(_xlpm.t,_xlfn.VSTACK(LC_House[Panel Tag],LC_Dept[Panel Tag],LC_Refrig[Panel Tag],LC_Mech[Panel Tag],LC_Plumb[Panel Tag],LC_Kitchen[Panel Tag],LC_Elev[Panel Tag],LC_EV[Panel Tag],LC_Data[Panel Tag],LC_Site[Panel Tag],LC_Fire[Panel Tag],LC_Process[Panel Tag]),IF(SUMPRODUCT(--(_xlpm.t<>""))=0,"— no panel tags assigned —",_xlfn._xlws.SORT(_xlfn.UNIQUE(_xlfn._xlws.FILTER(_xlpm.t,_xlpm.t<>"")))))} -> — no panel tags assigned — | B359: =IF(OR($A359="",LEFT($A359,1)="—"),"",IFERROR(_xlfn.XLOOKUP($A359,$A$101:$A$350,$B$101:$B$350,"not in registry"),"")) | C359: =IF(OR($A359="",LEFT($A359,1)="—"),"",SUMIF(LC_House[Panel Tag],$A359,LC_House[Total kVA])+SUMIF(LC_Dept[Panel Tag],$A359,LC_Dept[Total kVA])+SUMIF(LC_Refrig[Panel Tag],$A359,LC_Refrig[Total kVA])+SUMIF(LC_Mech[Panel Tag],$A359,LC_Mech[Total kVA])+SUMIF(LC_Plumb[Panel Tag],$A359,LC_Plumb[Total kVA])+SUMIF(LC_Kitchen[Panel Tag],$A359,LC_Kitchen[Total kVA])+SUMIF(LC_Elev[Panel Tag],$A359,LC_Elev[Total kVA])+SUMIF(LC_EV[Panel Tag],$A359,LC_EV[Total kVA])+SUMIF(LC_Data[Panel Tag],$A359,LC_Data[Total kVA])+SUMIF(LC_Site[Panel Tag],$A359,LC_Site[Total kVA])+SUMIF(LC_Fire[Panel Tag],$A359,LC_Fire[Total kVA])+SUMIF(LC_Process[Panel Tag],$A359,LC_Process[Total kVA])) | D359: =IF(OR($A359="",LEFT($A359,1)="—"),"",IFERROR(_xlfn.XLOOKUP($A359,$A$101:$A$350,$M$101:$M$350,""),"")) | E359: =IF(OR(NOT(ISNUMBER($C359)),NOT(ISNUMBER($D359))),"",$C359-$D359) | F359: =IF(NOT(ISNUMBER($C359)),"",IF(NOT(ISNUMBER($D359)),"link not set",IF(ABS($E359)<=$K$363,"OK","CHECK"))) | G359: =IF(NOT(ISNUMBER($C359)),"",IF($B359="","← set Type in column B",IFERROR("='"&$A359&"'!"&VLOOKUP($B359,$J$359:$K$361,2,FALSE),"← Type not recognized"))) | J359: Panelboard | K359: M69
B360: =IF(OR($A360="",LEFT($A360,1)="—"),"",IFERROR(_xlfn.XLOOKUP($A360,$A$101:$A$350,$B$101:$B$350,"not in registry"),"")) | C360: =IF(OR($A360="",LEFT($A360,1)="—"),"",SUMIF(LC_House[Panel Tag],$A360,LC_House[Total kVA])+SUMIF(LC_Dept[Panel Tag],$A360,LC_Dept[Total kVA])+SUMIF(LC_Refrig[Panel Tag],$A360,LC_Refrig[Total kVA])+SUMIF(LC_Mech[Panel Tag],$A360,LC_Mech[Total kVA])+SUMIF(LC_Plumb[Panel Tag],$A360,LC_Plumb[Total kVA])+SUMIF(LC_Kitchen[Panel Tag],$A360,LC_Kitchen[Total kVA])+SUMIF(LC_Elev[Panel Tag],$A360,LC_Elev[Total kVA])+SUMIF(LC_EV[Panel Tag],$A360,LC_EV[Total kVA])+SUMIF(LC_Data[Panel Tag],$A360,LC_Data[Total kVA])+SUMIF(LC_Site[Panel Tag],$A360,LC_Site[Total kVA])+SUMIF(LC_Fire[Panel Tag],$A360,LC_Fire[Total kVA])+SUMIF(LC_Process[Panel Tag],$A360,LC_Process[Total kVA])) | D360: =IF(OR($A360="",LEFT($A360,1)="—"),"",IFERROR(_xlfn.XLOOKUP($A360,$A$101:$A$350,$M$101:$M$350,""),"")) | E360: =IF(OR(NOT(ISNUMBER($C360)),NOT(ISNUMBER($D360))),"",$C360-$D360) | F360: =IF(NOT(ISNUMBER($C360)),"",IF(NOT(ISNUMBER($D360)),"link not set",IF(ABS($E360)<=$K$363,"OK","CHECK"))) | G360: =IF(NOT(ISNUMBER($C360)),"",IF($B360="","← set Type in column B",IFERROR("='"&$A360&"'!"&VLOOKUP($B360,$J$359:$K$361,2,FALSE),"← Type not recognized"))) | J360: MCC | K360: C47
B361: =IF(OR($A361="",LEFT($A361,1)="—"),"",IFERROR(_xlfn.XLOOKUP($A361,$A$101:$A$350,$B$101:$B$350,"not in registry"),"")) | C361: =IF(OR($A361="",LEFT($A361,1)="—"),"",SUMIF(LC_House[Panel Tag],$A361,LC_House[Total kVA])+SUMIF(LC_Dept[Panel Tag],$A361,LC_Dept[Total kVA])+SUMIF(LC_Refrig[Panel Tag],$A361,LC_Refrig[Total kVA])+SUMIF(LC_Mech[Panel Tag],$A361,LC_Mech[Total kVA])+SUMIF(LC_Plumb[Panel Tag],$A361,LC_Plumb[Total kVA])+SUMIF(LC_Kitchen[Panel Tag],$A361,LC_Kitchen[Total kVA])+SUMIF(LC_Elev[Panel Tag],$A361,LC_Elev[Total kVA])+SUMIF(LC_EV[Panel Tag],$A361,LC_EV[Total kVA])+SUMIF(LC_Data[Panel Tag],$A361,LC_Data[Total kVA])+SUMIF(LC_Site[Panel Tag],$A361,LC_Site[Total kVA])+SUMIF(LC_Fire[Panel Tag],$A361,LC_Fire[Total kVA])+SUMIF(LC_Process[Panel Tag],$A361,LC_Process[Total kVA])) | D361: =IF(OR($A361="",LEFT($A361,1)="—"),"",IFERROR(_xlfn.XLOOKUP($A361,$A$101:$A$350,$M$101:$M$350,""),"")) | E361: =IF(OR(NOT(ISNUMBER($C361)),NOT(ISNUMBER($D361))),"",$C361-$D361) | F361: =IF(NOT(ISNUMBER($C361)),"",IF(NOT(ISNUMBER($D361)),"link not set",IF(ABS($E361)<=$K$363,"OK","CHECK"))) | G361: =IF(NOT(ISNUMBER($C361)),"",IF($B361="","← set Type in column B",IFERROR("='"&$A361&"'!"&VLOOKUP($B361,$J$359:$K$361,2,FALSE),"← Type not recognized"))) | J361: Switchboard | K361: C49
B362: =IF(OR($A362="",LEFT($A362,1)="—"),"",IFERROR(_xlfn.XLOOKUP($A362,$A$101:$A$350,$B$101:$B$350,"not in registry"),"")) | C362: =IF(OR($A362="",LEFT($A362,1)="—"),"",SUMIF(LC_House[Panel Tag],$A362,LC_House[Total kVA])+SUMIF(LC_Dept[Panel Tag],$A362,LC_Dept[Total kVA])+SUMIF(LC_Refrig[Panel Tag],$A362,LC_Refrig[Total kVA])+SUMIF(LC_Mech[Panel Tag],$A362,LC_Mech[Total kVA])+SUMIF(LC_Plumb[Panel Tag],$A362,LC_Plumb[Total kVA])+SUMIF(LC_Kitchen[Panel Tag],$A362,LC_Kitchen[Total kVA])+SUMIF(LC_Elev[Panel Tag],$A362,LC_Elev[Total kVA])+SUMIF(LC_EV[Panel Tag],$A362,LC_EV[Total kVA])+SUMIF(LC_Data[Panel Tag],$A362,LC_Data[Total kVA])+SUMIF(LC_Site[Panel Tag],$A362,LC_Site[Total kVA])+SUMIF(LC_Fire[Panel Tag],$A362,LC_Fire[Total kVA])+SUMIF(LC_Process[Panel Tag],$A362,LC_Process[Total kVA])) | D362: =IF(OR($A362="",LEFT($A362,1)="—"),"",IFERROR(_xlfn.XLOOKUP($A362,$A$101:$A$350,$M$101:$M$350,""),"")) | E362: =IF(OR(NOT(ISNUMBER($C362)),NOT(ISNUMBER($D362))),"",$C362-$D362) | F362: =IF(NOT(ISNUMBER($C362)),"",IF(NOT(ISNUMBER($D362)),"link not set",IF(ABS($E362)<=$K$363,"OK","CHECK"))) | G362: =IF(NOT(ISNUMBER($C362)),"",IF($B362="","← set Type in column B",IFERROR("='"&$A362&"'!"&VLOOKUP($B362,$J$359:$K$361,2,FALSE),"← Type not recognized")))
B363: =IF(OR($A363="",LEFT($A363,1)="—"),"",IFERROR(_xlfn.XLOOKUP($A363,$A$101:$A$350,$B$101:$B$350,"not in registry"),"")) | C363: =IF(OR($A363="",LEFT($A363,1)="—"),"",SUMIF(LC_House[Panel Tag],$A363,LC_House[Total kVA])+SUMIF(LC_Dept[Panel Tag],$A363,LC_Dept[Total kVA])+SUMIF(LC_Refrig[Panel Tag],$A363,LC_Refrig[Total kVA])+SUMIF(LC_Mech[Panel Tag],$A363,LC_Mech[Total kVA])+SUMIF(LC_Plumb[Panel Tag],$A363,LC_Plumb[Total kVA])+SUMIF(LC_Kitchen[Panel Tag],$A363,LC_Kitchen[Total kVA])+SUMIF(LC_Elev[Panel Tag],$A363,LC_Elev[Total kVA])+SUMIF(LC_EV[Panel Tag],$A363,LC_EV[Total kVA])+SUMIF(LC_Data[Panel Tag],$A363,LC_Data[Total kVA])+SUMIF(LC_Site[Panel Tag],$A363,LC_Site[Total kVA])+SUMIF(LC_Fire[Panel Tag],$A363,LC_Fire[Total kVA])+SUMIF(LC_Process[Panel Tag],$A363,LC_Process[Total kVA])) | D363: =IF(OR($A363="",LEFT($A363,1)="—"),"",IFERROR(_xlfn.XLOOKUP($A363,$A$101:$A$350,$M$101:$M$350,""),"")) | E363: =IF(OR(NOT(ISNUMBER($C363)),NOT(ISNUMBER($D363))),"",$C363-$D363) | F363: =IF(NOT(ISNUMBER($C363)),"",IF(NOT(ISNUMBER($D363)),"link not set",IF(ABS($E363)<=$K$363,"OK","CHECK"))) | G363: =IF(NOT(ISNUMBER($C363)),"",IF($B363="","← set Type in column B",IFERROR("='"&$A363&"'!"&VLOOKUP($B363,$J$359:$K$361,2,FALSE),"← Type not recognized"))) | J363: Match tolerance (kVA) | K363: 0.1
B364: =IF(OR($A364="",LEFT($A364,1)="—"),"",IFERROR(_xlfn.XLOOKUP($A364,$A$101:$A$350,$B$101:$B$350,"not in registry"),"")) | C364: =IF(OR($A364="",LEFT($A364,1)="—"),"",SUMIF(LC_House[Panel Tag],$A364,LC_House[Total kVA])+SUMIF(LC_Dept[Panel Tag],$A364,LC_Dept[Total kVA])+SUMIF(LC_Refrig[Panel Tag],$A364,LC_Refrig[Total kVA])+SUMIF(LC_Mech[Panel Tag],$A364,LC_Mech[Total kVA])+SUMIF(LC_Plumb[Panel Tag],$A364,LC_Plumb[Total kVA])+SUMIF(LC_Kitchen[Panel Tag],$A364,LC_Kitchen[Total kVA])+SUMIF(LC_Elev[Panel Tag],$A364,LC_Elev[Total kVA])+SUMIF(LC_EV[Panel Tag],$A364,LC_EV[Total kVA])+SUMIF(LC_Data[Panel Tag],$A364,LC_Data[Total kVA])+SUMIF(LC_Site[Panel Tag],$A364,LC_Site[Total kVA])+SUMIF(LC_Fire[Panel Tag],$A364,LC_Fire[Total kVA])+SUMIF(LC_Process[Panel Tag],$A364,LC_Process[Total kVA])) | D364: =IF(OR($A364="",LEFT($A364,1)="—"),"",IFERROR(_xlfn.XLOOKUP($A364,$A$101:$A$350,$M$101:$M$350,""),"")) | E364: =IF(OR(NOT(ISNUMBER($C364)),NOT(ISNUMBER($D364))),"",$C364-$D364) | F364: =IF(NOT(ISNUMBER($C364)),"",IF(NOT(ISNUMBER($D364)),"link not set",IF(ABS($E364)<=$K$363,"OK","CHECK"))) | G364: =IF(NOT(ISNUMBER($C364)),"",IF($B364="","← set Type in column B",IFERROR("='"&$A364&"'!"&VLOOKUP($B364,$J$359:$K$361,2,FALSE),"← Type not recognized")))
B365: =IF(OR($A365="",LEFT($A365,1)="—"),"",IFERROR(_xlfn.XLOOKUP($A365,$A$101:$A$350,$B$101:$B$350,"not in registry"),"")) | C365: =IF(OR($A365="",LEFT($A365,1)="—"),"",SUMIF(LC_House[Panel Tag],$A365,LC_House[Total kVA])+SUMIF(LC_Dept[Panel Tag],$A365,LC_Dept[Total kVA])+SUMIF(LC_Refrig[Panel Tag],$A365,LC_Refrig[Total kVA])+SUMIF(LC_Mech[Panel Tag],$A365,LC_Mech[Total kVA])+SUMIF(LC_Plumb[Panel Tag],$A365,LC_Plumb[Total kVA])+SUMIF(LC_Kitchen[Panel Tag],$A365,LC_Kitchen[Total kVA])+SUMIF(LC_Elev[Panel Tag],$A365,LC_Elev[Total kVA])+SUMIF(LC_EV[Panel Tag],$A365,LC_EV[Total kVA])+SUMIF(LC_Data[Panel Tag],$A365,LC_Data[Total kVA])+SUMIF(LC_Site[Panel Tag],$A365,LC_Site[Total kVA])+SUMIF(LC_Fire[Panel Tag],$A365,LC_Fire[Total kVA])+SUMIF(LC_Process[Panel Tag],$A365,LC_Process[Total kVA])) | D365: =IF(OR($A365="",LEFT($A365,1)="—"),"",IFERROR(_xlfn.XLOOKUP($A365,$A$101:$A$350,$M$101:$M$350,""),"")) | E365: =IF(OR(NOT(ISNUMBER($C365)),NOT(ISNUMBER($D365))),"",$C365-$D365) | F365: =IF(NOT(ISNUMBER($C365)),"",IF(NOT(ISNUMBER($D365)),"link not set",IF(ABS($E365)<=$K$363,"OK","CHECK"))) | G365: =IF(NOT(ISNUMBER($C365)),"",IF($B365="","← set Type in column B",IFERROR("='"&$A365&"'!"&VLOOKUP($B365,$J$359:$K$361,2,FALSE),"← Type not recognized")))
B366: =IF(OR($A366="",LEFT($A366,1)="—"),"",IFERROR(_xlfn.XLOOKUP($A366,$A$101:$A$350,$B$101:$B$350,"not in registry"),"")) | C366: =IF(OR($A366="",LEFT($A366,1)="—"),"",SUMIF(LC_House[Panel Tag],$A366,LC_House[Total kVA])+SUMIF(LC_Dept[Panel Tag],$A366,LC_Dept[Total kVA])+SUMIF(LC_Refrig[Panel Tag],$A366,LC_Refrig[Total kVA])+SUMIF(LC_Mech[Panel Tag],$A366,LC_Mech[Total kVA])+SUMIF(LC_Plumb[Panel Tag],$A366,LC_Plumb[Total kVA])+SUMIF(LC_Kitchen[Panel Tag],$A366,LC_Kitchen[Total kVA])+SUMIF(LC_Elev[Panel Tag],$A366,LC_Elev[Total kVA])+SUMIF(LC_EV[Panel Tag],$A366,LC_EV[Total kVA])+SUMIF(LC_Data[Panel Tag],$A366,LC_Data[Total kVA])+SUMIF(LC_Site[Panel Tag],$A366,LC_Site[Total kVA])+SUMIF(LC_Fire[Panel Tag],$A366,LC_Fire[Total kVA])+SUMIF(LC_Process[Panel Tag],$A366,LC_Process[Total kVA])) | D366: =IF(OR($A366="",LEFT($A366,1)="—"),"",IFERROR(_xlfn.XLOOKUP($A366,$A$101:$A$350,$M$101:$M$350,""),"")) | E366: =IF(OR(NOT(ISNUMBER($C366)),NOT(ISNUMBER($D366))),"",$C366-$D366) | F366: =IF(NOT(ISNUMBER($C366)),"",IF(NOT(ISNUMBER($D366)),"link not set",IF(ABS($E366)<=$K$363,"OK","CHECK"))) | G366: =IF(NOT(ISNUMBER($C366)),"",IF($B366="","← set Type in column B",IFERROR("='"&$A366&"'!"&VLOOKUP($B366,$J$359:$K$361,2,FALSE),"← Type not recognized")))
B367: =IF(OR($A367="",LEFT($A367,1)="—"),"",IFERROR(_xlfn.XLOOKUP($A367,$A$101:$A$350,$B$101:$B$350,"not in registry"),"")) | C367: =IF(OR($A367="",LEFT($A367,1)="—"),"",SUMIF(LC_House[Panel Tag],$A367,LC_House[Total kVA])+SUMIF(LC_Dept[Panel Tag],$A367,LC_Dept[Total kVA])+SUMIF(LC_Refrig[Panel Tag],$A367,LC_Refrig[Total kVA])+SUMIF(LC_Mech[Panel Tag],$A367,LC_Mech[Total kVA])+SUMIF(LC_Plumb[Panel Tag],$A367,LC_Plumb[Total kVA])+SUMIF(LC_Kitchen[Panel Tag],$A367,LC_Kitchen[Total kVA])+SUMIF(LC_Elev[Panel Tag],$A367,LC_Elev[Total kVA])+SUMIF(LC_EV[Panel Tag],$A367,LC_EV[Total kVA])+SUMIF(LC_Data[Panel Tag],$A367,LC_Data[Total kVA])+SUMIF(LC_Site[Panel Tag],$A367,LC_Site[Total kVA])+SUMIF(LC_Fire[Panel Tag],$A367,LC_Fire[Total kVA])+SUMIF(LC_Process[Panel Tag],$A367,LC_Process[Total kVA])) | D367: =IF(OR($A367="",LEFT($A367,1)="—"),"",IFERROR(_xlfn.XLOOKUP($A367,$A$101:$A$350,$M$101:$M$350,""),"")) | E367: =IF(OR(NOT(ISNUMBER($C367)),NOT(ISNUMBER($D367))),"",$C367-$D367) | F367: =IF(NOT(ISNUMBER($C367)),"",IF(NOT(ISNUMBER($D367)),"link not set",IF(ABS($E367)<=$K$363,"OK","CHECK"))) | G367: =IF(NOT(ISNUMBER($C367)),"",IF($B367="","← set Type in column B",IFERROR("='"&$A367&"'!"&VLOOKUP($B367,$J$359:$K$361,2,FALSE),"← Type not recognized")))
B368: =IF(OR($A368="",LEFT($A368,1)="—"),"",IFERROR(_xlfn.XLOOKUP($A368,$A$101:$A$350,$B$101:$B$350,"not in registry"),"")) | C368: =IF(OR($A368="",LEFT($A368,1)="—"),"",SUMIF(LC_House[Panel Tag],$A368,LC_House[Total kVA])+SUMIF(LC_Dept[Panel Tag],$A368,LC_Dept[Total kVA])+SUMIF(LC_Refrig[Panel Tag],$A368,LC_Refrig[Total kVA])+SUMIF(LC_Mech[Panel Tag],$A368,LC_Mech[Total kVA])+SUMIF(LC_Plumb[Panel Tag],$A368,LC_Plumb[Total kVA])+SUMIF(LC_Kitchen[Panel Tag],$A368,LC_Kitchen[Total kVA])+SUMIF(LC_Elev[Panel Tag],$A368,LC_Elev[Total kVA])+SUMIF(LC_EV[Panel Tag],$A368,LC_EV[Total kVA])+SUMIF(LC_Data[Panel Tag],$A368,LC_Data[Total kVA])+SUMIF(LC_Site[Panel Tag],$A368,LC_Site[Total kVA])+SUMIF(LC_Fire[Panel Tag],$A368,LC_Fire[Total kVA])+SUMIF(LC_Process[Panel Tag],$A368,LC_Process[Total kVA])) | D368: =IF(OR($A368="",LEFT($A368,1)="—"),"",IFERROR(_xlfn.XLOOKUP($A368,$A$101:$A$350,$M$101:$M$350,""),"")) | E368: =IF(OR(NOT(ISNUMBER($C368)),NOT(ISNUMBER($D368))),"",$C368-$D368) | F368: =IF(NOT(ISNUMBER($C368)),"",IF(NOT(ISNUMBER($D368)),"link not set",IF(ABS($E368)<=$K$363,"OK","CHECK"))) | G368: =IF(NOT(ISNUMBER($C368)),"",IF($B368="","← set Type in column B",IFERROR("='"&$A368&"'!"&VLOOKUP($B368,$J$359:$K$361,2,FALSE),"← Type not recognized")))
B369: =IF(OR($A369="",LEFT($A369,1)="—"),"",IFERROR(_xlfn.XLOOKUP($A369,$A$101:$A$350,$B$101:$B$350,"not in registry"),"")) | C369: =IF(OR($A369="",LEFT($A369,1)="—"),"",SUMIF(LC_House[Panel Tag],$A369,LC_House[Total kVA])+SUMIF(LC_Dept[Panel Tag],$A369,LC_Dept[Total kVA])+SUMIF(LC_Refrig[Panel Tag],$A369,LC_Refrig[Total kVA])+SUMIF(LC_Mech[Panel Tag],$A369,LC_Mech[Total kVA])+SUMIF(LC_Plumb[Panel Tag],$A369,LC_Plumb[Total kVA])+SUMIF(LC_Kitchen[Panel Tag],$A369,LC_Kitchen[Total kVA])+SUMIF(LC_Elev[Panel Tag],$A369,LC_Elev[Total kVA])+SUMIF(LC_EV[Panel Tag],$A369,LC_EV[Total kVA])+SUMIF(LC_Data[Panel Tag],$A369,LC_Data[Total kVA])+SUMIF(LC_Site[Panel Tag],$A369,LC_Site[Total kVA])+SUMIF(LC_Fire[Panel Tag],$A369,LC_Fire[Total kVA])+SUMIF(LC_Process[Panel Tag],$A369,LC_Process[Total kVA])) | D369: =IF(OR($A369="",LEFT($A369,1)="—"),"",IFERROR(_xlfn.XLOOKUP($A369,$A$101:$A$350,$M$101:$M$350,""),"")) | E369: =IF(OR(NOT(ISNUMBER($C369)),NOT(ISNUMBER($D369))),"",$C369-$D369) | F369: =IF(NOT(ISNUMBER($C369)),"",IF(NOT(ISNUMBER($D369)),"link not set",IF(ABS($E369)<=$K$363,"OK","CHECK"))) | G369: =IF(NOT(ISNUMBER($C369)),"",IF($B369="","← set Type in column B",IFERROR("='"&$A369&"'!"&VLOOKUP($B369,$J$359:$K$361,2,FALSE),"← Type not recognized")))
B370: =IF(OR($A370="",LEFT($A370,1)="—"),"",IFERROR(_xlfn.XLOOKUP($A370,$A$101:$A$350,$B$101:$B$350,"not in registry"),"")) | C370: =IF(OR($A370="",LEFT($A370,1)="—"),"",SUMIF(LC_House[Panel Tag],$A370,LC_House[Total kVA])+SUMIF(LC_Dept[Panel Tag],$A370,LC_Dept[Total kVA])+SUMIF(LC_Refrig[Panel Tag],$A370,LC_Refrig[Total kVA])+SUMIF(LC_Mech[Panel Tag],$A370,LC_Mech[Total kVA])+SUMIF(LC_Plumb[Panel Tag],$A370,LC_Plumb[Total kVA])+SUMIF(LC_Kitchen[Panel Tag],$A370,LC_Kitchen[Total kVA])+SUMIF(LC_Elev[Panel Tag],$A370,LC_Elev[Total kVA])+SUMIF(LC_EV[Panel Tag],$A370,LC_EV[Total kVA])+SUMIF(LC_Data[Panel Tag],$A370,LC_Data[Total kVA])+SUMIF(LC_Site[Panel Tag],$A370,LC_Site[Total kVA])+SUMIF(LC_Fire[Panel Tag],$A370,LC_Fire[Total kVA])+SUMIF(LC_Process[Panel Tag],$A370,LC_Process[Total kVA])) | D370: =IF(OR($A370="",LEFT($A370,1)="—"),"",IFERROR(_xlfn.XLOOKUP($A370,$A$101:$A$350,$M$101:$M$350,""),"")) | E370: =IF(OR(NOT(ISNUMBER($C370)),NOT(ISNUMBER($D370))),"",$C370-$D370) | F370: =IF(NOT(ISNUMBER($C370)),"",IF(NOT(ISNUMBER($D370)),"link not set",IF(ABS($E370)<=$K$363,"OK","CHECK"))) | G370: =IF(NOT(ISNUMBER($C370)),"",IF($B370="","← set Type in column B",IFERROR("='"&$A370&"'!"&VLOOKUP($B370,$J$359:$K$361,2,FALSE),"← Type not recognized")))
B371: =IF(OR($A371="",LEFT($A371,1)="—"),"",IFERROR(_xlfn.XLOOKUP($A371,$A$101:$A$350,$B$101:$B$350,"not in registry"),"")) | C371: =IF(OR($A371="",LEFT($A371,1)="—"),"",SUMIF(LC_House[Panel Tag],$A371,LC_House[Total kVA])+SUMIF(LC_Dept[Panel Tag],$A371,LC_Dept[Total kVA])+SUMIF(LC_Refrig[Panel Tag],$A371,LC_Refrig[Total kVA])+SUMIF(LC_Mech[Panel Tag],$A371,LC_Mech[Total kVA])+SUMIF(LC_Plumb[Panel Tag],$A371,LC_Plumb[Total kVA])+SUMIF(LC_Kitchen[Panel Tag],$A371,LC_Kitchen[Total kVA])+SUMIF(LC_Elev[Panel Tag],$A371,LC_Elev[Total kVA])+SUMIF(LC_EV[Panel Tag],$A371,LC_EV[Total kVA])+SUMIF(LC_Data[Panel Tag],$A371,LC_Data[Total kVA])+SUMIF(LC_Site[Panel Tag],$A371,LC_Site[Total kVA])+SUMIF(LC_Fire[Panel Tag],$A371,LC_Fire[Total kVA])+SUMIF(LC_Process[Panel Tag],$A371,LC_Process[Total kVA])) | D371: =IF(OR($A371="",LEFT($A371,1)="—"),"",IFERROR(_xlfn.XLOOKUP($A371,$A$101:$A$350,$M$101:$M$350,""),"")) | E371: =IF(OR(NOT(ISNUMBER($C371)),NOT(ISNUMBER($D371))),"",$C371-$D371) | F371: =IF(NOT(ISNUMBER($C371)),"",IF(NOT(ISNUMBER($D371)),"link not set",IF(ABS($E371)<=$K$363,"OK","CHECK"))) | G371: =IF(NOT(ISNUMBER($C371)),"",IF($B371="","← set Type in column B",IFERROR("='"&$A371&"'!"&VLOOKUP($B371,$J$359:$K$361,2,FALSE),"← Type not recognized")))
...

Sheet Load Calc
A1: SERVICE LOAD CALCULATION
B2: Project: | C2: =IF(Dashboard!B7="","—",Dashboard!B7) -> — | H2: Service Voltage: | I2: =IF(Dashboard!$C$38="","",Dashboard!$C$38) | N2: Date: | O2: =IF(Dashboard!B12="",TODAY(),Dashboard!B12) -> 46322
A4: BASELINE SQUARE FOOTAGE
AA5: SECTION REGISTRY — ribbon-controlled (does not print)
AA6: Section | AB6: Table | AC6: Include | AD6: Connected kVA | AE6: Gen tag list | AF6: UPS tag list | AG6: Not placed (loads) | AH6: Not placed (kVA)
B7: Space Type | C7: SF per Floor | D7: Floors | E7: Total SF | F7: LPD (W/ft²) | G7: Lighting W | AA7: 1 Site / Exterior | AB7: LC_Site | AC7: Yes | AD7: =IF($AC7="No","n/a",SUM(LC_Site[Total kVA])) -> 0 | AE7: Y | AF7: Y | AG7: =IF($AC7="No",0,COUNTIFS(LC_Site[Status],"Unplaced")+COUNTIFS(LC_Site[Status],"Partial")) -> 0 | AH7: =IF($AC7="No",0,SUMIFS(LC_Site[Total kVA],LC_Site[Status],"Unplaced")+SUMIFS(LC_Site[Total kVA],LC_Site[Status],"Partial")) -> 0
E8: =IF(OR(LC_Areas[[#This Row],[SF per Floor]]="",LC_Areas[[#This Row],[Floors]]=""),"",LC_Areas[[#This Row],[SF per Floor]]*LC_Areas[[#This Row],[Floors]]) | F8: =IF(LC_Areas[[#This Row],[Space Type]]="","",_xlfn.LET(_xlpm.k,IF(Cfg_Energy_Code="SEC (Seattle)",3,2),_xlpm.v,IFERROR(VLOOKUP(LC_Areas[[#This Row],[Space Type]],LPD_BldgArea_Table,_xlpm.k,FALSE),IFERROR(VLOOKUP(LC_Areas[[#This Row],[Space Type]],LPD_Space_Table,_xlpm.k,FALSE),"")),IF(_xlpm.v="","not listed in "&Cfg_Energy_Code,_xlpm.v))) | G8: =IF(OR(LC_Areas[[#This Row],[Total SF]]="",NOT(ISNUMBER(LC_Areas[[#This Row],[LPD (W/ft²)]]))),"",LC_Areas[[#This Row],[Total SF]]*LC_Areas[[#This Row],[LPD (W/ft²)]]) | AA8: 2 House / Misc | AB8: LC_House | AC8: Yes | AD8: =IF($AC8="No","n/a",SUM(LC_House[Total kVA])) -> 0 | AE8: =IF(Generator!$B$53="","",Generator!$B$53) -> GEN-1 | AF8: =IF(UPS!$B$48="","",UPS!$B$48) -> UPS-1 | AG8: =IF($AC8="No",0,COUNTIFS(LC_House[Status],"Unplaced")+COUNTIFS(LC_House[Status],"Partial")) -> 0 | AH8: =IF($AC8="No",0,SUMIFS(LC_House[Total kVA],LC_House[Status],"Unplaced")+SUMIFS(LC_House[Total kVA],LC_House[Status],"Partial")) -> 0
B9: TOTAL BUILDING SF | E9: =SUM(LC_Areas[Total SF]) -> 0 | F9: =IF(N(E9)=0,"",G9/E9) | G9: =SUM(LC_Areas[Lighting W]) -> 0 | AA9: 3 Department / Owner | AB9: LC_Dept | AC9: Yes | AD9: =IF($AC9="No","n/a",SUM(LC_Dept[Total kVA])) -> 0 | AE9: =IF(Generator!$B$54="","",Generator!$B$54) | AF9: =IF(UPS!$B$49="","",UPS!$B$49) | AG9: =IF($AC9="No",0,COUNTIFS(LC_Dept[Status],"Unplaced")+COUNTIFS(LC_Dept[Status],"Partial")) -> 0 | AH9: =IF($AC9="No",0,SUMIFS(LC_Dept[Total kVA],LC_Dept[Status],"Unplaced")+SUMIFS(LC_Dept[Total kVA],LC_Dept[Status],"Partial")) -> 0
AA10: 4 Refrigeration (optional) | AB10: LC_Refrig | AC10: No | AD10: =IF($AC10="No","n/a",SUM(LC_Refrig[Total kVA])) -> n/a | AE10: =IF(Generator!$B$55="","",Generator!$B$55) | AF10: =IF(UPS!$B$50="","",UPS!$B$50) | AG10: =IF($AC10="No",0,COUNTIFS(LC_Refrig[Status],"Unplaced")+COUNTIFS(LC_Refrig[Status],"Partial")) -> 0 | AH10: =IF($AC10="No",0,SUMIFS(LC_Refrig[Total kVA],LC_Refrig[Status],"Unplaced")+SUMIFS(LC_Refrig[Total kVA],LC_Refrig[Status],"Partial")) -> 0
A11: ="LIGHTING POWER DENSITY — "&LEFT(Cfg_Energy_Code,FIND(" ",Cfg_Energy_Code&" ")-1)&" C405.4.2" -> LIGHTING POWER DENSITY — C405.4.2 | AA11: 5 Mechanical | AB11: LC_Mech | AC11: Yes | AD11: =IF($AC11="No","n/a",SUM(LC_Mech[Total kVA])) -> 0 | AG11: =IF($AC11="No",0,COUNTIFS(LC_Mech[Status],"Unplaced")+COUNTIFS(LC_Mech[Status],"Partial")) -> 0 | AH11: =IF($AC11="No",0,SUMIFS(LC_Mech[Total kVA],LC_Mech[Status],"Unplaced")+SUMIFS(LC_Mech[Total kVA],LC_Mech[Status],"Partial")) -> 0
AA12: 6 Plumbing | AB12: LC_Plumb | AC12: Yes | AD12: =IF($AC12="No","n/a",SUM(LC_Plumb[Total kVA])) -> 0 | AE12: =IF(Generator!$B$56="","",Generator!$B$56) | AF12: =IF(UPS!$B$51="","",UPS!$B$51) | AG12: =IF($AC12="No",0,COUNTIFS(LC_Plumb[Status],"Unplaced")+COUNTIFS(LC_Plumb[Status],"Partial")) -> 0 | AH12: =IF($AC12="No",0,SUMIFS(LC_Plumb[Total kVA],LC_Plumb[Status],"Unplaced")+SUMIFS(LC_Plumb[Total kVA],LC_Plumb[Status],"Partial")) -> 0
AA13: 7 Kitchen / Food Service (optional) | AB13: LC_Kitchen | AC13: No | AD13: =IF($AC13="No","n/a",SUM(LC_Kitchen[Total kVA])) -> n/a | AE13: =IF(Generator!$B$57="","",Generator!$B$57) | AF13: =IF(UPS!$B$52="","",UPS!$B$52) | AG13: =IF($AC13="No",0,COUNTIFS(LC_Kitchen[Status],"Unplaced")+COUNTIFS(LC_Kitchen[Status],"Partial")) -> 0 | AH13: =IF($AC13="No",0,SUMIFS(LC_Kitchen[Total kVA],LC_Kitchen[Status],"Unplaced")+SUMIFS(LC_Kitchen[Total kVA],LC_Kitchen[Status],"Partial")) -> 0
B14: Energy Code (Jurisdiction) | AA14: 8 Elevators / Conveying (optional) | AB14: LC_Elev | AC14: No | AD14: =IF($AC14="No","n/a",SUM(LC_Elev[Total kVA])) -> n/a | AE14: =IF(Generator!$B$58="","",Generator!$B$58) | AF14: =IF(UPS!$B$53="","",UPS!$B$53) | AG14: =IF($AC14="No",0,COUNTIFS(LC_Elev[Status],"Unplaced")+COUNTIFS(LC_Elev[Status],"Partial")) -> 0 | AH14: =IF($AC14="No",0,SUMIFS(LC_Elev[Total kVA],LC_Elev[Status],"Unplaced")+SUMIFS(LC_Elev[Total kVA],LC_Elev[Status],"Partial")) -> 0
B15: Compliance Method | AA15: 9 EV Charging (optional) | AB15: LC_EV | AC15: No | AD15: =IF($AC15="No","n/a",SUM(LC_EV[Total kVA])) -> n/a | AG15: =IF($AC15="No",0,COUNTIFS(LC_EV[Status],"Unplaced")+COUNTIFS(LC_EV[Status],"Partial")) -> 0 | AH15: =IF($AC15="No",0,SUMIFS(LC_EV[Total kVA],LC_EV[Status],"Unplaced")+SUMIFS(LC_EV[Total kVA],LC_EV[Status],"Partial")) -> 0
B16: Total Lighting Watts (from SF table) | C16: =SUM(LC_Areas[Lighting W]) -> 0 | AA16: 10 Data / IT | AB16: LC_Data | AC16: Yes | AD16: =IF($AC16="No","n/a",SUM(LC_Data[Total kVA])) -> 0 | AG16: =IF($AC16="No",0,COUNTIFS(LC_Data[Status],"Unplaced")+COUNTIFS(LC_Data[Status],"Partial")) -> 0 | AH16: =IF($AC16="No",0,SUMIFS(LC_Data[Total kVA],LC_Data[Status],"Unplaced")+SUMIFS(LC_Data[Total kVA],LC_Data[Status],"Partial")) -> 0
B17: Total Building SF | C17: =SUM(LC_Areas[Total SF]) -> 0 | AA17: 11 Fire / Life Safety (optional) | AB17: LC_Fire | AC17: No | AD17: =IF($AC17="No","n/a",SUM(LC_Fire[Total kVA])) -> n/a | AG17: =IF($AC17="No",0,COUNTIFS(LC_Fire[Status],"Unplaced")+COUNTIFS(LC_Fire[Status],"Partial")) -> 0 | AH17: =IF($AC17="No",0,SUMIFS(LC_Fire[Total kVA],LC_Fire[Status],"Unplaced")+SUMIFS(LC_Fire[Total kVA],LC_Fire[Status],"Partial")) -> 0
B18: GOVERNING BLENDED LPD (W/ft²) | C18: =IF(N($C$17)=0,0,$C$16/$C$17) -> 0 | AA18: 12 Process / Industrial (optional) | AB18: LC_Process | AC18: No | AD18: =IF($AC18="No","n/a",SUM(LC_Process[Total kVA])) -> n/a | AG18: =IF($AC18="No",0,COUNTIFS(LC_Process[Status],"Unplaced")+COUNTIFS(LC_Process[Status],"Partial")) -> 0 | AH18: =IF($AC18="No",0,SUMIFS(LC_Process[Total kVA],LC_Process[Status],"Unplaced")+SUMIFS(LC_Process[Total kVA],LC_Process[Status],"Partial")) -> 0
B19: Lighting Type Completeness | C19: =_xlfn.LET(_xlpm.n,COUNTIFS(LC_Areas[Total SF],">0"),_xlpm.m,COUNTIFS(LC_Areas[Total SF],">0",LC_Areas[Space Type],""),_xlpm.x,COUNTIF(LC_Areas[LPD (W/ft²)],"not listed*"),IF(_xlpm.n=0,"— no areas entered",IF(_xlpm.x>0,"✘ "&_xlpm.x&" type(s) not listed in "&Cfg_Energy_Code,IF(_xlpm.m>0,"⚠ "&_xlpm.m&" of "&_xlpm.n&" area(s) missing a type","✔ all "&_xlpm.n&" area(s) typed")))) -> — no areas entered
A21: GENERAL DEMAND ALLOWANCES (W/SF)
B24: Category | C24: W/SF | D24: Applies to SF | E24: Connected kVA | F24: Demand Factor | G24: Demand kVA
B25: General Power | C25: 2 | D25: =SUM(LC_Areas[Total SF]) -> 0 | E25: =IF(OR(LC_WSF[[#This Row],[W/SF]]="",LC_WSF[[#This Row],[Applies to SF]]=""),"",LC_WSF[[#This Row],[W/SF]]*LC_WSF[[#This Row],[Applies to SF]]/1000) -> 0 | F25: =IF(OR(E25="",E25=0),"",(MIN(E25*1000,Rcpt_Thresh_VA)+MAX(0,E25*1000-Rcpt_Thresh_VA)*Rcpt_Rem_DF)/1000/E25) | G25: =IF(LC_WSF[[#This Row],[Connected kVA]]="","",LC_WSF[[#This Row],[Connected kVA]]*IF(LC_WSF[[#This Row],[Demand Factor]]="",1,LC_WSF[[#This Row],[Demand Factor]])) -> 0
B26: Computer Power | C26: 2 | D26: =SUM(LC_Areas[Total SF]) -> 0 | E26: =IF(OR(LC_WSF[[#This Row],[W/SF]]="",LC_WSF[[#This Row],[Applies to SF]]=""),"",LC_WSF[[#This Row],[W/SF]]*LC_WSF[[#This Row],[Applies to SF]]/1000) -> 0 | F26: 1 | G26: =IF(LC_WSF[[#This Row],[Connected kVA]]="","",LC_WSF[[#This Row],[Connected kVA]]*IF(LC_WSF[[#This Row],[Demand Factor]]="",1,LC_WSF[[#This Row],[Demand Factor]])) -> 0
B27: ="General Lighting ("&LEFT(Cfg_Energy_Code,FIND(" ",Cfg_Energy_Code&" ")-1)&" C405.4.2)" -> General Lighting ( C405.4.2) | C27: =$C$18 -> 0 | D27: =SUM(LC_Areas[Total SF]) -> 0 | E27: =IF(OR(LC_WSF[[#This Row],[W/SF]]="",LC_WSF[[#This Row],[Applies to SF]]=""),"",LC_WSF[[#This Row],[W/SF]]*LC_WSF[[#This Row],[Applies to SF]]/1000) -> 0 | F27: 1 | G27: =IF(LC_WSF[[#This Row],[Connected kVA]]="","",LC_WSF[[#This Row],[Connected kVA]]*IF(LC_WSF[[#This Row],[Demand Factor]]="",1,LC_WSF[[#This Row],[Demand Factor]])) -> 0
B28: General Mechanical & Plumbing | C28: 15 | D28: =SUM(LC_Areas[Total SF]) -> 0 | E28: =IF(OR(LC_WSF[[#This Row],[W/SF]]="",LC_WSF[[#This Row],[Applies to SF]]=""),"",LC_WSF[[#This Row],[W/SF]]*LC_WSF[[#This Row],[Applies to SF]]/1000) -> 0 | F28: 1 | G28: =IF(LC_WSF[[#This Row],[Connected kVA]]="","",LC_WSF[[#This Row],[Connected kVA]]*IF(LC_WSF[[#This Row],[Demand Factor]]="",1,LC_WSF[[#This Row],[Demand Factor]])) -> 0
B29: TOTAL W/SF LOADS | E29: =SUM(LC_WSF[Connected kVA]) -> 0 | G29: =SUM(LC_WSF[Demand kVA]) -> 0
A31: {="EXISTING BUILDING DEMAND — NEC "&NECREF("220.87")&" (12-MONTH BILLS OR 30-DAY LOGGING)"} -> EXISTING BUILDING DEMAND — NEC 220.87 (12-MONTH BILLS OR 30-DAY LOGGING)
B34: Peak Existing Demand (kW) | C34: =IF($G$34="30-Day Metered Logging",'Logging Demand'!$C$45,'Utility Demand'!$G$36) -> 0 | F34: {="Method (NEC "&NECREF("220.87")&")"} -> Method (NEC 220.87)
B35: Peak Demand (kVA) | C35: =IF($G$34="30-Day Metered Logging",'Logging Demand'!$C$47,'Utility Demand'!$G$37) -> 0 | F35: Existing Service Size (A)
B36: {="NEC "&NECREF("220.87")&" Existing Load = 125% × Peak (kVA)"} -> NEC 220.87 Existing Load = 125% × Peak (kVA) | C36: =IF($C$35="","",1.25*$C$35) -> 0 | F36: Existing Service Capacity (kVA) | G36: =IF(OR($G$35="",NOT(ISNUMBER(Cfg_Volt))),"",$G$35*Cfg_Volt*IF(Cfg_Phase=3,SQRT3,1)/1000)
B37: Spare Capacity on Existing Service (kVA) | C37: =IF(OR($C$36="",$G$36=""),"",$G$36-$C$36) | F37: Service Utilization (%) | G37: =IF(OR($C$36="",$G$36=""),"",$C$36/$G$36)
B38: {=IF(NEC_Ed="NEC 2026","Load Being Removed (kVA) — NEC "&NECREF("220.87")&"(2)","Load Being Removed (kVA) — used only with NEC 2026")} -> Load Being Removed (kVA) — used only with NEC 2026
B39: {="Auto-filled from the NEC "&NECREF("220.87")&" module chosen at right — 12-Month Utility Bills (Utility Demand tab) or 30-Day Metered Logging (Logging Demand tab). Enter the source data on that tab; only the selected method feeds this total."} -> Auto-filled from the NEC 220.87 module chosen at right — 12-Month Utility Bills (Utility Demand tab) or 30-Day Metered Logging (Logging Demand tab). Enter the source data on that tab; only the selected method feeds this total.
A41: SITE / EXTERIOR
A43: No. | B43: Description | C43: Qty | D43: Connection | E43: Disc NEMA | F43: Disc Frame (A) | G43: Disc Fuse (A) | H43: Disc Supplied By | I43: Recept Type | J43: Load Value | K43: Unit | L43: Volts | M43: Ph | N43: PF | O43: kVA Each | P43: Total kVA | Q43: Ded. Ckt | R43: Gen | S43: UPS | T43: Panel Tag | U43: Notes | V43: Ckts | W43: Placed | X43: Status
O44: {=IF(OR(LC_Site[[#This Row],[Qty]]="",LC_Site[[#This Row],[Load Value]]="",LC_Site[[#This Row],[Unit]]=""),"",IFERROR(_xlfn.SWITCH(LC_Site[[#This Row],[Unit]],"HP",IF(LC_Site[[#This Row],[Ph]]=3,VLOOKUP(LC_Site[[#This Row],[Load Value]],Motor3_Table,IF(LC_Site[[#This Row],[Volts]]<=215,2,IF(LC_Site[[#This Row],[Volts]]<=245,3,IF(LC_Site[[#This Row],[Volts]]<=500,4,5))),TRUE)*LC_Site[[#This Row],[Volts]]*SQRT3/1000,VLOOKUP(LC_Site[[#This Row],[Load Value]],Motor1_Table,IF(LC_Site[[#This Row],[Volts]]<=130,2,3),TRUE)*LC_Site[[#This Row],[Volts]]/1000),"kW",LC_Site[[#This Row],[Load Value]]/IF(LC_Site[[#This Row],[PF]]="",0.9,LC_Site[[#This Row],[PF]]),"kVA",LC_Site[[#This Row],[Load Value]],"A",LC_Site[[#This Row],[Load Value]]*LC_Site[[#This Row],[Volts]]*IF(LC_Site[[#This Row],[Ph]]=3,SQRT3,1)/1000,"W",LC_Site[[#This Row],[Load Value]]/IF(LC_Site[[#This Row],[PF]]="",0.9,LC_Site[[#This Row],[PF]])/1000,"VA",LC_Site[[#This Row],[Load Value]]/1000),"chk"))} | P44: =IF(NOT(ISNUMBER(LC_Site[[#This Row],[kVA Each]])),"",LC_Site[[#This Row],[Qty]]*LC_Site[[#This Row],[kVA Each]]) | W44: 0 | X44: =IF(LC_Site[[#This Row],[Description]]="","",IF(N(LC_Site[[#This Row],[Placed]])=0,"Unplaced",IF(LC_Site[[#This Row],[Placed]]>=IF(LC_Site[[#This Row],[Ded. Ckt]]="N",1,MAX(1,N(LC_Site[[#This Row],[Qty]]))),"Placed","Partial")))
B46: NEC DEMAND FACTOR × SECTION TOTAL = SECTION DEMAND → | G46: 1 | O46: =SUM(LC_Site[Total kVA]) -> 0 | P46: =ROUND(IFERROR($O46*$G46,0),1) -> 0
A48: HOUSE / MISCELLANEOUS EQUIPMENT
A50: No. | B50: Description | C50: Qty | D50: Connection | E50: Disc NEMA | F50: Disc Frame (A) | G50: Disc Fuse (A) | H50: Disc Supplied By | I50: Recept Type | J50: Load Value | K50: Unit | L50: Volts | M50: Ph | N50: PF | O50: kVA Each | P50: Total kVA | Q50: Ded. Ckt | R50: Gen | S50: UPS | T50: Panel Tag | U50: Notes | V50: Ckts | W50: Placed | X50: Status
O51: {=IF(OR(LC_House[[#This Row],[Qty]]="",LC_House[[#This Row],[Load Value]]="",LC_House[[#This Row],[Unit]]=""),"",IFERROR(_xlfn.SWITCH(LC_House[[#This Row],[Unit]],"HP",IF(LC_House[[#This Row],[Ph]]=3,VLOOKUP(LC_House[[#This Row],[Load Value]],Motor3_Table,IF(LC_House[[#This Row],[Volts]]<=215,2,IF(LC_House[[#This Row],[Volts]]<=245,3,IF(LC_House[[#This Row],[Volts]]<=500,4,5))),TRUE)*LC_House[[#This Row],[Volts]]*SQRT3/1000,VLOOKUP(LC_House[[#This Row],[Load Value]],Motor1_Table,IF(LC_House[[#This Row],[Volts]]<=130,2,3),TRUE)*LC_House[[#This Row],[Volts]]/1000),"kW",LC_House[[#This Row],[Load Value]]/IF(LC_House[[#This Row],[PF]]="",0.9,LC_House[[#This Row],[PF]]),"kVA",LC_House[[#This Row],[Load Value]],"A",LC_House[[#This Row],[Load Value]]*LC_House[[#This Row],[Volts]]*IF(LC_House[[#This Row],[Ph]]=3,SQRT3,1)/1000,"W",LC_House[[#This Row],[Load Value]]/IF(LC_House[[#This Row],[PF]]="",0.9,LC_House[[#This Row],[PF]])/1000,"VA",LC_House[[#This Row],[Load Value]]/1000),"chk"))} | P51: =IF(NOT(ISNUMBER(LC_House[[#This Row],[kVA Each]])),"",LC_House[[#This Row],[Qty]]*LC_House[[#This Row],[kVA Each]]) | W51: 0 | X51: =IF(LC_House[[#This Row],[Description]]="","",IF(N(LC_House[[#This Row],[Placed]])=0,"Unplaced",IF(LC_House[[#This Row],[Placed]]>=IF(LC_House[[#This Row],[Ded. Ckt]]="N",1,MAX(1,N(LC_House[[#This Row],[Qty]]))),"Placed","Partial")))
B53: NEC DEMAND FACTOR × SECTION TOTAL = SECTION DEMAND → | G53: 1 | O53: =SUM(LC_House[Total kVA]) -> 0 | P53: =ROUND(IFERROR($O53*$G53,0),1) -> 0
A55: DEPARTMENT / OWNER EQUIPMENT
A57: No. | B57: Description | C57: Qty | D57: Connection | E57: Disc NEMA | F57: Disc Frame (A) | G57: Disc Fuse (A) | H57: Disc Supplied By | I57: Recept Type | J57: Load Value | K57: Unit | L57: Volts | M57: Ph | N57: PF | O57: kVA Each | P57: Total kVA | Q57: Ded. Ckt | R57: Gen | S57: UPS | T57: Panel Tag | U57: Notes | V57: Ckts | W57: Placed | X57: Status
O58: {=IF(OR(LC_Dept[[#This Row],[Qty]]="",LC_Dept[[#This Row],[Load Value]]="",LC_Dept[[#This Row],[Unit]]=""),"",IFERROR(_xlfn.SWITCH(LC_Dept[[#This Row],[Unit]],"HP",IF(LC_Dept[[#This Row],[Ph]]=3,VLOOKUP(LC_Dept[[#This Row],[Load Value]],Motor3_Table,IF(LC_Dept[[#This Row],[Volts]]<=215,2,IF(LC_Dept[[#This Row],[Volts]]<=245,3,IF(LC_Dept[[#This Row],[Volts]]<=500,4,5))),TRUE)*LC_Dept[[#This Row],[Volts]]*SQRT3/1000,VLOOKUP(LC_Dept[[#This Row],[Load Value]],Motor1_Table,IF(LC_Dept[[#This Row],[Volts]]<=130,2,3),TRUE)*LC_Dept[[#This Row],[Volts]]/1000),"kW",LC_Dept[[#This Row],[Load Value]]/IF(LC_Dept[[#This Row],[PF]]="",0.9,LC_Dept[[#This Row],[PF]]),"kVA",LC_Dept[[#This Row],[Load Value]],"A",LC_Dept[[#This Row],[Load Value]]*LC_Dept[[#This Row],[Volts]]*IF(LC_Dept[[#This Row],[Ph]]=3,SQRT3,1)/1000,"W",LC_Dept[[#This Row],[Load Value]]/IF(LC_Dept[[#This Row],[PF]]="",0.9,LC_Dept[[#This Row],[PF]])/1000,"VA",LC_Dept[[#This Row],[Load Value]]/1000),"chk"))} | P58: =IF(NOT(ISNUMBER(LC_Dept[[#This Row],[kVA Each]])),"",LC_Dept[[#This Row],[Qty]]*LC_Dept[[#This Row],[kVA Each]]) | W58: 0 | X58: =IF(LC_Dept[[#This Row],[Description]]="","",IF(N(LC_Dept[[#This Row],[Placed]])=0,"Unplaced",IF(LC_Dept[[#This Row],[Placed]]>=IF(LC_Dept[[#This Row],[Ded. Ckt]]="N",1,MAX(1,N(LC_Dept[[#This Row],[Qty]]))),"Placed","Partial")))
B60: NEC DEMAND FACTOR × SECTION TOTAL = SECTION DEMAND → | G60: 1 | O60: =SUM(LC_Dept[Total kVA]) -> 0 | P60: =ROUND(IFERROR($O60*$G60,0),1) -> 0
A62: REFRIGERATION EQUIPMENT
A64: No. | B64: Description | C64: Qty | D64: Connection | E64: Disc NEMA | F64: Disc Frame (A) | G64: Disc Fuse (A) | H64: Disc Supplied By | I64: Recept Type | J64: Load Value | K64: Unit | L64: Volts | M64: Ph | N64: PF | O64: kVA Each | P64: Total kVA | Q64: Ded. Ckt | R64: Gen | S64: UPS | T64: Panel Tag | U64: Notes | V64: Ckts | W64: Placed | X64: Status
O65: {=IF(OR(LC_Refrig[[#This Row],[Qty]]="",LC_Refrig[[#This Row],[Load Value]]="",LC_Refrig[[#This Row],[Unit]]=""),"",IFERROR(_xlfn.SWITCH(LC_Refrig[[#This Row],[Unit]],"HP",IF(LC_Refrig[[#This Row],[Ph]]=3,VLOOKUP(LC_Refrig[[#This Row],[Load Value]],Motor3_Table,IF(LC_Refrig[[#This Row],[Volts]]<=215,2,IF(LC_Refrig[[#This Row],[Volts]]<=245,3,IF(LC_Refrig[[#This Row],[Volts]]<=500,4,5))),TRUE)*LC_Refrig[[#This Row],[Volts]]*SQRT3/1000,VLOOKUP(LC_Refrig[[#This Row],[Load Value]],Motor1_Table,IF(LC_Refrig[[#This Row],[Volts]]<=130,2,3),TRUE)*LC_Refrig[[#This Row],[Volts]]/1000),"kW",LC_Refrig[[#This Row],[Load Value]]/IF(LC_Refrig[[#This Row],[PF]]="",0.9,LC_Refrig[[#This Row],[PF]]),"kVA",LC_Refrig[[#This Row],[Load Value]],"A",LC_Refrig[[#This Row],[Load Value]]*LC_Refrig[[#This Row],[Volts]]*IF(LC_Refrig[[#This Row],[Ph]]=3,SQRT3,1)/1000,"W",LC_Refrig[[#This Row],[Load Value]]/IF(LC_Refrig[[#This Row],[PF]]="",0.9,LC_Refrig[[#This Row],[PF]])/1000,"VA",LC_Refrig[[#This Row],[Load Value]]/1000),"chk"))} | P65: =IF(NOT(ISNUMBER(LC_Refrig[[#This Row],[kVA Each]])),"",LC_Refrig[[#This Row],[Qty]]*LC_Refrig[[#This Row],[kVA Each]]) | W65: 0 | X65: =IF(LC_Refrig[[#This Row],[Description]]="","",IF(N(LC_Refrig[[#This Row],[Placed]])=0,"Unplaced",IF(LC_Refrig[[#This Row],[Placed]]>=IF(LC_Refrig[[#This Row],[Ded. Ckt]]="N",1,MAX(1,N(LC_Refrig[[#This Row],[Qty]]))),"Placed","Partial")))
B67: NEC DEMAND FACTOR × SECTION TOTAL = SECTION DEMAND → | G67: 1 | O67: =SUM(LC_Refrig[Total kVA]) -> 0 | P67: =ROUND(IFERROR($O67*$G67,0),1) -> 0
A69: MECHANICAL EQUIPMENT
A71: No. | B71: Description | C71: Qty | D71: Connection | E71: Disc NEMA | F71: Disc Frame (A) | G71: Disc Fuse (A) | H71: Disc Supplied By | I71: Recept Type | J71: Load Value | K71: Unit | L71: Volts | M71: Ph | N71: PF | O71: kVA Each | P71: Total kVA | Q71: Ded. Ckt | R71: Gen | S71: UPS | T71: Panel Tag | U71: Notes | V71: Ckts | W71: Placed | X71: Status
O72: {=IF(OR(LC_Mech[[#This Row],[Qty]]="",LC_Mech[[#This Row],[Load Value]]="",LC_Mech[[#This Row],[Unit]]=""),"",IFERROR(_xlfn.SWITCH(LC_Mech[[#This Row],[Unit]],"HP",IF(LC_Mech[[#This Row],[Ph]]=3,VLOOKUP(LC_Mech[[#This Row],[Load Value]],Motor3_Table,IF(LC_Mech[[#This Row],[Volts]]<=215,2,IF(LC_Mech[[#This Row],[Volts]]<=245,3,IF(LC_Mech[[#This Row],[Volts]]<=500,4,5))),TRUE)*LC_Mech[[#This Row],[Volts]]*SQRT3/1000,VLOOKUP(LC_Mech[[#This Row],[Load Value]],Motor1_Table,IF(LC_Mech[[#This Row],[Volts]]<=130,2,3),TRUE)*LC_Mech[[#This Row],[Volts]]/1000),"kW",LC_Mech[[#This Row],[Load Value]]/IF(LC_Mech[[#This Row],[PF]]="",0.9,LC_Mech[[#This Row],[PF]]),"kVA",LC_Mech[[#This Row],[Load Value]],"A",LC_Mech[[#This Row],[Load Value]]*LC_Mech[[#This Row],[Volts]]*IF(LC_Mech[[#This Row],[Ph]]=3,SQRT3,1)/1000,"W",LC_Mech[[#This Row],[Load Value]]/IF(LC_Mech[[#This Row],[PF]]="",0.9,LC_Mech[[#This Row],[PF]])/1000,"VA",LC_Mech[[#This Row],[Load Value]]/1000),"chk"))} | P72: =IF(NOT(ISNUMBER(LC_Mech[[#This Row],[kVA Each]])),"",LC_Mech[[#This Row],[Qty]]*LC_Mech[[#This Row],[kVA Each]]) | W72: 0 | X72: =IF(LC_Mech[[#This Row],[Description]]="","",IF(N(LC_Mech[[#This Row],[Placed]])=0,"Unplaced",IF(LC_Mech[[#This Row],[Placed]]>=IF(LC_Mech[[#This Row],[Ded. Ckt]]="N",1,MAX(1,N(LC_Mech[[#This Row],[Qty]]))),"Placed","Partial")))
B74: NEC DEMAND FACTOR × SECTION TOTAL = SECTION DEMAND → | G74: 1 | O74: =SUM(LC_Mech[Total kVA]) -> 0 | P74: =ROUND(IFERROR($O74*$G74,0),1) -> 0
A76: PLUMBING EQUIPMENT
A78: No. | B78: Description | C78: Qty | D78: Connection | E78: Disc NEMA | F78: Disc Frame (A) | G78: Disc Fuse (A) | H78: Disc Supplied By | I78: Recept Type | J78: Load Value | K78: Unit | L78: Volts | M78: Ph | N78: PF | O78: kVA Each | P78: Total kVA | Q78: Ded. Ckt | R78: Gen | S78: UPS | T78: Panel Tag | U78: Notes | V78: Ckts | W78: Placed | X78: Status
O79: {=IF(OR(LC_Plumb[[#This Row],[Qty]]="",LC_Plumb[[#This Row],[Load Value]]="",LC_Plumb[[#This Row],[Unit]]=""),"",IFERROR(_xlfn.SWITCH(LC_Plumb[[#This Row],[Unit]],"HP",IF(LC_Plumb[[#This Row],[Ph]]=3,VLOOKUP(LC_Plumb[[#This Row],[Load Value]],Motor3_Table,IF(LC_Plumb[[#This Row],[Volts]]<=215,2,IF(LC_Plumb[[#This Row],[Volts]]<=245,3,IF(LC_Plumb[[#This Row],[Volts]]<=500,4,5))),TRUE)*LC_Plumb[[#This Row],[Volts]]*SQRT3/1000,VLOOKUP(LC_Plumb[[#This Row],[Load Value]],Motor1_Table,IF(LC_Plumb[[#This Row],[Volts]]<=130,2,3),TRUE)*LC_Plumb[[#This Row],[Volts]]/1000),"kW",LC_Plumb[[#This Row],[Load Value]]/IF(LC_Plumb[[#This Row],[PF]]="",0.9,LC_Plumb[[#This Row],[PF]]),"kVA",LC_Plumb[[#This Row],[Load Value]],"A",LC_Plumb[[#This Row],[Load Value]]*LC_Plumb[[#This Row],[Volts]]*IF(LC_Plumb[[#This Row],[Ph]]=3,SQRT3,1)/1000,"W",LC_Plumb[[#This Row],[Load Value]]/IF(LC_Plumb[[#This Row],[PF]]="",0.9,LC_Plumb[[#This Row],[PF]])/1000,"VA",LC_Plumb[[#This Row],[Load Value]]/1000),"chk"))} | P79: =IF(NOT(ISNUMBER(LC_Plumb[[#This Row],[kVA Each]])),"",LC_Plumb[[#This Row],[Qty]]*LC_Plumb[[#This Row],[kVA Each]]) | W79: 0 | X79: =IF(LC_Plumb[[#This Row],[Description]]="","",IF(N(LC_Plumb[[#This Row],[Placed]])=0,"Unplaced",IF(LC_Plumb[[#This Row],[Placed]]>=IF(LC_Plumb[[#This Row],[Ded. Ckt]]="N",1,MAX(1,N(LC_Plumb[[#This Row],[Qty]]))),"Placed","Partial")))
B81: NEC DEMAND FACTOR × SECTION TOTAL = SECTION DEMAND → | G81: 1 | O81: =SUM(LC_Plumb[Total kVA]) -> 0 | P81: =ROUND(IFERROR($O81*$G81,0),1) -> 0
A83: {="KITCHEN / FOOD SERVICE EQUIPMENT (NEC "&NECREF("220.56")&")"} -> KITCHEN / FOOD SERVICE EQUIPMENT (NEC 220.56)
A85: No. | B85: Description | C85: Qty | D85: Connection | E85: Disc NEMA | F85: Disc Frame (A) | G85: Disc Fuse (A) | H85: Disc Supplied By | I85: Recept Type | J85: Load Value | K85: Unit | L85: Volts | M85: Ph | N85: PF | O85: kVA Each | P85: Total kVA | Q85: Ded. Ckt | R85: Gen | S85: UPS | T85: Panel Tag | U85: Notes | V85: Ckts | W85: Placed | X85: Status
O86: {=IF(OR(LC_Kitchen[[#This Row],[Qty]]="",LC_Kitchen[[#This Row],[Load Value]]="",LC_Kitchen[[#This Row],[Unit]]=""),"",IFERROR(_xlfn.SWITCH(LC_Kitchen[[#This Row],[Unit]],"HP",IF(LC_Kitchen[[#This Row],[Ph]]=3,VLOOKUP(LC_Kitchen[[#This Row],[Load Value]],Motor3_Table,IF(LC_Kitchen[[#This Row],[Volts]]<=215,2,IF(LC_Kitchen[[#This Row],[Volts]]<=245,3,IF(LC_Kitchen[[#This Row],[Volts]]<=500,4,5))),TRUE)*LC_Kitchen[[#This Row],[Volts]]*SQRT3/1000,VLOOKUP(LC_Kitchen[[#This Row],[Load Value]],Motor1_Table,IF(LC_Kitchen[[#This Row],[Volts]]<=130,2,3),TRUE)*LC_Kitchen[[#This Row],[Volts]]/1000),"kW",LC_Kitchen[[#This Row],[Load Value]]/IF(LC_Kitchen[[#This Row],[PF]]="",0.9,LC_Kitchen[[#This Row],[PF]]),"kVA",LC_Kitchen[[#This Row],[Load Value]],"A",LC_Kitchen[[#This Row],[Load Value]]*LC_Kitchen[[#This Row],[Volts]]*IF(LC_Kitchen[[#This Row],[Ph]]=3,SQRT3,1)/1000,"W",LC_Kitchen[[#This Row],[Load Value]]/IF(LC_Kitchen[[#This Row],[PF]]="",0.9,LC_Kitchen[[#This Row],[PF]])/1000,"VA",LC_Kitchen[[#This Row],[Load Value]]/1000),"chk"))} | P86: =IF(NOT(ISNUMBER(LC_Kitchen[[#This Row],[kVA Each]])),"",LC_Kitchen[[#This Row],[Qty]]*LC_Kitchen[[#This Row],[kVA Each]]) | W86: 0 | X86: =IF(LC_Kitchen[[#This Row],[Description]]="","",IF(N(LC_Kitchen[[#This Row],[Placed]])=0,"Unplaced",IF(LC_Kitchen[[#This Row],[Placed]]>=IF(LC_Kitchen[[#This Row],[Ded. Ckt]]="N",1,MAX(1,N(LC_Kitchen[[#This Row],[Qty]]))),"Placed","Partial")))
B88: NEC DEMAND FACTOR × SECTION TOTAL = SECTION DEMAND → | G88: =IFERROR(VLOOKUP(MAX(1,SUM(LC_Kitchen[Qty])),Kitchen_Table,2,TRUE),1) -> 1 | O88: =SUM(LC_Kitchen[Total kVA]) -> 0 | P88: =ROUND(IFERROR($O88*$G88,0),1) -> 0
A90: {="ELEVATORS / CONVEYING (NEC "&NECREF("620.14")&")"} -> ELEVATORS / CONVEYING (NEC 620.14)
A92: No. | B92: Description | C92: Qty | D92: Connection | E92: Disc NEMA | F92: Disc Frame (A) | G92: Disc Fuse (A) | H92: Disc Supplied By | I92: Recept Type | J92: Load Value | K92: Unit | L92: Volts | M92: Ph | N92: PF | O92: kVA Each | P92: Total kVA | Q92: Ded. Ckt | R92: Gen | S92: UPS | T92: Panel Tag | U92: Notes | V92: Ckts | W92: Placed | X92: Status
O93: {=IF(OR(LC_Elev[[#This Row],[Qty]]="",LC_Elev[[#This Row],[Load Value]]="",LC_Elev[[#This Row],[Unit]]=""),"",IFERROR(_xlfn.SWITCH(LC_Elev[[#This Row],[Unit]],"HP",IF(LC_Elev[[#This Row],[Ph]]=3,VLOOKUP(LC_Elev[[#This Row],[Load Value]],Motor3_Table,IF(LC_Elev[[#This Row],[Volts]]<=215,2,IF(LC_Elev[[#This Row],[Volts]]<=245,3,IF(LC_Elev[[#This Row],[Volts]]<=500,4,5))),TRUE)*LC_Elev[[#This Row],[Volts]]*SQRT3/1000,VLOOKUP(LC_Elev[[#This Row],[Load Value]],Motor1_Table,IF(LC_Elev[[#This Row],[Volts]]<=130,2,3),TRUE)*LC_Elev[[#This Row],[Volts]]/1000),"kW",LC_Elev[[#This Row],[Load Value]]/IF(LC_Elev[[#This Row],[PF]]="",0.9,LC_Elev[[#This Row],[PF]]),"kVA",LC_Elev[[#This Row],[Load Value]],"A",LC_Elev[[#This Row],[Load Value]]*LC_Elev[[#This Row],[Volts]]*IF(LC_Elev[[#This Row],[Ph]]=3,SQRT3,1)/1000,"W",LC_Elev[[#This Row],[Load Value]]/IF(LC_Elev[[#This Row],[PF]]="",0.9,LC_Elev[[#This Row],[PF]])/1000,"VA",LC_Elev[[#This Row],[Load Value]]/1000),"chk"))} | P93: =IF(NOT(ISNUMBER(LC_Elev[[#This Row],[kVA Each]])),"",LC_Elev[[#This Row],[Qty]]*LC_Elev[[#This Row],[kVA Each]]) | W93: 0 | X93: =IF(LC_Elev[[#This Row],[Description]]="","",IF(N(LC_Elev[[#This Row],[Placed]])=0,"Unplaced",IF(LC_Elev[[#This Row],[Placed]]>=IF(LC_Elev[[#This Row],[Ded. Ckt]]="N",1,MAX(1,N(LC_Elev[[#This Row],[Qty]]))),"Placed","Partial")))
B95: NEC DEMAND FACTOR × SECTION TOTAL = SECTION DEMAND → | G95: 1 | O95: =SUM(LC_Elev[Total kVA]) -> 0 | P95: =ROUND(IFERROR($O95*$G95,0),1) -> 0
A97: {="EV CHARGING (NEC "&NECREF("625")&" — 100% Unless EMS)"} -> EV CHARGING (NEC 625 — 100% Unless EMS)
A99: No. | B99: Description | C99: Qty | D99: Connection | E99: Disc NEMA | F99: Disc Frame (A) | G99: Disc Fuse (A) | H99: Disc Supplied By | I99: Recept Type | J99: Load Value | K99: Unit | L99: Volts | M99: Ph | N99: PF | O99: kVA Each | P99: Total kVA | Q99: Ded. Ckt | R99: Gen | S99: UPS | T99: Panel Tag | U99: Notes | V99: Ckts | W99: Placed | X99: Status
O100: {=IF(OR(LC_EV[[#This Row],[Qty]]="",LC_EV[[#This Row],[Load Value]]="",LC_EV[[#This Row],[Unit]]=""),"",IFERROR(_xlfn.SWITCH(LC_EV[[#This Row],[Unit]],"HP",IF(LC_EV[[#This Row],[Ph]]=3,VLOOKUP(LC_EV[[#This Row],[Load Value]],Motor3_Table,IF(LC_EV[[#This Row],[Volts]]<=215,2,IF(LC_EV[[#This Row],[Volts]]<=245,3,IF(LC_EV[[#This Row],[Volts]]<=500,4,5))),TRUE)*LC_EV[[#This Row],[Volts]]*SQRT3/1000,VLOOKUP(LC_EV[[#This Row],[Load Value]],Motor1_Table,IF(LC_EV[[#This Row],[Volts]]<=130,2,3),TRUE)*LC_EV[[#This Row],[Volts]]/1000),"kW",LC_EV[[#This Row],[Load Value]]/IF(LC_EV[[#This Row],[PF]]="",0.9,LC_EV[[#This Row],[PF]]),"kVA",LC_EV[[#This Row],[Load Value]],"A",LC_EV[[#This Row],[Load Value]]*LC_EV[[#This Row],[Volts]]*IF(LC_EV[[#This Row],[Ph]]=3,SQRT3,1)/1000,"W",LC_EV[[#This Row],[Load Value]]/IF(LC_EV[[#This Row],[PF]]="",0.9,LC_EV[[#This Row],[PF]])/1000,"VA",LC_EV[[#This Row],[Load Value]]/1000),"chk"))} | P100: =IF(NOT(ISNUMBER(LC_EV[[#This Row],[kVA Each]])),"",LC_EV[[#This Row],[Qty]]*LC_EV[[#This Row],[kVA Each]]) | W100: 0 | X100: =IF(LC_EV[[#This Row],[Description]]="","",IF(N(LC_EV[[#This Row],[Placed]])=0,"Unplaced",IF(LC_EV[[#This Row],[Placed]]>=IF(LC_EV[[#This Row],[Ded. Ckt]]="N",1,MAX(1,N(LC_EV[[#This Row],[Qty]]))),"Placed","Partial")))
B102: NEC DEMAND FACTOR × SECTION TOTAL = SECTION DEMAND → | G102: 1 | O102: =SUM(LC_EV[Total kVA]) -> 0 | P102: =ROUND(IFERROR($O102*$G102,0),1) -> 0
A104: DATA / IT EQUIPMENT
A106: No. | B106: Description | C106: Qty | D106: Connection | E106: Disc NEMA | F106: Disc Frame (A) | G106: Disc Fuse (A) | H106: Disc Supplied By | I106: Recept Type | J106: Load Value | K106: Unit | L106: Volts | M106: Ph | N106: PF | O106: kVA Each | P106: Total kVA | Q106: Ded. Ckt | R106: Gen | S106: UPS | T106: Panel Tag | U106: Notes | V106: Ckts | W106: Placed | X106: Status
O107: {=IF(OR(LC_Data[[#This Row],[Qty]]="",LC_Data[[#This Row],[Load Value]]="",LC_Data[[#This Row],[Unit]]=""),"",IFERROR(_xlfn.SWITCH(LC_Data[[#This Row],[Unit]],"HP",IF(LC_Data[[#This Row],[Ph]]=3,VLOOKUP(LC_Data[[#This Row],[Load Value]],Motor3_Table,IF(LC_Data[[#This Row],[Volts]]<=215,2,IF(LC_Data[[#This Row],[Volts]]<=245,3,IF(LC_Data[[#This Row],[Volts]]<=500,4,5))),TRUE)*LC_Data[[#This Row],[Volts]]*SQRT3/1000,VLOOKUP(LC_Data[[#This Row],[Load Value]],Motor1_Table,IF(LC_Data[[#This Row],[Volts]]<=130,2,3),TRUE)*LC_Data[[#This Row],[Volts]]/1000),"kW",LC_Data[[#This Row],[Load Value]]/IF(LC_Data[[#This Row],[PF]]="",0.9,LC_Data[[#This Row],[PF]]),"kVA",LC_Data[[#This Row],[Load Value]],"A",LC_Data[[#This Row],[Load Value]]*LC_Data[[#This Row],[Volts]]*IF(LC_Data[[#This Row],[Ph]]=3,SQRT3,1)/1000,"W",LC_Data[[#This Row],[Load Value]]/IF(LC_Data[[#This Row],[PF]]="",0.9,LC_Data[[#This Row],[PF]])/1000,"VA",LC_Data[[#This Row],[Load Value]]/1000),"chk"))} | P107: =IF(NOT(ISNUMBER(LC_Data[[#This Row],[kVA Each]])),"",LC_Data[[#This Row],[Qty]]*LC_Data[[#This Row],[kVA Each]]) | W107: 0 | X107: =IF(LC_Data[[#This Row],[Description]]="","",IF(N(LC_Data[[#This Row],[Placed]])=0,"Unplaced",IF(LC_Data[[#This Row],[Placed]]>=IF(LC_Data[[#This Row],[Ded. Ckt]]="N",1,MAX(1,N(LC_Data[[#This Row],[Qty]]))),"Placed","Partial")))
B109: NEC DEMAND FACTOR × SECTION TOTAL = SECTION DEMAND → | G109: 1 | O109: =SUM(LC_Data[Total kVA]) -> 0 | P109: =ROUND(IFERROR($O109*$G109,0),1) -> 0
A111: FIRE / LIFE SAFETY
A113: No. | B113: Description | C113: Qty | D113: Connection | E113: Disc NEMA | F113: Disc Frame (A) | G113: Disc Fuse (A) | H113: Disc Supplied By | I113: Recept Type | J113: Load Value | K113: Unit | L113: Volts | M113: Ph | N113: PF | O113: kVA Each | P113: Total kVA | Q113: Ded. Ckt | R113: Gen | S113: UPS | T113: Panel Tag | U113: Notes | V113: Ckts | W113: Placed | X113: Status
O114: {=IF(OR(LC_Fire[[#This Row],[Qty]]="",LC_Fire[[#This Row],[Load Value]]="",LC_Fire[[#This Row],[Unit]]=""),"",IFERROR(_xlfn.SWITCH(LC_Fire[[#This Row],[Unit]],"HP",IF(LC_Fire[[#This Row],[Ph]]=3,VLOOKUP(LC_Fire[[#This Row],[Load Value]],Motor3_Table,IF(LC_Fire[[#This Row],[Volts]]<=215,2,IF(LC_Fire[[#This Row],[Volts]]<=245,3,IF(LC_Fire[[#This Row],[Volts]]<=500,4,5))),TRUE)*LC_Fire[[#This Row],[Volts]]*SQRT3/1000,VLOOKUP(LC_Fire[[#This Row],[Load Value]],Motor1_Table,IF(LC_Fire[[#This Row],[Volts]]<=130,2,3),TRUE)*LC_Fire[[#This Row],[Volts]]/1000),"kW",LC_Fire[[#This Row],[Load Value]]/IF(LC_Fire[[#This Row],[PF]]="",0.9,LC_Fire[[#This Row],[PF]]),"kVA",LC_Fire[[#This Row],[Load Value]],"A",LC_Fire[[#This Row],[Load Value]]*LC_Fire[[#This Row],[Volts]]*IF(LC_Fire[[#This Row],[Ph]]=3,SQRT3,1)/1000,"W",LC_Fire[[#This Row],[Load Value]]/IF(LC_Fire[[#This Row],[PF]]="",0.9,LC_Fire[[#This Row],[PF]])/1000,"VA",LC_Fire[[#This Row],[Load Value]]/1000),"chk"))} | P114: =IF(NOT(ISNUMBER(LC_Fire[[#This Row],[kVA Each]])),"",LC_Fire[[#This Row],[Qty]]*LC_Fire[[#This Row],[kVA Each]]) | W114: 0 | X114: =IF(LC_Fire[[#This Row],[Description]]="","",IF(N(LC_Fire[[#This Row],[Placed]])=0,"Unplaced",IF(LC_Fire[[#This Row],[Placed]]>=IF(LC_Fire[[#This Row],[Ded. Ckt]]="N",1,MAX(1,N(LC_Fire[[#This Row],[Qty]]))),"Placed","Partial")))
B116: NEC DEMAND FACTOR × SECTION TOTAL = SECTION DEMAND → | G116: 1 | O116: =SUM(LC_Fire[Total kVA]) -> 0 | P116: =ROUND(IFERROR($O116*$G116,0),1) -> 0
A118: PROCESS / INDUSTRIAL
A120: No. | B120: Description | C120: Qty | D120: Connection | E120: Disc NEMA | F120: Disc Frame (A) | G120: Disc Fuse (A) | H120: Disc Supplied By | I120: Recept Type | J120: Load Value | K120: Unit | L120: Volts | M120: Ph | N120: PF | O120: kVA Each | P120: Total kVA | Q120: Ded. Ckt | R120: Gen | S120: UPS | T120: Panel Tag | U120: Notes | V120: Ckts | W120: Placed | X120: Status
O121: {=IF(OR(LC_Process[[#This Row],[Qty]]="",LC_Process[[#This Row],[Load Value]]="",LC_Process[[#This Row],[Unit]]=""),"",IFERROR(_xlfn.SWITCH(LC_Process[[#This Row],[Unit]],"HP",IF(LC_Process[[#This Row],[Ph]]=3,VLOOKUP(LC_Process[[#This Row],[Load Value]],Motor3_Table,IF(LC_Process[[#This Row],[Volts]]<=215,2,IF(LC_Process[[#This Row],[Volts]]<=245,3,IF(LC_Process[[#This Row],[Volts]]<=500,4,5))),TRUE)*LC_Process[[#This Row],[Volts]]*SQRT3/1000,VLOOKUP(LC_Process[[#This Row],[Load Value]],Motor1_Table,IF(LC_Process[[#This Row],[Volts]]<=130,2,3),TRUE)*LC_Process[[#This Row],[Volts]]/1000),"kW",LC_Process[[#This Row],[Load Value]]/IF(LC_Process[[#This Row],[PF]]="",0.9,LC_Process[[#This Row],[PF]]),"kVA",LC_Process[[#This Row],[Load Value]],"A",LC_Process[[#This Row],[Load Value]]*LC_Process[[#This Row],[Volts]]*IF(LC_Process[[#This Row],[Ph]]=3,SQRT3,1)/1000,"W",LC_Process[[#This Row],[Load Value]]/IF(LC_Process[[#This Row],[PF]]="",0.9,LC_Process[[#This Row],[PF]])/1000,"VA",LC_Process[[#This Row],[Load Value]]/1000),"chk"))} | P121: =IF(NOT(ISNUMBER(LC_Process[[#This Row],[kVA Each]])),"",LC_Process[[#This Row],[Qty]]*LC_Process[[#This Row],[kVA Each]]) | W121: 0 | X121: =IF(LC_Process[[#This Row],[Description]]="","",IF(N(LC_Process[[#This Row],[Placed]])=0,"Unplaced",IF(LC_Process[[#This Row],[Placed]]>=IF(LC_Process[[#This Row],[Ded. Ckt]]="N",1,MAX(1,N(LC_Process[[#This Row],[Qty]]))),"Placed","Partial")))
B123: NEC DEMAND FACTOR × SECTION TOTAL = SECTION DEMAND → | G123: 1 | O123: =SUM(LC_Process[Total kVA]) -> 0 | P123: =ROUND(IFERROR($O123*$G123,0),1) -> 0
A125: PANEL SPACE COUNTER — PRELIMINARY RISER PLANNING
C127: 480Y/277V Spaces | D127: 208Y/120V Spaces | E127: 240/120V Spaces
B128: Section | F128: Rows marked Ded. Ckt = N are excluded. 120V loads appear in BOTH 208Y and 240 families — read the column matching your system.
B129: Site / Exterior | C129: {=IF($AC$7="No",0,3*SUMPRODUCT((LC_Site[Volts]=480)*(LC_Site[Ph]=3)*(LC_Site[Ded. Ckt]<>"N")*LC_Site[Qty])+2*SUMPRODUCT((LC_Site[Volts]=480)*(LC_Site[Ph]=1)*(LC_Site[Ded. Ckt]<>"N")*LC_Site[Qty])+SUMPRODUCT((LC_Site[Volts]=277)*(LC_Site[Ded. Ckt]<>"N")*LC_Site[Qty]))} -> 0 | D129: {=IF($AC$7="No",0,3*SUMPRODUCT((LC_Site[Volts]=208)*(LC_Site[Ph]=3)*(LC_Site[Ded. Ckt]<>"N")*LC_Site[Qty])+2*SUMPRODUCT((LC_Site[Volts]=208)*(LC_Site[Ph]=1)*(LC_Site[Ded. Ckt]<>"N")*LC_Site[Qty])+SUMPRODUCT((LC_Site[Volts]=120)*(LC_Site[Ded. Ckt]<>"N")*LC_Site[Qty]))} -> 0 | E129: {=IF($AC$7="No",0,3*SUMPRODUCT((LC_Site[Volts]=240)*(LC_Site[Ph]=3)*(LC_Site[Ded. Ckt]<>"N")*LC_Site[Qty])+2*SUMPRODUCT((LC_Site[Volts]=240)*(LC_Site[Ph]=1)*(LC_Site[Ded. Ckt]<>"N")*LC_Site[Qty])+SUMPRODUCT((LC_Site[Volts]=120)*(LC_Site[Ded. Ckt]<>"N")*LC_Site[Qty]))} -> 0
B130: House / Misc | C130: {=IF($AC$8="No",0,3*SUMPRODUCT((LC_House[Volts]=480)*(LC_House[Ph]=3)*(LC_House[Ded. Ckt]<>"N")*LC_House[Qty])+2*SUMPRODUCT((LC_House[Volts]=480)*(LC_House[Ph]=1)*(LC_House[Ded. Ckt]<>"N")*LC_House[Qty])+SUMPRODUCT((LC_House[Volts]=277)*(LC_House[Ded. Ckt]<>"N")*LC_House[Qty]))} -> 0 | D130: {=IF($AC$8="No",0,3*SUMPRODUCT((LC_House[Volts]=208)*(LC_House[Ph]=3)*(LC_House[Ded. Ckt]<>"N")*LC_House[Qty])+2*SUMPRODUCT((LC_House[Volts]=208)*(LC_House[Ph]=1)*(LC_House[Ded. Ckt]<>"N")*LC_House[Qty])+SUMPRODUCT((LC_House[Volts]=120)*(LC_House[Ded. Ckt]<>"N")*LC_House[Qty]))} -> 0 | E130: {=IF($AC$8="No",0,3*SUMPRODUCT((LC_House[Volts]=240)*(LC_House[Ph]=3)*(LC_House[Ded. Ckt]<>"N")*LC_House[Qty])+2*SUMPRODUCT((LC_House[Volts]=240)*(LC_House[Ph]=1)*(LC_House[Ded. Ckt]<>"N")*LC_House[Qty])+SUMPRODUCT((LC_House[Volts]=120)*(LC_House[Ded. Ckt]<>"N")*LC_House[Qty]))} -> 0
B131: Department / Owner | C131: {=IF($AC$9="No",0,3*SUMPRODUCT((LC_Dept[Volts]=480)*(LC_Dept[Ph]=3)*(LC_Dept[Ded. Ckt]<>"N")*LC_Dept[Qty])+2*SUMPRODUCT((LC_Dept[Volts]=480)*(LC_Dept[Ph]=1)*(LC_Dept[Ded. Ckt]<>"N")*LC_Dept[Qty])+SUMPRODUCT((LC_Dept[Volts]=277)*(LC_Dept[Ded. Ckt]<>"N")*LC_Dept[Qty]))} -> 0 | D131: {=IF($AC$9="No",0,3*SUMPRODUCT((LC_Dept[Volts]=208)*(LC_Dept[Ph]=3)*(LC_Dept[Ded. Ckt]<>"N")*LC_Dept[Qty])+2*SUMPRODUCT((LC_Dept[Volts]=208)*(LC_Dept[Ph]=1)*(LC_Dept[Ded. Ckt]<>"N")*LC_Dept[Qty])+SUMPRODUCT((LC_Dept[Volts]=120)*(LC_Dept[Ded. Ckt]<>"N")*LC_Dept[Qty]))} -> 0 | E131: {=IF($AC$9="No",0,3*SUMPRODUCT((LC_Dept[Volts]=240)*(LC_Dept[Ph]=3)*(LC_Dept[Ded. Ckt]<>"N")*LC_Dept[Qty])+2*SUMPRODUCT((LC_Dept[Volts]=240)*(LC_Dept[Ph]=1)*(LC_Dept[Ded. Ckt]<>"N")*LC_Dept[Qty])+SUMPRODUCT((LC_Dept[Volts]=120)*(LC_Dept[Ded. Ckt]<>"N")*LC_Dept[Qty]))} -> 0
B132: Refrigeration | C132: {=IF($AC$10="No",0,3*SUMPRODUCT((LC_Refrig[Volts]=480)*(LC_Refrig[Ph]=3)*(LC_Refrig[Ded. Ckt]<>"N")*LC_Refrig[Qty])+2*SUMPRODUCT((LC_Refrig[Volts]=480)*(LC_Refrig[Ph]=1)*(LC_Refrig[Ded. Ckt]<>"N")*LC_Refrig[Qty])+SUMPRODUCT((LC_Refrig[Volts]=277)*(LC_Refrig[Ded. Ckt]<>"N")*LC_Refrig[Qty]))} -> 0 | D132: {=IF($AC$10="No",0,3*SUMPRODUCT((LC_Refrig[Volts]=208)*(LC_Refrig[Ph]=3)*(LC_Refrig[Ded. Ckt]<>"N")*LC_Refrig[Qty])+2*SUMPRODUCT((LC_Refrig[Volts]=208)*(LC_Refrig[Ph]=1)*(LC_Refrig[Ded. Ckt]<>"N")*LC_Refrig[Qty])+SUMPRODUCT((LC_Refrig[Volts]=120)*(LC_Refrig[Ded. Ckt]<>"N")*LC_Refrig[Qty]))} -> 0 | E132: {=IF($AC$10="No",0,3*SUMPRODUCT((LC_Refrig[Volts]=240)*(LC_Refrig[Ph]=3)*(LC_Refrig[Ded. Ckt]<>"N")*LC_Refrig[Qty])+2*SUMPRODUCT((LC_Refrig[Volts]=240)*(LC_Refrig[Ph]=1)*(LC_Refrig[Ded. Ckt]<>"N")*LC_Refrig[Qty])+SUMPRODUCT((LC_Refrig[Volts]=120)*(LC_Refrig[Ded. Ckt]<>"N")*LC_Refrig[Qty]))} -> 0
B133: Mechanical | C133: {=IF($AC$11="No",0,3*SUMPRODUCT((LC_Mech[Volts]=480)*(LC_Mech[Ph]=3)*(LC_Mech[Ded. Ckt]<>"N")*LC_Mech[Qty])+2*SUMPRODUCT((LC_Mech[Volts]=480)*(LC_Mech[Ph]=1)*(LC_Mech[Ded. Ckt]<>"N")*LC_Mech[Qty])+SUMPRODUCT((LC_Mech[Volts]=277)*(LC_Mech[Ded. Ckt]<>"N")*LC_Mech[Qty]))} -> 0 | D133: {=IF($AC$11="No",0,3*SUMPRODUCT((LC_Mech[Volts]=208)*(LC_Mech[Ph]=3)*(LC_Mech[Ded. Ckt]<>"N")*LC_Mech[Qty])+2*SUMPRODUCT((LC_Mech[Volts]=208)*(LC_Mech[Ph]=1)*(LC_Mech[Ded. Ckt]<>"N")*LC_Mech[Qty])+SUMPRODUCT((LC_Mech[Volts]=120)*(LC_Mech[Ded. Ckt]<>"N")*LC_Mech[Qty]))} -> 0 | E133: {=IF($AC$11="No",0,3*SUMPRODUCT((LC_Mech[Volts]=240)*(LC_Mech[Ph]=3)*(LC_Mech[Ded. Ckt]<>"N")*LC_Mech[Qty])+2*SUMPRODUCT((LC_Mech[Volts]=240)*(LC_Mech[Ph]=1)*(LC_Mech[Ded. Ckt]<>"N")*LC_Mech[Qty])+SUMPRODUCT((LC_Mech[Volts]=120)*(LC_Mech[Ded. Ckt]<>"N")*LC_Mech[Qty]))} -> 0
B134: Plumbing | C134: {=IF($AC$12="No",0,3*SUMPRODUCT((LC_Plumb[Volts]=480)*(LC_Plumb[Ph]=3)*(LC_Plumb[Ded. Ckt]<>"N")*LC_Plumb[Qty])+2*SUMPRODUCT((LC_Plumb[Volts]=480)*(LC_Plumb[Ph]=1)*(LC_Plumb[Ded. Ckt]<>"N")*LC_Plumb[Qty])+SUMPRODUCT((LC_Plumb[Volts]=277)*(LC_Plumb[Ded. Ckt]<>"N")*LC_Plumb[Qty]))} -> 0 | D134: {=IF($AC$12="No",0,3*SUMPRODUCT((LC_Plumb[Volts]=208)*(LC_Plumb[Ph]=3)*(LC_Plumb[Ded. Ckt]<>"N")*LC_Plumb[Qty])+2*SUMPRODUCT((LC_Plumb[Volts]=208)*(LC_Plumb[Ph]=1)*(LC_Plumb[Ded. Ckt]<>"N")*LC_Plumb[Qty])+SUMPRODUCT((LC_Plumb[Volts]=120)*(LC_Plumb[Ded. Ckt]<>"N")*LC_Plumb[Qty]))} -> 0 | E134: {=IF($AC$12="No",0,3*SUMPRODUCT((LC_Plumb[Volts]=240)*(LC_Plumb[Ph]=3)*(LC_Plumb[Ded. Ckt]<>"N")*LC_Plumb[Qty])+2*SUMPRODUCT((LC_Plumb[Volts]=240)*(LC_Plumb[Ph]=1)*(LC_Plumb[Ded. Ckt]<>"N")*LC_Plumb[Qty])+SUMPRODUCT((LC_Plumb[Volts]=120)*(LC_Plumb[Ded. Ckt]<>"N")*LC_Plumb[Qty]))} -> 0
B135: Kitchen / Food Service | C135: {=IF($AC$13="No",0,3*SUMPRODUCT((LC_Kitchen[Volts]=480)*(LC_Kitchen[Ph]=3)*(LC_Kitchen[Ded. Ckt]<>"N")*LC_Kitchen[Qty])+2*SUMPRODUCT((LC_Kitchen[Volts]=480)*(LC_Kitchen[Ph]=1)*(LC_Kitchen[Ded. Ckt]<>"N")*LC_Kitchen[Qty])+SUMPRODUCT((LC_Kitchen[Volts]=277)*(LC_Kitchen[Ded. Ckt]<>"N")*LC_Kitchen[Qty]))} -> 0 | D135: {=IF($AC$13="No",0,3*SUMPRODUCT((LC_Kitchen[Volts]=208)*(LC_Kitchen[Ph]=3)*(LC_Kitchen[Ded. Ckt]<>"N")*LC_Kitchen[Qty])+2*SUMPRODUCT((LC_Kitchen[Volts]=208)*(LC_Kitchen[Ph]=1)*(LC_Kitchen[Ded. Ckt]<>"N")*LC_Kitchen[Qty])+SUMPRODUCT((LC_Kitchen[Volts]=120)*(LC_Kitchen[Ded. Ckt]<>"N")*LC_Kitchen[Qty]))} -> 0 | E135: {=IF($AC$13="No",0,3*SUMPRODUCT((LC_Kitchen[Volts]=240)*(LC_Kitchen[Ph]=3)*(LC_Kitchen[Ded. Ckt]<>"N")*LC_Kitchen[Qty])+2*SUMPRODUCT((LC_Kitchen[Volts]=240)*(LC_Kitchen[Ph]=1)*(LC_Kitchen[Ded. Ckt]<>"N")*LC_Kitchen[Qty])+SUMPRODUCT((LC_Kitchen[Volts]=120)*(LC_Kitchen[Ded. Ckt]<>"N")*LC_Kitchen[Qty]))} -> 0
B136: Elevators / Conveying | C136: {=IF($AC$14="No",0,3*SUMPRODUCT((LC_Elev[Volts]=480)*(LC_Elev[Ph]=3)*(LC_Elev[Ded. Ckt]<>"N")*LC_Elev[Qty])+2*SUMPRODUCT((LC_Elev[Volts]=480)*(LC_Elev[Ph]=1)*(LC_Elev[Ded. Ckt]<>"N")*LC_Elev[Qty])+SUMPRODUCT((LC_Elev[Volts]=277)*(LC_Elev[Ded. Ckt]<>"N")*LC_Elev[Qty]))} -> 0 | D136: {=IF($AC$14="No",0,3*SUMPRODUCT((LC_Elev[Volts]=208)*(LC_Elev[Ph]=3)*(LC_Elev[Ded. Ckt]<>"N")*LC_Elev[Qty])+2*SUMPRODUCT((LC_Elev[Volts]=208)*(LC_Elev[Ph]=1)*(LC_Elev[Ded. Ckt]<>"N")*LC_Elev[Qty])+SUMPRODUCT((LC_Elev[Volts]=120)*(LC_Elev[Ded. Ckt]<>"N")*LC_Elev[Qty]))} -> 0 | E136: {=IF($AC$14="No",0,3*SUMPRODUCT((LC_Elev[Volts]=240)*(LC_Elev[Ph]=3)*(LC_Elev[Ded. Ckt]<>"N")*LC_Elev[Qty])+2*SUMPRODUCT((LC_Elev[Volts]=240)*(LC_Elev[Ph]=1)*(LC_Elev[Ded. Ckt]<>"N")*LC_Elev[Qty])+SUMPRODUCT((LC_Elev[Volts]=120)*(LC_Elev[Ded. Ckt]<>"N")*LC_Elev[Qty]))} -> 0
B137: EV Charging | C137: {=IF($AC$15="No",0,3*SUMPRODUCT((LC_EV[Volts]=480)*(LC_EV[Ph]=3)*(LC_EV[Ded. Ckt]<>"N")*LC_EV[Qty])+2*SUMPRODUCT((LC_EV[Volts]=480)*(LC_EV[Ph]=1)*(LC_EV[Ded. Ckt]<>"N")*LC_EV[Qty])+SUMPRODUCT((LC_EV[Volts]=277)*(LC_EV[Ded. Ckt]<>"N")*LC_EV[Qty]))} -> 0 | D137: {=IF($AC$15="No",0,3*SUMPRODUCT((LC_EV[Volts]=208)*(LC_EV[Ph]=3)*(LC_EV[Ded. Ckt]<>"N")*LC_EV[Qty])+2*SUMPRODUCT((LC_EV[Volts]=208)*(LC_EV[Ph]=1)*(LC_EV[Ded. Ckt]<>"N")*LC_EV[Qty])+SUMPRODUCT((LC_EV[Volts]=120)*(LC_EV[Ded. Ckt]<>"N")*LC_EV[Qty]))} -> 0 | E137: {=IF($AC$15="No",0,3*SUMPRODUCT((LC_EV[Volts]=240)*(LC_EV[Ph]=3)*(LC_EV[Ded. Ckt]<>"N")*LC_EV[Qty])+2*SUMPRODUCT((LC_EV[Volts]=240)*(LC_EV[Ph]=1)*(LC_EV[Ded. Ckt]<>"N")*LC_EV[Qty])+SUMPRODUCT((LC_EV[Volts]=120)*(LC_EV[Ded. Ckt]<>"N")*LC_EV[Qty]))} -> 0
B138: Data / IT | C138: {=IF($AC$16="No",0,3*SUMPRODUCT((LC_Data[Volts]=480)*(LC_Data[Ph]=3)*(LC_Data[Ded. Ckt]<>"N")*LC_Data[Qty])+2*SUMPRODUCT((LC_Data[Volts]=480)*(LC_Data[Ph]=1)*(LC_Data[Ded. Ckt]<>"N")*LC_Data[Qty])+SUMPRODUCT((LC_Data[Volts]=277)*(LC_Data[Ded. Ckt]<>"N")*LC_Data[Qty]))} -> 0 | D138: {=IF($AC$16="No",0,3*SUMPRODUCT((LC_Data[Volts]=208)*(LC_Data[Ph]=3)*(LC_Data[Ded. Ckt]<>"N")*LC_Data[Qty])+2*SUMPRODUCT((LC_Data[Volts]=208)*(LC_Data[Ph]=1)*(LC_Data[Ded. Ckt]<>"N")*LC_Data[Qty])+SUMPRODUCT((LC_Data[Volts]=120)*(LC_Data[Ded. Ckt]<>"N")*LC_Data[Qty]))} -> 0 | E138: {=IF($AC$16="No",0,3*SUMPRODUCT((LC_Data[Volts]=240)*(LC_Data[Ph]=3)*(LC_Data[Ded. Ckt]<>"N")*LC_Data[Qty])+2*SUMPRODUCT((LC_Data[Volts]=240)*(LC_Data[Ph]=1)*(LC_Data[Ded. Ckt]<>"N")*LC_Data[Qty])+SUMPRODUCT((LC_Data[Volts]=120)*(LC_Data[Ded. Ckt]<>"N")*LC_Data[Qty]))} -> 0
B139: Fire / Life Safety | C139: {=IF($AC$17="No",0,3*SUMPRODUCT((LC_Fire[Volts]=480)*(LC_Fire[Ph]=3)*(LC_Fire[Ded. Ckt]<>"N")*LC_Fire[Qty])+2*SUMPRODUCT((LC_Fire[Volts]=480)*(LC_Fire[Ph]=1)*(LC_Fire[Ded. Ckt]<>"N")*LC_Fire[Qty])+SUMPRODUCT((LC_Fire[Volts]=277)*(LC_Fire[Ded. Ckt]<>"N")*LC_Fire[Qty]))} -> 0 | D139: {=IF($AC$17="No",0,3*SUMPRODUCT((LC_Fire[Volts]=208)*(LC_Fire[Ph]=3)*(LC_Fire[Ded. Ckt]<>"N")*LC_Fire[Qty])+2*SUMPRODUCT((LC_Fire[Volts]=208)*(LC_Fire[Ph]=1)*(LC_Fire[Ded. Ckt]<>"N")*LC_Fire[Qty])+SUMPRODUCT((LC_Fire[Volts]=120)*(LC_Fire[Ded. Ckt]<>"N")*LC_Fire[Qty]))} -> 0 | E139: {=IF($AC$17="No",0,3*SUMPRODUCT((LC_Fire[Volts]=240)*(LC_Fire[Ph]=3)*(LC_Fire[Ded. Ckt]<>"N")*LC_Fire[Qty])+2*SUMPRODUCT((LC_Fire[Volts]=240)*(LC_Fire[Ph]=1)*(LC_Fire[Ded. Ckt]<>"N")*LC_Fire[Qty])+SUMPRODUCT((LC_Fire[Volts]=120)*(LC_Fire[Ded. Ckt]<>"N")*LC_Fire[Qty]))} -> 0
B140: Process / Industrial | C140: {=IF($AC$18="No",0,3*SUMPRODUCT((LC_Process[Volts]=480)*(LC_Process[Ph]=3)*(LC_Process[Ded. Ckt]<>"N")*LC_Process[Qty])+2*SUMPRODUCT((LC_Process[Volts]=480)*(LC_Process[Ph]=1)*(LC_Process[Ded. Ckt]<>"N")*LC_Process[Qty])+SUMPRODUCT((LC_Process[Volts]=277)*(LC_Process[Ded. Ckt]<>"N")*LC_Process[Qty]))} -> 0 | D140: {=IF($AC$18="No",0,3*SUMPRODUCT((LC_Process[Volts]=208)*(LC_Process[Ph]=3)*(LC_Process[Ded. Ckt]<>"N")*LC_Process[Qty])+2*SUMPRODUCT((LC_Process[Volts]=208)*(LC_Process[Ph]=1)*(LC_Process[Ded. Ckt]<>"N")*LC_Process[Qty])+SUMPRODUCT((LC_Process[Volts]=120)*(LC_Process[Ded. Ckt]<>"N")*LC_Process[Qty]))} -> 0 | E140: {=IF($AC$18="No",0,3*SUMPRODUCT((LC_Process[Volts]=240)*(LC_Process[Ph]=3)*(LC_Process[Ded. Ckt]<>"N")*LC_Process[Qty])+2*SUMPRODUCT((LC_Process[Volts]=240)*(LC_Process[Ph]=1)*(LC_Process[Ded. Ckt]<>"N")*LC_Process[Qty])+SUMPRODUCT((LC_Process[Volts]=120)*(LC_Process[Ded. Ckt]<>"N")*LC_Process[Qty]))} -> 0
B141: TOTAL SPACES | C141: =SUM(C129:C140) -> 0 | D141: =SUM(D129:D140) -> 0 | E141: =SUM(E129:E140) -> 0
B142: Design Spare Spaces (%) | C142: 0.25
B143: Spaces incl. Spares | C143: =ROUNDUP(C141*(1+$C$142),0) -> 0 | D143: =ROUNDUP(D141*(1+$C$142),0) -> 0 | E143: =ROUNDUP(E141*(1+$C$142),0) -> 0
B144: Suggested 42-Pole Panels | C144: =IF(C143=0,0,ROUNDUP(C143/42,0)) -> 0 | D144: =IF(D143=0,0,ROUNDUP(D143/42,0)) -> 0 | E144: =IF(E143=0,0,ROUNDUP(E143/42,0)) -> 0
A146: {="TOTAL SERVICE LOAD SUMMARY — NEC "&NECREF("220")} -> TOTAL SERVICE LOAD SUMMARY — NEC 220
...

Sheet Utility Demand
A1: {="UTILITY DEMAND ANALYSIS — NEC "&NECREF("220.87")&"(1) — 12-MONTH BILLING DATA"} -> UTILITY DEMAND ANALYSIS — NEC 220.87(1) — 12-MONTH BILLING DATA
B2: Project: | C2: =IF(Dashboard!B7="","—",Dashboard!B7) -> — | G2: Service Voltage: | H2: =IF(Dashboard!$C$38="","",Dashboard!$C$38)
A4: SETTINGS
C6: Default Power Factor | D6: 0.9 | E6: Used only when a bill has neither kVAR nor a stated PF.
C7: Assumed Load Factor (optional) | E7: If a bill has no metered peak, Peak kW = Avg kW ÷ Load Factor. Leave blank to use metered peaks only.
C8: System Voltage (L-L) | D8: =Dashboard!C39
C9: Phase | D9: =Dashboard!C40
C10: Existing Service (A) | E10: Main breaker / service rating. Leave blank for a new service; capacity in D11 stays blank.
C11: Existing Service Capacity (kVA) | D11: =IF(OR(D10=0,D10="",D8="",D9=""),"",IF(D9=3,D8*D10*SQRT(3)/1000,D8*D10/1000))
A13: METER 1 | L13: SÄZÄN PowerCalc ▸ Existing Demand ▸ Add Meter creates another meter section below.
B15: Meter # | E15: Source: | H15: Rate Schedule: | K15: Serves:
E16: Utility: | F16: =_xlfn.LET(_xlpm.t,""&$F15,_xlpm.p,IF(_xlpm.t="",INDEX(Util_Provider,1),_xlfn.XLOOKUP(_xlpm.t,Util_Tags,Util_Provider,"")),IF(""&_xlpm.p="","",_xlpm.p)) | K16: Metered Board: | M16: Board this meter measures — its 125% load lands on that board and rolls up the tree. Blank = service board.
B18: Cycle | C18: Start Date | D18: End Date | E18: Days | F18: kWh | G18: Avg kW | H18: Peak kW (Bill) | I18: Peak kVAR (Bill) | J18: PF (Bill) | K18: PF Used | L18: Peak kW Used | M18: Peak kVA | N18: Peak A | O18: Notes
B19: 1 | E19: =IF(OR($C19="",$D19=""),"",$D19-$C19) | G19: =IF(OR($F19="",$E19=""),"",$F19/($E19*24)) | K19: =IF($J19<>"",$J19,IF(AND($H19<>"",$I19<>""),$H19/SQRT($H19^2+$I19^2),$D$6)) -> 0.9 | L19: =IF($H19<>"",$H19,IF(AND($G19<>"",$D$7<>""),$G19/$D$7,"")) | M19: =IF($L19="","",$L19/$K19) | N19: =IF(OR($M19="",N($D$8)=0),"",$M19*1000/IF($D$9=3,$D$8*SQRT(3),$D$8))
B20: 2 | E20: =IF(OR($C20="",$D20=""),"",$D20-$C20) | G20: =IF(OR($F20="",$E20=""),"",$F20/($E20*24)) | K20: =IF($J20<>"",$J20,IF(AND($H20<>"",$I20<>""),$H20/SQRT($H20^2+$I20^2),$D$6)) -> 0.9 | L20: =IF($H20<>"",$H20,IF(AND($G20<>"",$D$7<>""),$G20/$D$7,"")) | M20: =IF($L20="","",$L20/$K20) | N20: =IF(OR($M20="",N($D$8)=0),"",$M20*1000/IF($D$9=3,$D$8*SQRT(3),$D$8))
B21: 3 | E21: =IF(OR($C21="",$D21=""),"",$D21-$C21) | G21: =IF(OR($F21="",$E21=""),"",$F21/($E21*24)) | K21: =IF($J21<>"",$J21,IF(AND($H21<>"",$I21<>""),$H21/SQRT($H21^2+$I21^2),$D$6)) -> 0.9 | L21: =IF($H21<>"",$H21,IF(AND($G21<>"",$D$7<>""),$G21/$D$7,"")) | M21: =IF($L21="","",$L21/$K21) | N21: =IF(OR($M21="",N($D$8)=0),"",$M21*1000/IF($D$9=3,$D$8*SQRT(3),$D$8))
B22: 4 | E22: =IF(OR($C22="",$D22=""),"",$D22-$C22) | G22: =IF(OR($F22="",$E22=""),"",$F22/($E22*24)) | K22: =IF($J22<>"",$J22,IF(AND($H22<>"",$I22<>""),$H22/SQRT($H22^2+$I22^2),$D$6)) -> 0.9 | L22: =IF($H22<>"",$H22,IF(AND($G22<>"",$D$7<>""),$G22/$D$7,"")) | M22: =IF($L22="","",$L22/$K22) | N22: =IF(OR($M22="",N($D$8)=0),"",$M22*1000/IF($D$9=3,$D$8*SQRT(3),$D$8))
B23: 5 | E23: =IF(OR($C23="",$D23=""),"",$D23-$C23) | G23: =IF(OR($F23="",$E23=""),"",$F23/($E23*24)) | K23: =IF($J23<>"",$J23,IF(AND($H23<>"",$I23<>""),$H23/SQRT($H23^2+$I23^2),$D$6)) -> 0.9 | L23: =IF($H23<>"",$H23,IF(AND($G23<>"",$D$7<>""),$G23/$D$7,"")) | M23: =IF($L23="","",$L23/$K23) | N23: =IF(OR($M23="",N($D$8)=0),"",$M23*1000/IF($D$9=3,$D$8*SQRT(3),$D$8))
B24: 6 | E24: =IF(OR($C24="",$D24=""),"",$D24-$C24) | G24: =IF(OR($F24="",$E24=""),"",$F24/($E24*24)) | K24: =IF($J24<>"",$J24,IF(AND($H24<>"",$I24<>""),$H24/SQRT($H24^2+$I24^2),$D$6)) -> 0.9 | L24: =IF($H24<>"",$H24,IF(AND($G24<>"",$D$7<>""),$G24/$D$7,"")) | M24: =IF($L24="","",$L24/$K24) | N24: =IF(OR($M24="",N($D$8)=0),"",$M24*1000/IF($D$9=3,$D$8*SQRT(3),$D$8))
B25: 7 | E25: =IF(OR($C25="",$D25=""),"",$D25-$C25) | G25: =IF(OR($F25="",$E25=""),"",$F25/($E25*24)) | K25: =IF($J25<>"",$J25,IF(AND($H25<>"",$I25<>""),$H25/SQRT($H25^2+$I25^2),$D$6)) -> 0.9 | L25: =IF($H25<>"",$H25,IF(AND($G25<>"",$D$7<>""),$G25/$D$7,"")) | M25: =IF($L25="","",$L25/$K25) | N25: =IF(OR($M25="",N($D$8)=0),"",$M25*1000/IF($D$9=3,$D$8*SQRT(3),$D$8))
B26: 8 | E26: =IF(OR($C26="",$D26=""),"",$D26-$C26) | G26: =IF(OR($F26="",$E26=""),"",$F26/($E26*24)) | K26: =IF($J26<>"",$J26,IF(AND($H26<>"",$I26<>""),$H26/SQRT($H26^2+$I26^2),$D$6)) -> 0.9 | L26: =IF($H26<>"",$H26,IF(AND($G26<>"",$D$7<>""),$G26/$D$7,"")) | M26: =IF($L26="","",$L26/$K26) | N26: =IF(OR($M26="",N($D$8)=0),"",$M26*1000/IF($D$9=3,$D$8*SQRT(3),$D$8))
B27: 9 | E27: =IF(OR($C27="",$D27=""),"",$D27-$C27) | G27: =IF(OR($F27="",$E27=""),"",$F27/($E27*24)) | K27: =IF($J27<>"",$J27,IF(AND($H27<>"",$I27<>""),$H27/SQRT($H27^2+$I27^2),$D$6)) -> 0.9 | L27: =IF($H27<>"",$H27,IF(AND($G27<>"",$D$7<>""),$G27/$D$7,"")) | M27: =IF($L27="","",$L27/$K27) | N27: =IF(OR($M27="",N($D$8)=0),"",$M27*1000/IF($D$9=3,$D$8*SQRT(3),$D$8))
B28: 10 | E28: =IF(OR($C28="",$D28=""),"",$D28-$C28) | G28: =IF(OR($F28="",$E28=""),"",$F28/($E28*24)) | K28: =IF($J28<>"",$J28,IF(AND($H28<>"",$I28<>""),$H28/SQRT($H28^2+$I28^2),$D$6)) -> 0.9 | L28: =IF($H28<>"",$H28,IF(AND($G28<>"",$D$7<>""),$G28/$D$7,"")) | M28: =IF($L28="","",$L28/$K28) | N28: =IF(OR($M28="",N($D$8)=0),"",$M28*1000/IF($D$9=3,$D$8*SQRT(3),$D$8))
B29: 11 | E29: =IF(OR($C29="",$D29=""),"",$D29-$C29) | G29: =IF(OR($F29="",$E29=""),"",$F29/($E29*24)) | K29: =IF($J29<>"",$J29,IF(AND($H29<>"",$I29<>""),$H29/SQRT($H29^2+$I29^2),$D$6)) -> 0.9 | L29: =IF($H29<>"",$H29,IF(AND($G29<>"",$D$7<>""),$G29/$D$7,"")) | M29: =IF($L29="","",$L29/$K29) | N29: =IF(OR($M29="",N($D$8)=0),"",$M29*1000/IF($D$9=3,$D$8*SQRT(3),$D$8))
B30: 12 | E30: =IF(OR($C30="",$D30=""),"",$D30-$C30) | G30: =IF(OR($F30="",$E30=""),"",$F30/($E30*24)) | K30: =IF($J30<>"",$J30,IF(AND($H30<>"",$I30<>""),$H30/SQRT($H30^2+$I30^2),$D$6)) -> 0.9 | L30: =IF($H30<>"",$H30,IF(AND($G30<>"",$D$7<>""),$G30/$D$7,"")) | M30: =IF($L30="","",$L30/$K30) | N30: =IF(OR($M30="",N($D$8)=0),"",$M30*1000/IF($D$9=3,$D$8*SQRT(3),$D$8))
B31: METER PEAK | C31: =IF($C$15="","(enter meter #)","Meter "&$C$15) -> (enter meter #) | E31: Bill-year kWh → | F31: =SUM(F19:F30) -> 0 | K31: Peak → | L31: =IFERROR(MAX(L19:L30),0) -> 0 | M31: =IFERROR(MAX(M19:M30),0) -> 0 | N31: =IFERROR(MAX(N19:N30),0) -> 0 | O31: {=IF(TRIM(L16&"")<>"",TRIM(L16&""),Exist_ServiceBoard)}
A33: {="RESULTS — NEC "&NECREF("220.87")&" EXISTING LOAD (ALL METERS)"} -> RESULTS — NEC 220.87 EXISTING LOAD (ALL METERS)
F35: Meters Included | G35: =COUNTIF($B:$B,"METER PEAK") -> 1
F36: Total Existing Peak Demand — Sum of Meter Peaks (kW) | G36: =SUMIF($B:$B,"METER PEAK",$L:$L) -> 0
F37: Total Existing Peak Demand (kVA) | G37: =SUMIF($B:$B,"METER PEAK",$M:$M) -> 0
F38: Total Existing Peak Demand (A) | G38: =SUMIF($B:$B,"METER PEAK",$N:$N) -> 0
F39: {="NEC "&NECREF("220.87")&" Existing Load = 125% × Peak (kVA)"} -> NEC 220.87 Existing Load = 125% × Peak (kVA) | G39: =G37*1.25 -> 0
F40: {="NEC "&NECREF("220.87")&" Existing Load (A)"} -> NEC 220.87 Existing Load (A) | G40: =G38*1.25 -> 0
F41: Existing Service Capacity (kVA) | G41: =IF(D11="","",D11)
F42: Spare Capacity for New Load (kVA) | G42: =IF(G41="","",G41-G39)
F43: Service Utilization (%) | G43: =IF(G41="","",G39/G41)
B45: {="NEC "&NECREF("220.87")&"(1): existing load basis requires demand data for a full year (12 consecutive billing cycles). Multi-meter total is the non-coincident sum of each meter's individual peak (conservative)."} -> NEC 220.87(1): existing load basis requires demand data for a full year (12 consecutive billing cycles). Multi-meter total is the non-coincident sum of each meter's individual peak (conservative).
B46: PF per bill: enter the billed PF directly, or enter Peak kVAR and PF is derived (kW/√(kW²+kVAR²)). Bills with PF below 0.90 flag gold.
A48: PEAK DEMAND PROFILE — BY BILLING CYCLE (ALL METERS)
B50: Cycle | C50: Month | D50: Peak kVA | E50: Peak Cycle | F50: 125% Mark (kVA)
B51: 1 | C51: {=IF(INDEX($D$19:$D$30,$B51)="","Cycle "&$B51,TEXT(INDEX($D$19:$D$30,$B51),"mmm yy"))} -> Cycle 1 | D51: =SUMIF($B:$B,$B51,$M:$M) -> 0 | E51: =IF(AND($D51>0,$D51=MAX($D$51:$D$62)),$D51,0) -> 0 | F51: =N($G$39) -> 0
B52: 2 | C52: {=IF(INDEX($D$19:$D$30,$B52)="","Cycle "&$B52,TEXT(INDEX($D$19:$D$30,$B52),"mmm yy"))} -> Cycle 2 | D52: =SUMIF($B:$B,$B52,$M:$M) -> 0 | E52: =IF(AND($D52>0,$D52=MAX($D$51:$D$62)),$D52,0) -> 0 | F52: =N($G$39) -> 0
B53: 3 | C53: {=IF(INDEX($D$19:$D$30,$B53)="","Cycle "&$B53,TEXT(INDEX($D$19:$D$30,$B53),"mmm yy"))} -> Cycle 3 | D53: =SUMIF($B:$B,$B53,$M:$M) -> 0 | E53: =IF(AND($D53>0,$D53=MAX($D$51:$D$62)),$D53,0) -> 0 | F53: =N($G$39) -> 0
B54: 4 | C54: {=IF(INDEX($D$19:$D$30,$B54)="","Cycle "&$B54,TEXT(INDEX($D$19:$D$30,$B54),"mmm yy"))} -> Cycle 4 | D54: =SUMIF($B:$B,$B54,$M:$M) -> 0 | E54: =IF(AND($D54>0,$D54=MAX($D$51:$D$62)),$D54,0) -> 0 | F54: =N($G$39) -> 0
B55: 5 | C55: {=IF(INDEX($D$19:$D$30,$B55)="","Cycle "&$B55,TEXT(INDEX($D$19:$D$30,$B55),"mmm yy"))} -> Cycle 5 | D55: =SUMIF($B:$B,$B55,$M:$M) -> 0 | E55: =IF(AND($D55>0,$D55=MAX($D$51:$D$62)),$D55,0) -> 0 | F55: =N($G$39) -> 0
B56: 6 | C56: {=IF(INDEX($D$19:$D$30,$B56)="","Cycle "&$B56,TEXT(INDEX($D$19:$D$30,$B56),"mmm yy"))} -> Cycle 6 | D56: =SUMIF($B:$B,$B56,$M:$M) -> 0 | E56: =IF(AND($D56>0,$D56=MAX($D$51:$D$62)),$D56,0) -> 0 | F56: =N($G$39) -> 0
B57: 7 | C57: {=IF(INDEX($D$19:$D$30,$B57)="","Cycle "&$B57,TEXT(INDEX($D$19:$D$30,$B57),"mmm yy"))} -> Cycle 7 | D57: =SUMIF($B:$B,$B57,$M:$M) -> 0 | E57: =IF(AND($D57>0,$D57=MAX($D$51:$D$62)),$D57,0) -> 0 | F57: =N($G$39) -> 0
B58: 8 | C58: {=IF(INDEX($D$19:$D$30,$B58)="","Cycle "&$B58,TEXT(INDEX($D$19:$D$30,$B58),"mmm yy"))} -> Cycle 8 | D58: =SUMIF($B:$B,$B58,$M:$M) -> 0 | E58: =IF(AND($D58>0,$D58=MAX($D$51:$D$62)),$D58,0) -> 0 | F58: =N($G$39) -> 0
B59: 9 | C59: {=IF(INDEX($D$19:$D$30,$B59)="","Cycle "&$B59,TEXT(INDEX($D$19:$D$30,$B59),"mmm yy"))} -> Cycle 9 | D59: =SUMIF($B:$B,$B59,$M:$M) -> 0 | E59: =IF(AND($D59>0,$D59=MAX($D$51:$D$62)),$D59,0) -> 0 | F59: =N($G$39) -> 0
B60: 10 | C60: {=IF(INDEX($D$19:$D$30,$B60)="","Cycle "&$B60,TEXT(INDEX($D$19:$D$30,$B60),"mmm yy"))} -> Cycle 10 | D60: =SUMIF($B:$B,$B60,$M:$M) -> 0 | E60: =IF(AND($D60>0,$D60=MAX($D$51:$D$62)),$D60,0) -> 0 | F60: =N($G$39) -> 0
B61: 11 | C61: {=IF(INDEX($D$19:$D$30,$B61)="","Cycle "&$B61,TEXT(INDEX($D$19:$D$30,$B61),"mmm yy"))} -> Cycle 11 | D61: =SUMIF($B:$B,$B61,$M:$M) -> 0 | E61: =IF(AND($D61>0,$D61=MAX($D$51:$D$62)),$D61,0) -> 0 | F61: =N($G$39) -> 0
B62: 12 | C62: {=IF(INDEX($D$19:$D$30,$B62)="","Cycle "&$B62,TEXT(INDEX($D$19:$D$30,$B62),"mmm yy"))} -> Cycle 12 | D62: =SUMIF($B:$B,$B62,$M:$M) -> 0 | E62: =IF(AND($D62>0,$D62=MAX($D$51:$D$62)),$D62,0) -> 0 | F62: =N($G$39) -> 0
B68: {="Bars = all meters' billed peak kVA summed per cycle (month from Meter 1 end dates); gold = peak cycle; red dash = 125% NEC "&NECREF("220.87")&" existing load (G38)."} -> Bars = all meters' billed peak kVA summed per cycle (month from Meter 1 end dates); gold = peak cycle; red dash = 125% NEC 220.87 existing load (G38).

Sheet Logging Demand
A1: {="30-DAY LOGGING DEMAND — NEC "&NECREF("220.87")&"(2) — METERING / LOGGING SESSION"} -> 30-DAY LOGGING DEMAND — NEC 220.87(2) — METERING / LOGGING SESSION
B2: Project: | C2: =IF(Dashboard!B7="","—",Dashboard!B7) -> — | G2: Service Voltage: | H2: =IF(Dashboard!$C$38="","",Dashboard!$C$38)
A4: SETTINGS
B6: Data Source | D6: Choose whether results use the logger-reported peaks (manual block) or the raw interval data pasted below.
B7: Default Power Factor | C7: 0.9 | D7: Used when the logger provides kW only (no kVAR / PF / kVA).
B8: System Voltage (L-L) | C8: =Dashboard!C39
B9: Phase | C9: =Dashboard!C40
B10: Existing Service (A) | C10: 0
B11: Existing Service Capacity (kVA) | C11: =IF(C10=0,"",IF(C9=3,C8*C10*SQRT(3)/1000,C8*C10/1000))
B12: Service Source | D12: Dashboard utility source this logging session measured. Blank = Source 1.
B13: Utility / Provider | C13: =_xlfn.LET(_xlpm.t,""&$C12,_xlpm.p,IF(_xlpm.t="",INDEX(Util_Provider,1),_xlfn.XLOOKUP(_xlpm.t,Util_Tags,Util_Provider,"")),IF(""&_xlpm.p="","",_xlpm.p)) | D13: From Dashboard ▸ Utility Sources — enter the provider there.
B14: Metered Board | D14: {="Board this session measured — its NEC "&NECREF("220.87")&" load lands on "&IF(Exist_LogBoard="","(no board yet)",Exist_LogBoard)&" and rolls up the tree. Blank = service board."} -> Board this session measured — its NEC 220.87 load lands on (no board yet) and rolls up the tree. Blank = service board.
A15: MANUAL PEAK ENTRY — FROM LOGGER REPORT
B17: Recording Start Date
B18: Recording End Date
B19: Recording Duration (days) | C19: =IF(OR(C17="",C18=""),"",C18-C17) | E19: {=IF(C19="","",IF(C19<30,("⚠ NEC "&NECREF("220.87")&"(2) requires a minimum 30-day recording"),"✓ ≥ 30 days"))}
B20: Recorded Peak kW
B21: Recorded Peak kVAR (optional)
B22: Recorded PF (optional)
B23: PF Used | C23: =IF(C22<>"",C22,IF(AND(C20<>"",C21<>""),C20/SQRT(C20^2+C21^2),C7)) -> 0.9
B24: Peak kVA (manual entry) | C24: =IF(C20="","",C20/C23)
A26: RAW INTERVAL DATA — SUMMARY | E26: Paste the logger export exactly as received into the grey columns G to K starting at row 54 — Date, Time, Avg kW, and kVAR / kVA if the logger supplied them. The Date column only needs a value where the day changes; blanks are carried down automatically. Columns B to E derive the timestamp and are locked. Depth is 10,000 intervals, enough for 30 days at 4-minute resolution.
B28: Records Found | C28: =COUNT($C$79:$C$50031) -> 0 | E28: =IF($C$28=0,"",IF(OR($C$31="",$C$32="",$C$32=0),"",_xlfn.LET(_xlpm.exp,ROUND($C$31*1440/$C$32,0)+1,IF(ABS(_xlpm.exp-$C$28)<=1,"✔ no gaps detected","⚠ "&TEXT(_xlpm.exp-$C$28,"#,##0")&" interval(s) missing — logger gap or partial days"))))
B29: First Timestamp | C29: =IF($C$28=0,"",MIN($B$79:$B$50031))
B30: Last Timestamp | C30: =IF($C$28=0,"",MAX($B$79:$B$50031))
B31: Recording Span (days) | C31: =IF($C$28=0,"",C30-C29) | E31: {=IF($C$31="","",IF($C$31>=30,("✔ meets the 30-day minimum in "&NECREF("220.87")),"✘ only "&TEXT($C$31,"0.0")&(" days — "&NECREF("220.87")&" requires at least 30")))}
B32: Interval (most common, min) | C32: {=IF($C$28<2,"",IFERROR(_xlfn.LET(_xlpm.t,_xlfn._xlws.FILTER($B$79:$B$10025,$B$79:$B$10025<>""),_xlpm.d,ROUND((_xlfn.DROP(_xlpm.t,1)-_xlfn.DROP(_xlpm.t,-1))*1440,0),IFERROR(MODE(_xlpm.d),MEDIAN(_xlpm.d))),""))} | E32: =IF($C$32="","",IF($C$32<=15,"✔ "&TEXT($C$32,"0")&"-minute intervals","⚠ "&TEXT($C$32,"0")&"-minute intervals — 15 minutes or finer is expected for demand data"))
B33: Max kW (from data) | C33: =IF($C$28=0,"",MAX($C$79:$C$50031)) | E33: =IF($C$33="","","peak at "&TEXT(IFERROR(INDEX($B$79:$B$10025,MATCH($C$33,$C$79:$C$10025,0)),""),"ddd yyyy-mm-dd hh:mm"))
B34: kVAR Coincident with Peak kW | C34: =IF($C$28=0,"",IFERROR(INDEX($D$79:$D$50031,MATCH($C$33,$C$79:$C$50031,0)),""))
B35: Max kVA (from data) | C35: =IF($C$28=0,"",IF(COUNT($E$79:$E$50031)>0,MAX($E$79:$E$50031),IF(ISNUMBER(C34),SQRT(C33^2+C34^2),C33/C7)))
B36: Load Factor (avg ÷ peak) | C36: =IF(OR($C$28=0,$C$33="",$C$33=0),"",AVERAGE($C$79:$C$10025)/$C$33) | E36: =IF($C$36="","",IF($C$36>=0.6,"steady load — peak is representative",IF($C$36>=0.35,"typical commercial profile","peaky load — the 125% figure is driven by short spikes, worth reviewing the duration curve")))
A38: COMPLIANCE & SEASONAL ADJUSTMENT
B40: Recording taken during period of maximum loading? | D40: {=IF(C40="Yes","✓",("⚠ NEC "&NECREF("220.87")&"(2): data must be taken while the building is at its period of maximum loading"))} -> ⚠ NEC 220.87(2): data must be taken while the building is at its period of maximum loading
B41: Seasonal / Periodic Load Adjustment Factor | C41: 1 | D41: Multiplier on peak to account for seasonal/periodic loads not energized during the recording (e.g., heating logged in summer). 1.00 = no adjustment.
A43: {="RESULTS — NEC "&NECREF("220.87")&" EXISTING LOAD"} -> RESULTS — NEC 220.87 EXISTING LOAD
B45: Governing Peak kW | C45: =IF($C$6="Manual Peak Entry",IF(C20="",0,C20),IF(C28=0,0,C33)) -> 0
B46: Governing Peak kVA | C46: =IF($C$6="Manual Peak Entry",IF(C24="",0,C24),IF(C28=0,0,C35)) -> 0
B47: Seasonally Adjusted Peak kVA | C47: =C46*C41 -> 0
B48: {="NEC "&NECREF("220.87")&" Existing Load = 125% × Adjusted Peak (kVA)"} -> NEC 220.87 Existing Load = 125% × Adjusted Peak (kVA) | C48: =C47*1.25 -> 0
B49: {="NEC "&NECREF("220.87")&" Existing Load (A)"} -> NEC 220.87 Existing Load (A) | C49: =IF(OR(C48=0,N(C8)=0),"",C48*1000/IF(C9=3,C8*SQRT(3),C8))
B50: Existing Service Capacity (kVA) | C50: =IF(C11="","",C11)
B51: Spare Capacity for New Load (kVA) | C51: =IF(C50="","",C50-C48)
B52: Service Utilization (%) | C52: =IF(C50="","",C48/C50)
A54: DEMAND PROFILE — LOAD DURATION CURVE
A55: Every interval sorted from highest to lowest demand. A curve that drops away steeply means the peak is a brief spike and the 125% figure is conservative; a flat curve means the load is sustained and the peak is representative. Populates once the logger export is pasted below.
A76: RAW INTERVAL DATA — PASTE LOGGER EXPORT BELOW (kVAR / kVA COLUMNS OPTIONAL)
G77: PASTE EXACTLY AS RECEIVED → | M77: DURATION CURVE DATA — derived, feeds the chart
B78: Timestamp | C78: kW | D78: kVAR (optional) | E78: kVA (optional) | G78: Date | H78: Time | I78: Avg kW | J78: kVAR (optional) | K78: kVA (optional) | M78: % of Time | N78: kW (sorted desc)
B79: {=_xlfn.LET(_xlpm.g,$G$79:$G$10025,_xlpm.h,$H$79:$H$10025,_xlpm.i,$I$79:$I$10025,_xlpm.k,_xlpm.i<>"",IF(SUM(--_xlpm.k)=0,"",_xlfn.LET(_xlpm.gf,_xlfn._xlws.FILTER(_xlpm.g,_xlpm.k),_xlpm.hf,_xlfn._xlws.FILTER(_xlpm.h,_xlpm.k),_xlpm.d,_xlfn.SCAN(0,_xlpm.gf,_xlfn.LAMBDA(_xlpm.a,_xlpm.x,IF(_xlpm.x="",_xlpm.a,IF(ISNUMBER(_xlpm.x),_xlpm.x,IFERROR(DATEVALUE(_xlpm.x),_xlpm.a))))),_xlpm.t,IF(ISNUMBER(_xlpm.hf),MOD(_xlpm.hf,1),IFERROR(TIMEVALUE(_xlpm.hf),0)),_xlpm.d+_xlpm.t)))} | C79: {=_xlfn.LET(_xlpm.i,$I$79:$I$10025,_xlpm.c,$I$79:$I$10025,_xlpm.k,_xlpm.i<>"",IF(SUM(--_xlpm.k)=0,"",_xlfn.LET(_xlpm.v,_xlfn._xlws.FILTER(_xlpm.c,_xlpm.k),IF(_xlpm.v="","",_xlpm.v))))} | D79: {=_xlfn.LET(_xlpm.i,$I$79:$I$10025,_xlpm.c,$J$79:$J$10025,_xlpm.k,_xlpm.i<>"",IF(SUM(--_xlpm.k)=0,"",_xlfn.LET(_xlpm.v,_xlfn._xlws.FILTER(_xlpm.c,_xlpm.k),IF(_xlpm.v="","",_xlpm.v))))} | E79: {=_xlfn.LET(_xlpm.i,$I$79:$I$10025,_xlpm.c,$K$79:$K$10025,_xlpm.k,_xlpm.i<>"",IF(SUM(--_xlpm.k)=0,"",_xlfn.LET(_xlpm.v,_xlfn._xlws.FILTER(_xlpm.c,_xlpm.k),IF(_xlpm.v="","",_xlpm.v))))} | M79: {=IF($C$28=0,"",IFERROR(_xlfn.SEQUENCE(ROWS(_xlfn.ANCHORARRAY($N$79)))/ROWS(_xlfn.ANCHORARRAY($N$79)),""))} | N79: {=IFERROR(_xlfn._xlws.SORT(_xlfn._xlws.FILTER($C$79:$C$10025,$C$79:$C$10025<>""),1,-1),"")}

Sheet Generator
A1: GENERATOR SIZING — NEC 700 / 701 / 702
B2: Project: | C2: =IF(Dashboard!B7="","—",Dashboard!B7) -> — | G2: Service Voltage: | H2: =IF(Dashboard!$C$38="","",Dashboard!$C$38)
A4: SETTINGS
B6: Generator Rated PF | C6: 0.8 | E6: Design Margin (×) | F6: 1.2 | H6: Assumed Load PF (kVA→kW) | I6: 0.9 | K6: Sizing Basis (ATS & Gen) | L6: Calculated Demand
A8: LOADS FROM LOAD CALC (Gen = Y)
B9: Section | C9: Connected kVA | D9: Include?
B10: Site / Exterior | C10: {=INDEX(LC_GenByCategory,ROW()-ROW($B$9))} -> 0 | D10: Y
B11: House / Misc | C11: {=INDEX(LC_GenByCategory,ROW()-ROW($B$9))} -> 0 | D11: Y
B12: Department / Owner | C12: {=INDEX(LC_GenByCategory,ROW()-ROW($B$9))} -> 0 | D12: Y
B13: Refrigeration | C13: {=INDEX(LC_GenByCategory,ROW()-ROW($B$9))} -> 0 | D13: Y
B14: Mechanical | C14: {=INDEX(LC_GenByCategory,ROW()-ROW($B$9))} -> 0 | D14: Y
B15: Plumbing | C15: {=INDEX(LC_GenByCategory,ROW()-ROW($B$9))} -> 0 | D15: Y
B16: Kitchen / Food Service | C16: {=INDEX(LC_GenByCategory,ROW()-ROW($B$9))} -> 0 | D16: Y
B17: Elevators / Conveying | C17: {=INDEX(LC_GenByCategory,ROW()-ROW($B$9))} -> 0 | D17: Y
B18: EV Charging | C18: {=INDEX(LC_GenByCategory,ROW()-ROW($B$9))} -> 0 | D18: Y
B19: Data / IT | C19: {=INDEX(LC_GenByCategory,ROW()-ROW($B$9))} -> 0 | D19: Y
B20: Fire / Life Safety | C20: {=INDEX(LC_GenByCategory,ROW()-ROW($B$9))} -> 0 | D20: Y
B21: Process / Industrial | C21: {=INDEX(LC_GenByCategory,ROW()-ROW($B$9))} -> 0 | D21: Y
B23: TOTAL INCLUDED (kVA) | C23: =SUMIF($D$10:$D$21,"Y",$C$10:$C$21) -> 0
A25: ADDITIONAL / MANUAL LOADS
B26: Description | C26: Load Class | D26: Qty | E26: kW each | F26: PF | G26: kW total | H26: kVA | I26: Start Method | J26: Start kVA | K26: Notes | L26: Unit
G27: =IF(OR(GEN_Loads[[#This Row],[Qty]]="",GEN_Loads[[#This Row],[kW each]]=""),"",GEN_Loads[[#This Row],[Qty]]*GEN_Loads[[#This Row],[kW each]]) | H27: =IF(GEN_Loads[[#This Row],[kW total]]="","",GEN_Loads[[#This Row],[kW total]]/IF(GEN_Loads[[#This Row],[PF]]="",0.8,GEN_Loads[[#This Row],[PF]])) | J27: {=IF(GEN_Loads[[#This Row],[kVA]]="","",GEN_Loads[[#This Row],[kVA]]*_xlfn.SWITCH(GEN_Loads[[#This Row],[Start Method]],"Across-the-Line",6,"Soft Start",3,"VFD",1.5,"None",1,1))}
G28: =IF(OR(GEN_Loads[[#This Row],[Qty]]="",GEN_Loads[[#This Row],[kW each]]=""),"",GEN_Loads[[#This Row],[Qty]]*GEN_Loads[[#This Row],[kW each]]) | H28: =IF(GEN_Loads[[#This Row],[kW total]]="","",GEN_Loads[[#This Row],[kW total]]/IF(GEN_Loads[[#This Row],[PF]]="",0.8,GEN_Loads[[#This Row],[PF]])) | J28: {=IF(GEN_Loads[[#This Row],[kVA]]="","",GEN_Loads[[#This Row],[kVA]]*_xlfn.SWITCH(GEN_Loads[[#This Row],[Start Method]],"Across-the-Line",6,"Soft Start",3,"VFD",1.5,"None",1,1))}
G29: =IF(OR(GEN_Loads[[#This Row],[Qty]]="",GEN_Loads[[#This Row],[kW each]]=""),"",GEN_Loads[[#This Row],[Qty]]*GEN_Loads[[#This Row],[kW each]]) | H29: =IF(GEN_Loads[[#This Row],[kW total]]="","",GEN_Loads[[#This Row],[kW total]]/IF(GEN_Loads[[#This Row],[PF]]="",0.8,GEN_Loads[[#This Row],[PF]])) | J29: {=IF(GEN_Loads[[#This Row],[kVA]]="","",GEN_Loads[[#This Row],[kVA]]*_xlfn.SWITCH(GEN_Loads[[#This Row],[Start Method]],"Across-the-Line",6,"Soft Start",3,"VFD",1.5,"None",1,1))}
G30: =IF(OR(GEN_Loads[[#This Row],[Qty]]="",GEN_Loads[[#This Row],[kW each]]=""),"",GEN_Loads[[#This Row],[Qty]]*GEN_Loads[[#This Row],[kW each]]) | H30: =IF(GEN_Loads[[#This Row],[kW total]]="","",GEN_Loads[[#This Row],[kW total]]/IF(GEN_Loads[[#This Row],[PF]]="",0.8,GEN_Loads[[#This Row],[PF]])) | J30: {=IF(GEN_Loads[[#This Row],[kVA]]="","",GEN_Loads[[#This Row],[kVA]]*_xlfn.SWITCH(GEN_Loads[[#This Row],[Start Method]],"Across-the-Line",6,"Soft Start",3,"VFD",1.5,"None",1,1))}
G31: =IF(OR(GEN_Loads[[#This Row],[Qty]]="",GEN_Loads[[#This Row],[kW each]]=""),"",GEN_Loads[[#This Row],[Qty]]*GEN_Loads[[#This Row],[kW each]]) | H31: =IF(GEN_Loads[[#This Row],[kW total]]="","",GEN_Loads[[#This Row],[kW total]]/IF(GEN_Loads[[#This Row],[PF]]="",0.8,GEN_Loads[[#This Row],[PF]])) | J31: {=IF(GEN_Loads[[#This Row],[kVA]]="","",GEN_Loads[[#This Row],[kVA]]*_xlfn.SWITCH(GEN_Loads[[#This Row],[Start Method]],"Across-the-Line",6,"Soft Start",3,"VFD",1.5,"None",1,1))}
G32: =IF(OR(GEN_Loads[[#This Row],[Qty]]="",GEN_Loads[[#This Row],[kW each]]=""),"",GEN_Loads[[#This Row],[Qty]]*GEN_Loads[[#This Row],[kW each]]) | H32: =IF(GEN_Loads[[#This Row],[kW total]]="","",GEN_Loads[[#This Row],[kW total]]/IF(GEN_Loads[[#This Row],[PF]]="",0.8,GEN_Loads[[#This Row],[PF]])) | J32: {=IF(GEN_Loads[[#This Row],[kVA]]="","",GEN_Loads[[#This Row],[kVA]]*_xlfn.SWITCH(GEN_Loads[[#This Row],[Start Method]],"Across-the-Line",6,"Soft Start",3,"VFD",1.5,"None",1,1))}
G33: =IF(OR(GEN_Loads[[#This Row],[Qty]]="",GEN_Loads[[#This Row],[kW each]]=""),"",GEN_Loads[[#This Row],[Qty]]*GEN_Loads[[#This Row],[kW each]]) | H33: =IF(GEN_Loads[[#This Row],[kW total]]="","",GEN_Loads[[#This Row],[kW total]]/IF(GEN_Loads[[#This Row],[PF]]="",0.8,GEN_Loads[[#This Row],[PF]])) | J33: {=IF(GEN_Loads[[#This Row],[kVA]]="","",GEN_Loads[[#This Row],[kVA]]*_xlfn.SWITCH(GEN_Loads[[#This Row],[Start Method]],"Across-the-Line",6,"Soft Start",3,"VFD",1.5,"None",1,1))}
G34: =IF(OR(GEN_Loads[[#This Row],[Qty]]="",GEN_Loads[[#This Row],[kW each]]=""),"",GEN_Loads[[#This Row],[Qty]]*GEN_Loads[[#This Row],[kW each]]) | H34: =IF(GEN_Loads[[#This Row],[kW total]]="","",GEN_Loads[[#This Row],[kW total]]/IF(GEN_Loads[[#This Row],[PF]]="",0.8,GEN_Loads[[#This Row],[PF]])) | J34: {=IF(GEN_Loads[[#This Row],[kVA]]="","",GEN_Loads[[#This Row],[kVA]]*_xlfn.SWITCH(GEN_Loads[[#This Row],[Start Method]],"Across-the-Line",6,"Soft Start",3,"VFD",1.5,"None",1,1))}
G35: =IF(OR(GEN_Loads[[#This Row],[Qty]]="",GEN_Loads[[#This Row],[kW each]]=""),"",GEN_Loads[[#This Row],[Qty]]*GEN_Loads[[#This Row],[kW each]]) | H35: =IF(GEN_Loads[[#This Row],[kW total]]="","",GEN_Loads[[#This Row],[kW total]]/IF(GEN_Loads[[#This Row],[PF]]="",0.8,GEN_Loads[[#This Row],[PF]])) | J35: {=IF(GEN_Loads[[#This Row],[kVA]]="","",GEN_Loads[[#This Row],[kVA]]*_xlfn.SWITCH(GEN_Loads[[#This Row],[Start Method]],"Across-the-Line",6,"Soft Start",3,"VFD",1.5,"None",1,1))}
G36: =IF(OR(GEN_Loads[[#This Row],[Qty]]="",GEN_Loads[[#This Row],[kW each]]=""),"",GEN_Loads[[#This Row],[Qty]]*GEN_Loads[[#This Row],[kW each]]) | H36: =IF(GEN_Loads[[#This Row],[kW total]]="","",GEN_Loads[[#This Row],[kW total]]/IF(GEN_Loads[[#This Row],[PF]]="",0.8,GEN_Loads[[#This Row],[PF]])) | J36: {=IF(GEN_Loads[[#This Row],[kVA]]="","",GEN_Loads[[#This Row],[kVA]]*_xlfn.SWITCH(GEN_Loads[[#This Row],[Start Method]],"Across-the-Line",6,"Soft Start",3,"VFD",1.5,"None",1,1))}
A38: SIZING SUMMARY
B40: Total Running kVA | D40: =ROUND(SUM($J$53:$J$58),1) -> 0
B41: Total Running kW | D41: =ROUND(SUM($K$53:$K$58),1) -> 0
B42: Max Single-Step Starting kVA | D42: =MAX($L$53:$L$58) -> 0
B43: Required kW = Σ per-unit (Running kW × Margin) | D43: =ROUND(SUM($M$53:$M$58),1) -> 0
B44: Required kVA = Σ per-unit max(Running kVA × Margin, Start kVA) | D44: =ROUND(SUM($N$53:$N$58),1) -> 0
B45: TOTAL SUGGESTED GENERATOR (kW) — all units / banks | D45: =IF(SUMIFS($R$53:$R$58,$Q$53:$Q$58,"Y")=0,"—",SUMIFS($R$53:$R$58,$Q$53:$Q$58,"Y")) -> —
B46: Total Generator kVA @ Rated PF | D46: =IF(ISNUMBER($D$45),ROUND(SUMIFS($S$53:$S$58,$Q$53:$Q$58,"Y"),0),"—") -> —
A48: Starting-kVA multipliers are typical (ATL×6, Soft×3, VFD×1.5). Verify against equipment data; largest single step drives voltage-dip sizing.
A51: GENERATOR UNITS — multi-unit / paralleling
B52: Unit Tag | C52: Description | D52: Parallel Group | E52: Rated PF | F52: Margin (×) | G52: Load PF | H52: Section kVA | I52: Manual kVA | J52: Running kVA | K52: Running kW | L52: Max Start kVA | M52: Required kW | N52: Required kVA | O52: Bank Req kW | P52: Bank Req kVA | Q52: Bank Primary | R52: SUGGESTED kW | S52: Gen kVA @ PF | T52: Absorb untagged? | U52: X"d (pu) | V52: Bank names (edit this list)
B53: GEN-1 | C53: Standby Generator | E53: 0.8 | F53: 1.2 | G53: 0.9 | H53: {=IF($B53="",0,IFERROR(SUMPRODUCT(($D$10:$D$21="Y")*INDEX('Load Calc'!$F$178:$K$189,0,MATCH($B53,'Load Calc'!$F$177:$K$177,0))),0)+IF($T53="Y",SUMPRODUCT(($D$10:$D$21="Y")*'Load Calc'!$L$178:$L$189),0))} -> 0 | I53: =IF($B53="",0,SUMIFS(GEN_Loads[kVA],GEN_Loads[Unit],$B53)) -> 0 | J53: =ROUND($H53+$I53,1) -> 0 | K53: =IF($B53="",0,ROUND($H53*$G53+SUMIFS(GEN_Loads[kW total],GEN_Loads[Unit],$B53),1)) -> 0 | L53: =IF($B53="",0,IFERROR(_xlfn.MAXIFS(GEN_Loads[Start kVA],GEN_Loads[Unit],$B53),0)) -> 0 | M53: {=ROUND(MAX($K53*$F53,SUMPRODUCT(($H$62:$H$69=$B53)*($C$62:$C$69="ATS")*IF(ISNUMBER($K$62:$K$69),$K$62:$K$69,0)*IF(LEFT(IF($V$62:$V$69<>"",$V$62:$V$69,Gen_SizeBasis),3)="Equ",1,$F53))*$G53),1)} -> 0 | N53: {=ROUND(MAX($J53*$F53,$L53,SUMPRODUCT(($H$62:$H$69=$B53)*($C$62:$C$69="ATS")*IF(ISNUMBER($K$62:$K$69),$K$62:$K$69,0)*IF(LEFT(IF($V$62:$V$69<>"",$V$62:$V$69,Gen_SizeBasis),3)="Equ",1,$F53))),1)} -> 0 | O53: =IF($D53="",$M53,SUMIFS($M$53:$M$58,$D$53:$D$58,$D53)) -> 0 | P53: =IF($D53="",$N53,SUMIFS($N$53:$N$58,$D$53:$D$58,$D53)) -> 0 | Q53: =IF($B53="","",IF($D53="","Y",IF(COUNTIFS($D$53:$D53,$D53)=1,"Y",""))) -> Y | R53: =IF(OR($B53="",$O53+$P53=0),"—",IFERROR(_xlfn.XLOOKUP(MAX($O53,$P53*$E53),Gen_kW_List,Gen_kW_List,"> 3000",1),"—")) -> — | S53: =IF(ISNUMBER($R53),ROUND($R53/$E53,0),"—") -> — | T53: Y | U53: 0.15 | V53: BANK-A
E54: 0.8 | F54: 1.2 | G54: 0.9 | H54: {=IF($B54="",0,IFERROR(SUMPRODUCT(($D$10:$D$21="Y")*INDEX('Load Calc'!$F$178:$K$189,0,MATCH($B54,'Load Calc'!$F$177:$K$177,0))),0)+IF($T54="Y",SUMPRODUCT(($D$10:$D$21="Y")*'Load Calc'!$L$178:$L$189),0))} -> 0 | I54: =IF($B54="",0,SUMIFS(GEN_Loads[kVA],GEN_Loads[Unit],$B54)) -> 0 | J54: =ROUND($H54+$I54,1) -> 0 | K54: =IF($B54="",0,ROUND($H54*$G54+SUMIFS(GEN_Loads[kW total],GEN_Loads[Unit],$B54),1)) -> 0 | L54: =IF($B54="",0,IFERROR(_xlfn.MAXIFS(GEN_Loads[Start kVA],GEN_Loads[Unit],$B54),0)) -> 0 | M54: {=ROUND(MAX($K54*$F54,SUMPRODUCT(($H$62:$H$69=$B54)*($C$62:$C$69="ATS")*IF(ISNUMBER($K$62:$K$69),$K$62:$K$69,0)*IF(LEFT(IF($V$62:$V$69<>"",$V$62:$V$69,Gen_SizeBasis),3)="Equ",1,$F54))*$G54),1)} -> 0 | N54: {=ROUND(MAX($J54*$F54,$L54,SUMPRODUCT(($H$62:$H$69=$B54)*($C$62:$C$69="ATS")*IF(ISNUMBER($K$62:$K$69),$K$62:$K$69,0)*IF(LEFT(IF($V$62:$V$69<>"",$V$62:$V$69,Gen_SizeBasis),3)="Equ",1,$F54))),1)} -> 0 | O54: =IF($D54="",$M54,SUMIFS($M$53:$M$58,$D$53:$D$58,$D54)) -> 0 | P54: =IF($D54="",$N54,SUMIFS($N$53:$N$58,$D$53:$D$58,$D54)) -> 0 | Q54: =IF($B54="","",IF($D54="","Y",IF(COUNTIFS($D$53:$D54,$D54)=1,"Y",""))) | R54: =IF(OR($B54="",$O54+$P54=0),"—",IFERROR(_xlfn.XLOOKUP(MAX($O54,$P54*$E54),Gen_kW_List,Gen_kW_List,"> 3000",1),"—")) -> — | S54: =IF(ISNUMBER($R54),ROUND($R54/$E54,0),"—") -> — | U54: 0.15 | V54: BANK-B
E55: 0.8 | F55: 1.2 | G55: 0.9 | H55: {=IF($B55="",0,IFERROR(SUMPRODUCT(($D$10:$D$21="Y")*INDEX('Load Calc'!$F$178:$K$189,0,MATCH($B55,'Load Calc'!$F$177:$K$177,0))),0)+IF($T55="Y",SUMPRODUCT(($D$10:$D$21="Y")*'Load Calc'!$L$178:$L$189),0))} -> 0 | I55: =IF($B55="",0,SUMIFS(GEN_Loads[kVA],GEN_Loads[Unit],$B55)) -> 0 | J55: =ROUND($H55+$I55,1) -> 0 | K55: =IF($B55="",0,ROUND($H55*$G55+SUMIFS(GEN_Loads[kW total],GEN_Loads[Unit],$B55),1)) -> 0 | L55: =IF($B55="",0,IFERROR(_xlfn.MAXIFS(GEN_Loads[Start kVA],GEN_Loads[Unit],$B55),0)) -> 0 | M55: {=ROUND(MAX($K55*$F55,SUMPRODUCT(($H$62:$H$69=$B55)*($C$62:$C$69="ATS")*IF(ISNUMBER($K$62:$K$69),$K$62:$K$69,0)*IF(LEFT(IF($V$62:$V$69<>"",$V$62:$V$69,Gen_SizeBasis),3)="Equ",1,$F55))*$G55),1)} -> 0 | N55: {=ROUND(MAX($J55*$F55,$L55,SUMPRODUCT(($H$62:$H$69=$B55)*($C$62:$C$69="ATS")*IF(ISNUMBER($K$62:$K$69),$K$62:$K$69,0)*IF(LEFT(IF($V$62:$V$69<>"",$V$62:$V$69,Gen_SizeBasis),3)="Equ",1,$F55))),1)} -> 0 | O55: =IF($D55="",$M55,SUMIFS($M$53:$M$58,$D$53:$D$58,$D55)) -> 0 | P55: =IF($D55="",$N55,SUMIFS($N$53:$N$58,$D$53:$D$58,$D55)) -> 0 | Q55: =IF($B55="","",IF($D55="","Y",IF(COUNTIFS($D$53:$D55,$D55)=1,"Y",""))) | R55: =IF(OR($B55="",$O55+$P55=0),"—",IFERROR(_xlfn.XLOOKUP(MAX($O55,$P55*$E55),Gen_kW_List,Gen_kW_List,"> 3000",1),"—")) -> — | S55: =IF(ISNUMBER($R55),ROUND($R55/$E55,0),"—") -> — | U55: 0.15 | V55: BANK-C
E56: 0.8 | F56: 1.2 | G56: 0.9 | H56: {=IF($B56="",0,IFERROR(SUMPRODUCT(($D$10:$D$21="Y")*INDEX('Load Calc'!$F$178:$K$189,0,MATCH($B56,'Load Calc'!$F$177:$K$177,0))),0)+IF($T56="Y",SUMPRODUCT(($D$10:$D$21="Y")*'Load Calc'!$L$178:$L$189),0))} -> 0 | I56: =IF($B56="",0,SUMIFS(GEN_Loads[kVA],GEN_Loads[Unit],$B56)) -> 0 | J56: =ROUND($H56+$I56,1) -> 0 | K56: =IF($B56="",0,ROUND($H56*$G56+SUMIFS(GEN_Loads[kW total],GEN_Loads[Unit],$B56),1)) -> 0 | L56: =IF($B56="",0,IFERROR(_xlfn.MAXIFS(GEN_Loads[Start kVA],GEN_Loads[Unit],$B56),0)) -> 0 | M56: {=ROUND(MAX($K56*$F56,SUMPRODUCT(($H$62:$H$69=$B56)*($C$62:$C$69="ATS")*IF(ISNUMBER($K$62:$K$69),$K$62:$K$69,0)*IF(LEFT(IF($V$62:$V$69<>"",$V$62:$V$69,Gen_SizeBasis),3)="Equ",1,$F56))*$G56),1)} -> 0 | N56: {=ROUND(MAX($J56*$F56,$L56,SUMPRODUCT(($H$62:$H$69=$B56)*($C$62:$C$69="ATS")*IF(ISNUMBER($K$62:$K$69),$K$62:$K$69,0)*IF(LEFT(IF($V$62:$V$69<>"",$V$62:$V$69,Gen_SizeBasis),3)="Equ",1,$F56))),1)} -> 0 | O56: =IF($D56="",$M56,SUMIFS($M$53:$M$58,$D$53:$D$58,$D56)) -> 0 | P56: =IF($D56="",$N56,SUMIFS($N$53:$N$58,$D$53:$D$58,$D56)) -> 0 | Q56: =IF($B56="","",IF($D56="","Y",IF(COUNTIFS($D$53:$D56,$D56)=1,"Y",""))) | R56: =IF(OR($B56="",$O56+$P56=0),"—",IFERROR(_xlfn.XLOOKUP(MAX($O56,$P56*$E56),Gen_kW_List,Gen_kW_List,"> 3000",1),"—")) -> — | S56: =IF(ISNUMBER($R56),ROUND($R56/$E56,0),"—") -> — | U56: 0.15 | V56: BANK-D
E57: 0.8 | F57: 1.2 | G57: 0.9 | H57: {=IF($B57="",0,IFERROR(SUMPRODUCT(($D$10:$D$21="Y")*INDEX('Load Calc'!$F$178:$K$189,0,MATCH($B57,'Load Calc'!$F$177:$K$177,0))),0)+IF($T57="Y",SUMPRODUCT(($D$10:$D$21="Y")*'Load Calc'!$L$178:$L$189),0))} -> 0 | I57: =IF($B57="",0,SUMIFS(GEN_Loads[kVA],GEN_Loads[Unit],$B57)) -> 0 | J57: =ROUND($H57+$I57,1) -> 0 | K57: =IF($B57="",0,ROUND($H57*$G57+SUMIFS(GEN_Loads[kW total],GEN_Loads[Unit],$B57),1)) -> 0 | L57: =IF($B57="",0,IFERROR(_xlfn.MAXIFS(GEN_Loads[Start kVA],GEN_Loads[Unit],$B57),0)) -> 0 | M57: {=ROUND(MAX($K57*$F57,SUMPRODUCT(($H$62:$H$69=$B57)*($C$62:$C$69="ATS")*IF(ISNUMBER($K$62:$K$69),$K$62:$K$69,0)*IF(LEFT(IF($V$62:$V$69<>"",$V$62:$V$69,Gen_SizeBasis),3)="Equ",1,$F57))*$G57),1)} -> 0 | N57: {=ROUND(MAX($J57*$F57,$L57,SUMPRODUCT(($H$62:$H$69=$B57)*($C$62:$C$69="ATS")*IF(ISNUMBER($K$62:$K$69),$K$62:$K$69,0)*IF(LEFT(IF($V$62:$V$69<>"",$V$62:$V$69,Gen_SizeBasis),3)="Equ",1,$F57))),1)} -> 0 | O57: =IF($D57="",$M57,SUMIFS($M$53:$M$58,$D$53:$D$58,$D57)) -> 0 | P57: =IF($D57="",$N57,SUMIFS($N$53:$N$58,$D$53:$D$58,$D57)) -> 0 | Q57: =IF($B57="","",IF($D57="","Y",IF(COUNTIFS($D$53:$D57,$D57)=1,"Y",""))) | R57: =IF(OR($B57="",$O57+$P57=0),"—",IFERROR(_xlfn.XLOOKUP(MAX($O57,$P57*$E57),Gen_kW_List,Gen_kW_List,"> 3000",1),"—")) -> — | S57: =IF(ISNUMBER($R57),ROUND($R57/$E57,0),"—") -> — | U57: 0.15 | V57: BANK-E
E58: 0.8 | F58: 1.2 | G58: 0.9 | H58: {=IF($B58="",0,IFERROR(SUMPRODUCT(($D$10:$D$21="Y")*INDEX('Load Calc'!$F$178:$K$189,0,MATCH($B58,'Load Calc'!$F$177:$K$177,0))),0)+IF($T58="Y",SUMPRODUCT(($D$10:$D$21="Y")*'Load Calc'!$L$178:$L$189),0))} -> 0 | I58: =IF($B58="",0,SUMIFS(GEN_Loads[kVA],GEN_Loads[Unit],$B58)) -> 0 | J58: =ROUND($H58+$I58,1) -> 0 | K58: =IF($B58="",0,ROUND($H58*$G58+SUMIFS(GEN_Loads[kW total],GEN_Loads[Unit],$B58),1)) -> 0 | L58: =IF($B58="",0,IFERROR(_xlfn.MAXIFS(GEN_Loads[Start kVA],GEN_Loads[Unit],$B58),0)) -> 0 | M58: {=ROUND(MAX($K58*$F58,SUMPRODUCT(($H$62:$H$69=$B58)*($C$62:$C$69="ATS")*IF(ISNUMBER($K$62:$K$69),$K$62:$K$69,0)*IF(LEFT(IF($V$62:$V$69<>"",$V$62:$V$69,Gen_SizeBasis),3)="Equ",1,$F58))*$G58),1)} -> 0 | N58: {=ROUND(MAX($J58*$F58,$L58,SUMPRODUCT(($H$62:$H$69=$B58)*($C$62:$C$69="ATS")*IF(ISNUMBER($K$62:$K$69),$K$62:$K$69,0)*IF(LEFT(IF($V$62:$V$69<>"",$V$62:$V$69,Gen_SizeBasis),3)="Equ",1,$F58))),1)} -> 0 | O58: =IF($D58="",$M58,SUMIFS($M$53:$M$58,$D$53:$D$58,$D58)) -> 0 | P58: =IF($D58="",$N58,SUMIFS($N$53:$N$58,$D$53:$D$58,$D58)) -> 0 | Q58: =IF($B58="","",IF($D58="","Y",IF(COUNTIFS($D$53:$D58,$D58)=1,"Y",""))) | R58: =IF(OR($B58="",$O58+$P58=0),"—",IFERROR(_xlfn.XLOOKUP(MAX($O58,$P58*$E58),Gen_kW_List,Gen_kW_List,"> 3000",1),"—")) -> — | S58: =IF(ISNUMBER($R58),ROUND($R58/$E58,0),"—") -> — | U58: 0.15 | V58: BANK-F
A60: TRANSFER SWITCHES — ATS / MTS (created by ribbon ▸ New Transfer Switch)
B61: Tag | C61: Type | D61: Poles | E61: SE Rated | F61: Scope | G61: Normal Source | H61: Emergency Source | I61: Load Side | J61: Voltage | K61: Load kVA (basis) | L61: Gen Running kVA | M61: Design A | N61: Calc Rating (A) | O61: Rating Override | P61: RATING (A) | Q61: Typ. WCR (A) | R61: WCR Override | S61: WCR Used (A) | T61: Fault at ATS (A) | U61: WCR Check | V61: Basis Override
J62: =IF($B62="","",IFERROR(_xlfn.XLOOKUP($B62,Dashboard!$A$101:$A$350,Dashboard!$C$101:$C$350,""),"")) | K62: =IF($B62="","",_xlfn.LET(_xlpm.bs,IF($V62<>"",$V62,Gen_SizeBasis),_xlpm.dem,IFERROR(N(_xlfn.XLOOKUP($I62,Equip_List,Equip_Demand,0)),0),_xlpm.amp,IFERROR(N(_xlfn.XLOOKUP($I62,Equip_List,Dashboard!$P$101:$P$350,0)),0),_xlpm.v,IFERROR(_xlfn.XLOOKUP($J62,Xfmr_VoltStr,Xfmr_BaseV),""),_xlpm.p,IFERROR(_xlfn.XLOOKUP($J62,Xfmr_VoltStr,Xfmr_Ph),3),_xlpm.rk,IF(OR(_xlpm.amp=0,N(_xlpm.v)=0),0,_xlpm.amp*_xlpm.v*IF(_xlpm.p=3,SQRT(3),1)/1000),IF(AND(LEFT(_xlpm.bs,3)="Equ",_xlpm.rk>0),ROUND(_xlpm.rk,1),_xlpm.dem))) | L62: =IF($B62="","",IFERROR(N(_xlfn.XLOOKUP($H62,$B$53:$B$58,$J$53:$J$58,0)),0)) | M62: =IF($B62="","",_xlfn.LET(_xlpm.bs,IF($V62<>"",$V62,Gen_SizeBasis),_xlpm.v,IFERROR(_xlfn.XLOOKUP($J62,Xfmr_VoltStr,Xfmr_BaseV),""),_xlpm.p,IFERROR(_xlfn.XLOOKUP($J62,Xfmr_VoltStr,Xfmr_Ph),3),_xlpm.amp,IFERROR(N(_xlfn.XLOOKUP($I62,Equip_List,Dashboard!$P$101:$P$350,0)),0),IF(N(_xlpm.v)=0,"",_xlfn.LET(_xlpm.gA,N($L62)*1000/(_xlpm.v*IF(_xlpm.p=3,SQRT(3),1)),IF(AND(LEFT(_xlpm.bs,3)="Equ",_xlpm.amp>0),ROUND(MAX(_xlpm.amp,1.25*_xlpm.gA),1),ROUND(MAX(N($K62),N($L62))*1.25*1000/(_xlpm.v*IF(_xlpm.p=3,SQRT(3),1)),1)))))) | N62: =IF(NOT(ISNUMBER($M62)),"",IFERROR(_xlfn.XLOOKUP($M62,ATS_List,ATS_List,"> 4000",1),"—")) | P62: =IF($B62="","",IF(N($O62)>0,$O62,$N62)) | Q62: =IF(NOT(ISNUMBER($P62)),"",IFERROR(_xlfn.XLOOKUP($P62,ATS_List,ATS_WCR,"",1),"")) | S62: =IF($B62="","",IF(N($R62)>0,$R62,$Q62)) | T62: =IF($B62="","",IFERROR(_xlfn.XLOOKUP($B62,'Short Circuit'!$A$6:$A$255,'Short Circuit'!$Q$6:$Q$255,""),"")) | U62: =IF(OR($B62="",NOT(ISNUMBER($S62)),NOT(ISNUMBER($T62))),"",IF($S62>=$T62,"✔ WCR OK","✖ WCR below fault — raise WCR / series device"))
J63: =IF($B63="","",IFERROR(_xlfn.XLOOKUP($B63,Dashboard!$A$101:$A$350,Dashboard!$C$101:$C$350,""),"")) | K63: =IF($B63="","",_xlfn.LET(_xlpm.bs,IF($V63<>"",$V63,Gen_SizeBasis),_xlpm.dem,IFERROR(N(_xlfn.XLOOKUP($I63,Equip_List,Equip_Demand,0)),0),_xlpm.amp,IFERROR(N(_xlfn.XLOOKUP($I63,Equip_List,Dashboard!$P$101:$P$350,0)),0),_xlpm.v,IFERROR(_xlfn.XLOOKUP($J63,Xfmr_VoltStr,Xfmr_BaseV),""),_xlpm.p,IFERROR(_xlfn.XLOOKUP($J63,Xfmr_VoltStr,Xfmr_Ph),3),_xlpm.rk,IF(OR(_xlpm.amp=0,N(_xlpm.v)=0),0,_xlpm.amp*_xlpm.v*IF(_xlpm.p=3,SQRT(3),1)/1000),IF(AND(LEFT(_xlpm.bs,3)="Equ",_xlpm.rk>0),ROUND(_xlpm.rk,1),_xlpm.dem))) | L63: =IF($B63="","",IFERROR(N(_xlfn.XLOOKUP($H63,$B$53:$B$58,$J$53:$J$58,0)),0)) | M63: =IF($B63="","",_xlfn.LET(_xlpm.bs,IF($V63<>"",$V63,Gen_SizeBasis),_xlpm.v,IFERROR(_xlfn.XLOOKUP($J63,Xfmr_VoltStr,Xfmr_BaseV),""),_xlpm.p,IFERROR(_xlfn.XLOOKUP($J63,Xfmr_VoltStr,Xfmr_Ph),3),_xlpm.amp,IFERROR(N(_xlfn.XLOOKUP($I63,Equip_List,Dashboard!$P$101:$P$350,0)),0),IF(N(_xlpm.v)=0,"",_xlfn.LET(_xlpm.gA,N($L63)*1000/(_xlpm.v*IF(_xlpm.p=3,SQRT(3),1)),IF(AND(LEFT(_xlpm.bs,3)="Equ",_xlpm.amp>0),ROUND(MAX(_xlpm.amp,1.25*_xlpm.gA),1),ROUND(MAX(N($K63),N($L63))*1.25*1000/(_xlpm.v*IF(_xlpm.p=3,SQRT(3),1)),1)))))) | N63: =IF(NOT(ISNUMBER($M63)),"",IFERROR(_xlfn.XLOOKUP($M63,ATS_List,ATS_List,"> 4000",1),"—")) | P63: =IF($B63="","",IF(N($O63)>0,$O63,$N63)) | Q63: =IF(NOT(ISNUMBER($P63)),"",IFERROR(_xlfn.XLOOKUP($P63,ATS_List,ATS_WCR,"",1),"")) | S63: =IF($B63="","",IF(N($R63)>0,$R63,$Q63)) | T63: =IF($B63="","",IFERROR(_xlfn.XLOOKUP($B63,'Short Circuit'!$A$6:$A$255,'Short Circuit'!$Q$6:$Q$255,""),"")) | U63: =IF(OR($B63="",NOT(ISNUMBER($S63)),NOT(ISNUMBER($T63))),"",IF($S63>=$T63,"✔ WCR OK","✖ WCR below fault — raise WCR / series device"))
J64: =IF($B64="","",IFERROR(_xlfn.XLOOKUP($B64,Dashboard!$A$101:$A$350,Dashboard!$C$101:$C$350,""),"")) | K64: =IF($B64="","",_xlfn.LET(_xlpm.bs,IF($V64<>"",$V64,Gen_SizeBasis),_xlpm.dem,IFERROR(N(_xlfn.XLOOKUP($I64,Equip_List,Equip_Demand,0)),0),_xlpm.amp,IFERROR(N(_xlfn.XLOOKUP($I64,Equip_List,Dashboard!$P$101:$P$350,0)),0),_xlpm.v,IFERROR(_xlfn.XLOOKUP($J64,Xfmr_VoltStr,Xfmr_BaseV),""),_xlpm.p,IFERROR(_xlfn.XLOOKUP($J64,Xfmr_VoltStr,Xfmr_Ph),3),_xlpm.rk,IF(OR(_xlpm.amp=0,N(_xlpm.v)=0),0,_xlpm.amp*_xlpm.v*IF(_xlpm.p=3,SQRT(3),1)/1000),IF(AND(LEFT(_xlpm.bs,3)="Equ",_xlpm.rk>0),ROUND(_xlpm.rk,1),_xlpm.dem))) | L64: =IF($B64="","",IFERROR(N(_xlfn.XLOOKUP($H64,$B$53:$B$58,$J$53:$J$58,0)),0)) | M64: =IF($B64="","",_xlfn.LET(_xlpm.bs,IF($V64<>"",$V64,Gen_SizeBasis),_xlpm.v,IFERROR(_xlfn.XLOOKUP($J64,Xfmr_VoltStr,Xfmr_BaseV),""),_xlpm.p,IFERROR(_xlfn.XLOOKUP($J64,Xfmr_VoltStr,Xfmr_Ph),3),_xlpm.amp,IFERROR(N(_xlfn.XLOOKUP($I64,Equip_List,Dashboard!$P$101:$P$350,0)),0),IF(N(_xlpm.v)=0,"",_xlfn.LET(_xlpm.gA,N($L64)*1000/(_xlpm.v*IF(_xlpm.p=3,SQRT(3),1)),IF(AND(LEFT(_xlpm.bs,3)="Equ",_xlpm.amp>0),ROUND(MAX(_xlpm.amp,1.25*_xlpm.gA),1),ROUND(MAX(N($K64),N($L64))*1.25*1000/(_xlpm.v*IF(_xlpm.p=3,SQRT(3),1)),1)))))) | N64: =IF(NOT(ISNUMBER($M64)),"",IFERROR(_xlfn.XLOOKUP($M64,ATS_List,ATS_List,"> 4000",1),"—")) | P64: =IF($B64="","",IF(N($O64)>0,$O64,$N64)) | Q64: =IF(NOT(ISNUMBER($P64)),"",IFERROR(_xlfn.XLOOKUP($P64,ATS_List,ATS_WCR,"",1),"")) | S64: =IF($B64="","",IF(N($R64)>0,$R64,$Q64)) | T64: =IF($B64="","",IFERROR(_xlfn.XLOOKUP($B64,'Short Circuit'!$A$6:$A$255,'Short Circuit'!$Q$6:$Q$255,""),"")) | U64: =IF(OR($B64="",NOT(ISNUMBER($S64)),NOT(ISNUMBER($T64))),"",IF($S64>=$T64,"✔ WCR OK","✖ WCR below fault — raise WCR / series device"))
J65: =IF($B65="","",IFERROR(_xlfn.XLOOKUP($B65,Dashboard!$A$101:$A$350,Dashboard!$C$101:$C$350,""),"")) | K65: =IF($B65="","",_xlfn.LET(_xlpm.bs,IF($V65<>"",$V65,Gen_SizeBasis),_xlpm.dem,IFERROR(N(_xlfn.XLOOKUP($I65,Equip_List,Equip_Demand,0)),0),_xlpm.amp,IFERROR(N(_xlfn.XLOOKUP($I65,Equip_List,Dashboard!$P$101:$P$350,0)),0),_xlpm.v,IFERROR(_xlfn.XLOOKUP($J65,Xfmr_VoltStr,Xfmr_BaseV),""),_xlpm.p,IFERROR(_xlfn.XLOOKUP($J65,Xfmr_VoltStr,Xfmr_Ph),3),_xlpm.rk,IF(OR(_xlpm.amp=0,N(_xlpm.v)=0),0,_xlpm.amp*_xlpm.v*IF(_xlpm.p=3,SQRT(3),1)/1000),IF(AND(LEFT(_xlpm.bs,3)="Equ",_xlpm.rk>0),ROUND(_xlpm.rk,1),_xlpm.dem))) | L65: =IF($B65="","",IFERROR(N(_xlfn.XLOOKUP($H65,$B$53:$B$58,$J$53:$J$58,0)),0)) | M65: =IF($B65="","",_xlfn.LET(_xlpm.bs,IF($V65<>"",$V65,Gen_SizeBasis),_xlpm.v,IFERROR(_xlfn.XLOOKUP($J65,Xfmr_VoltStr,Xfmr_BaseV),""),_xlpm.p,IFERROR(_xlfn.XLOOKUP($J65,Xfmr_VoltStr,Xfmr_Ph),3),_xlpm.amp,IFERROR(N(_xlfn.XLOOKUP($I65,Equip_List,Dashboard!$P$101:$P$350,0)),0),IF(N(_xlpm.v)=0,"",_xlfn.LET(_xlpm.gA,N($L65)*1000/(_xlpm.v*IF(_xlpm.p=3,SQRT(3),1)),IF(AND(LEFT(_xlpm.bs,3)="Equ",_xlpm.amp>0),ROUND(MAX(_xlpm.amp,1.25*_xlpm.gA),1),ROUND(MAX(N($K65),N($L65))*1.25*1000/(_xlpm.v*IF(_xlpm.p=3,SQRT(3),1)),1)))))) | N65: =IF(NOT(ISNUMBER($M65)),"",IFERROR(_xlfn.XLOOKUP($M65,ATS_List,ATS_List,"> 4000",1),"—")) | P65: =IF($B65="","",IF(N($O65)>0,$O65,$N65)) | Q65: =IF(NOT(ISNUMBER($P65)),"",IFERROR(_xlfn.XLOOKUP($P65,ATS_List,ATS_WCR,"",1),"")) | S65: =IF($B65="","",IF(N($R65)>0,$R65,$Q65)) | T65: =IF($B65="","",IFERROR(_xlfn.XLOOKUP($B65,'Short Circuit'!$A$6:$A$255,'Short Circuit'!$Q$6:$Q$255,""),"")) | U65: =IF(OR($B65="",NOT(ISNUMBER($S65)),NOT(ISNUMBER($T65))),"",IF($S65>=$T65,"✔ WCR OK","✖ WCR below fault — raise WCR / series device"))
J66: =IF($B66="","",IFERROR(_xlfn.XLOOKUP($B66,Dashboard!$A$101:$A$350,Dashboard!$C$101:$C$350,""),"")) | K66: =IF($B66="","",_xlfn.LET(_xlpm.bs,IF($V66<>"",$V66,Gen_SizeBasis),_xlpm.dem,IFERROR(N(_xlfn.XLOOKUP($I66,Equip_List,Equip_Demand,0)),0),_xlpm.amp,IFERROR(N(_xlfn.XLOOKUP($I66,Equip_List,Dashboard!$P$101:$P$350,0)),0),_xlpm.v,IFERROR(_xlfn.XLOOKUP($J66,Xfmr_VoltStr,Xfmr_BaseV),""),_xlpm.p,IFERROR(_xlfn.XLOOKUP($J66,Xfmr_VoltStr,Xfmr_Ph),3),_xlpm.rk,IF(OR(_xlpm.amp=0,N(_xlpm.v)=0),0,_xlpm.amp*_xlpm.v*IF(_xlpm.p=3,SQRT(3),1)/1000),IF(AND(LEFT(_xlpm.bs,3)="Equ",_xlpm.rk>0),ROUND(_xlpm.rk,1),_xlpm.dem))) | L66: =IF($B66="","",IFERROR(N(_xlfn.XLOOKUP($H66,$B$53:$B$58,$J$53:$J$58,0)),0)) | M66: =IF($B66="","",_xlfn.LET(_xlpm.bs,IF($V66<>"",$V66,Gen_SizeBasis),_xlpm.v,IFERROR(_xlfn.XLOOKUP($J66,Xfmr_VoltStr,Xfmr_BaseV),""),_xlpm.p,IFERROR(_xlfn.XLOOKUP($J66,Xfmr_VoltStr,Xfmr_Ph),3),_xlpm.amp,IFERROR(N(_xlfn.XLOOKUP($I66,Equip_List,Dashboard!$P$101:$P$350,0)),0),IF(N(_xlpm.v)=0,"",_xlfn.LET(_xlpm.gA,N($L66)*1000/(_xlpm.v*IF(_xlpm.p=3,SQRT(3),1)),IF(AND(LEFT(_xlpm.bs,3)="Equ",_xlpm.amp>0),ROUND(MAX(_xlpm.amp,1.25*_xlpm.gA),1),ROUND(MAX(N($K66),N($L66))*1.25*1000/(_xlpm.v*IF(_xlpm.p=3,SQRT(3),1)),1)))))) | N66: =IF(NOT(ISNUMBER($M66)),"",IFERROR(_xlfn.XLOOKUP($M66,ATS_List,ATS_List,"> 4000",1),"—")) | P66: =IF($B66="","",IF(N($O66)>0,$O66,$N66)) | Q66: =IF(NOT(ISNUMBER($P66)),"",IFERROR(_xlfn.XLOOKUP($P66,ATS_List,ATS_WCR,"",1),"")) | S66: =IF($B66="","",IF(N($R66)>0,$R66,$Q66)) | T66: =IF($B66="","",IFERROR(_xlfn.XLOOKUP($B66,'Short Circuit'!$A$6:$A$255,'Short Circuit'!$Q$6:$Q$255,""),"")) | U66: =IF(OR($B66="",NOT(ISNUMBER($S66)),NOT(ISNUMBER($T66))),"",IF($S66>=$T66,"✔ WCR OK","✖ WCR below fault — raise WCR / series device"))
J67: =IF($B67="","",IFERROR(_xlfn.XLOOKUP($B67,Dashboard!$A$101:$A$350,Dashboard!$C$101:$C$350,""),"")) | K67: =IF($B67="","",_xlfn.LET(_xlpm.bs,IF($V67<>"",$V67,Gen_SizeBasis),_xlpm.dem,IFERROR(N(_xlfn.XLOOKUP($I67,Equip_List,Equip_Demand,0)),0),_xlpm.amp,IFERROR(N(_xlfn.XLOOKUP($I67,Equip_List,Dashboard!$P$101:$P$350,0)),0),_xlpm.v,IFERROR(_xlfn.XLOOKUP($J67,Xfmr_VoltStr,Xfmr_BaseV),""),_xlpm.p,IFERROR(_xlfn.XLOOKUP($J67,Xfmr_VoltStr,Xfmr_Ph),3),_xlpm.rk,IF(OR(_xlpm.amp=0,N(_xlpm.v)=0),0,_xlpm.amp*_xlpm.v*IF(_xlpm.p=3,SQRT(3),1)/1000),IF(AND(LEFT(_xlpm.bs,3)="Equ",_xlpm.rk>0),ROUND(_xlpm.rk,1),_xlpm.dem))) | L67: =IF($B67="","",IFERROR(N(_xlfn.XLOOKUP($H67,$B$53:$B$58,$J$53:$J$58,0)),0)) | M67: =IF($B67="","",_xlfn.LET(_xlpm.bs,IF($V67<>"",$V67,Gen_SizeBasis),_xlpm.v,IFERROR(_xlfn.XLOOKUP($J67,Xfmr_VoltStr,Xfmr_BaseV),""),_xlpm.p,IFERROR(_xlfn.XLOOKUP($J67,Xfmr_VoltStr,Xfmr_Ph),3),_xlpm.amp,IFERROR(N(_xlfn.XLOOKUP($I67,Equip_List,Dashboard!$P$101:$P$350,0)),0),IF(N(_xlpm.v)=0,"",_xlfn.LET(_xlpm.gA,N($L67)*1000/(_xlpm.v*IF(_xlpm.p=3,SQRT(3),1)),IF(AND(LEFT(_xlpm.bs,3)="Equ",_xlpm.amp>0),ROUND(MAX(_xlpm.amp,1.25*_xlpm.gA),1),ROUND(MAX(N($K67),N($L67))*1.25*1000/(_xlpm.v*IF(_xlpm.p=3,SQRT(3),1)),1)))))) | N67: =IF(NOT(ISNUMBER($M67)),"",IFERROR(_xlfn.XLOOKUP($M67,ATS_List,ATS_List,"> 4000",1),"—")) | P67: =IF($B67="","",IF(N($O67)>0,$O67,$N67)) | Q67: =IF(NOT(ISNUMBER($P67)),"",IFERROR(_xlfn.XLOOKUP($P67,ATS_List,ATS_WCR,"",1),"")) | S67: =IF($B67="","",IF(N($R67)>0,$R67,$Q67)) | T67: =IF($B67="","",IFERROR(_xlfn.XLOOKUP($B67,'Short Circuit'!$A$6:$A$255,'Short Circuit'!$Q$6:$Q$255,""),"")) | U67: =IF(OR($B67="",NOT(ISNUMBER($S67)),NOT(ISNUMBER($T67))),"",IF($S67>=$T67,"✔ WCR OK","✖ WCR below fault — raise WCR / series device"))
J68: =IF($B68="","",IFERROR(_xlfn.XLOOKUP($B68,Dashboard!$A$101:$A$350,Dashboard!$C$101:$C$350,""),"")) | K68: =IF($B68="","",_xlfn.LET(_xlpm.bs,IF($V68<>"",$V68,Gen_SizeBasis),_xlpm.dem,IFERROR(N(_xlfn.XLOOKUP($I68,Equip_List,Equip_Demand,0)),0),_xlpm.amp,IFERROR(N(_xlfn.XLOOKUP($I68,Equip_List,Dashboard!$P$101:$P$350,0)),0),_xlpm.v,IFERROR(_xlfn.XLOOKUP($J68,Xfmr_VoltStr,Xfmr_BaseV),""),_xlpm.p,IFERROR(_xlfn.XLOOKUP($J68,Xfmr_VoltStr,Xfmr_Ph),3),_xlpm.rk,IF(OR(_xlpm.amp=0,N(_xlpm.v)=0),0,_xlpm.amp*_xlpm.v*IF(_xlpm.p=3,SQRT(3),1)/1000),IF(AND(LEFT(_xlpm.bs,3)="Equ",_xlpm.rk>0),ROUND(_xlpm.rk,1),_xlpm.dem))) | L68: =IF($B68="","",IFERROR(N(_xlfn.XLOOKUP($H68,$B$53:$B$58,$J$53:$J$58,0)),0)) | M68: =IF($B68="","",_xlfn.LET(_xlpm.bs,IF($V68<>"",$V68,Gen_SizeBasis),_xlpm.v,IFERROR(_xlfn.XLOOKUP($J68,Xfmr_VoltStr,Xfmr_BaseV),""),_xlpm.p,IFERROR(_xlfn.XLOOKUP($J68,Xfmr_VoltStr,Xfmr_Ph),3),_xlpm.amp,IFERROR(N(_xlfn.XLOOKUP($I68,Equip_List,Dashboard!$P$101:$P$350,0)),0),IF(N(_xlpm.v)=0,"",_xlfn.LET(_xlpm.gA,N($L68)*1000/(_xlpm.v*IF(_xlpm.p=3,SQRT(3),1)),IF(AND(LEFT(_xlpm.bs,3)="Equ",_xlpm.amp>0),ROUND(MAX(_xlpm.amp,1.25*_xlpm.gA),1),ROUND(MAX(N($K68),N($L68))*1.25*1000/(_xlpm.v*IF(_xlpm.p=3,SQRT(3),1)),1)))))) | N68: =IF(NOT(ISNUMBER($M68)),"",IFERROR(_xlfn.XLOOKUP($M68,ATS_List,ATS_List,"> 4000",1),"—")) | P68: =IF($B68="","",IF(N($O68)>0,$O68,$N68)) | Q68: =IF(NOT(ISNUMBER($P68)),"",IFERROR(_xlfn.XLOOKUP($P68,ATS_List,ATS_WCR,"",1),"")) | S68: =IF($B68="","",IF(N($R68)>0,$R68,$Q68)) | T68: =IF($B68="","",IFERROR(_xlfn.XLOOKUP($B68,'Short Circuit'!$A$6:$A$255,'Short Circuit'!$Q$6:$Q$255,""),"")) | U68: =IF(OR($B68="",NOT(ISNUMBER($S68)),NOT(ISNUMBER($T68))),"",IF($S68>=$T68,"✔ WCR OK","✖ WCR below fault — raise WCR / series device"))
J69: =IF($B69="","",IFERROR(_xlfn.XLOOKUP($B69,Dashboard!$A$101:$A$350,Dashboard!$C$101:$C$350,""),"")) | K69: =IF($B69="","",_xlfn.LET(_xlpm.bs,IF($V69<>"",$V69,Gen_SizeBasis),_xlpm.dem,IFERROR(N(_xlfn.XLOOKUP($I69,Equip_List,Equip_Demand,0)),0),_xlpm.amp,IFERROR(N(_xlfn.XLOOKUP($I69,Equip_List,Dashboard!$P$101:$P$350,0)),0),_xlpm.v,IFERROR(_xlfn.XLOOKUP($J69,Xfmr_VoltStr,Xfmr_BaseV),""),_xlpm.p,IFERROR(_xlfn.XLOOKUP($J69,Xfmr_VoltStr,Xfmr_Ph),3),_xlpm.rk,IF(OR(_xlpm.amp=0,N(_xlpm.v)=0),0,_xlpm.amp*_xlpm.v*IF(_xlpm.p=3,SQRT(3),1)/1000),IF(AND(LEFT(_xlpm.bs,3)="Equ",_xlpm.rk>0),ROUND(_xlpm.rk,1),_xlpm.dem))) | L69: =IF($B69="","",IFERROR(N(_xlfn.XLOOKUP($H69,$B$53:$B$58,$J$53:$J$58,0)),0)) | M69: =IF($B69="","",_xlfn.LET(_xlpm.bs,IF($V69<>"",$V69,Gen_SizeBasis),_xlpm.v,IFERROR(_xlfn.XLOOKUP($J69,Xfmr_VoltStr,Xfmr_BaseV),""),_xlpm.p,IFERROR(_xlfn.XLOOKUP($J69,Xfmr_VoltStr,Xfmr_Ph),3),_xlpm.amp,IFERROR(N(_xlfn.XLOOKUP($I69,Equip_List,Dashboard!$P$101:$P$350,0)),0),IF(N(_xlpm.v)=0,"",_xlfn.LET(_xlpm.gA,N($L69)*1000/(_xlpm.v*IF(_xlpm.p=3,SQRT(3),1)),IF(AND(LEFT(_xlpm.bs,3)="Equ",_xlpm.amp>0),ROUND(MAX(_xlpm.amp,1.25*_xlpm.gA),1),ROUND(MAX(N($K69),N($L69))*1.25*1000/(_xlpm.v*IF(_xlpm.p=3,SQRT(3),1)),1)))))) | N69: =IF(NOT(ISNUMBER($M69)),"",IFERROR(_xlfn.XLOOKUP($M69,ATS_List,ATS_List,"> 4000",1),"—")) | P69: =IF($B69="","",IF(N($O69)>0,$O69,$N69)) | Q69: =IF(NOT(ISNUMBER($P69)),"",IFERROR(_xlfn.XLOOKUP($P69,ATS_List,ATS_WCR,"",1),"")) | S69: =IF($B69="","",IF(N($R69)>0,$R69,$Q69)) | T69: =IF($B69="","",IFERROR(_xlfn.XLOOKUP($B69,'Short Circuit'!$A$6:$A$255,'Short Circuit'!$Q$6:$Q$255,""),"")) | U69: =IF(OR($B69="",NOT(ISNUMBER($S69)),NOT(ISNUMBER($T69))),"",IF($S69>=$T69,"✔ WCR OK","✖ WCR below fault — raise WCR / series device"))
A71: Rating basis (L6, per-switch override in V): CALCULATED DEMAND = next UL 1008 frame ≥ 1.25 × the larger of the load-side NEC 220 demand and the generator unit's running kVA; the generator carries that demand × Design Margin (NEC 702.4(B)(2)(a) full load transferred). EQUIPMENT RATING = the switch is rated at least the load-side board's main/bus rating (registry Rating A) and the generator carries the full rated kVA (V × A × √3), no margin. WCR values are typical — confirm with the manufacturer. Fault at ATS = worst of the normal (utility) path and the generator's own contribution (kVA / X"d).

Sheet UPS
A1: UPS SIZING — CRITICAL / CONTINUOUS LOADS
B2: Project: | C2: =IF(Dashboard!B7="","—",Dashboard!B7) -> — | G2: Service Voltage: | H2: =IF(Dashboard!$C$38="","",Dashboard!$C$38)
A4: SETTINGS
B6: UPS Output PF | C6: 0.9 | E6: Design Margin (×) | F6: 1.25 | G6: Redundancy | H6: N | J6: Runtime Target (min) | K6: 10 | M6: Typ. UPS SCCR (A) | N6: 65000
A8: LOADS FROM LOAD CALC (UPS = Y)
B9: Section | C9: Connected kVA | D9: Include?
B10: Site / Exterior | C10: {=INDEX(LC_UPSByCategory,ROW()-ROW($B$9))} -> 0 | D10: Y
B11: House / Misc | C11: {=INDEX(LC_UPSByCategory,ROW()-ROW($B$9))} -> 0 | D11: Y
B12: Department / Owner | C12: {=INDEX(LC_UPSByCategory,ROW()-ROW($B$9))} -> 0 | D12: Y
B13: Refrigeration | C13: {=INDEX(LC_UPSByCategory,ROW()-ROW($B$9))} -> 0 | D13: Y
B14: Mechanical | C14: {=INDEX(LC_UPSByCategory,ROW()-ROW($B$9))} -> 0 | D14: Y
B15: Plumbing | C15: {=INDEX(LC_UPSByCategory,ROW()-ROW($B$9))} -> 0 | D15: Y
B16: Kitchen / Food Service | C16: {=INDEX(LC_UPSByCategory,ROW()-ROW($B$9))} -> 0 | D16: Y
B17: Elevators / Conveying | C17: {=INDEX(LC_UPSByCategory,ROW()-ROW($B$9))} -> 0 | D17: Y
B18: EV Charging | C18: {=INDEX(LC_UPSByCategory,ROW()-ROW($B$9))} -> 0 | D18: Y
B19: Data / IT | C19: {=INDEX(LC_UPSByCategory,ROW()-ROW($B$9))} -> 0 | D19: Y
B20: Fire / Life Safety | C20: {=INDEX(LC_UPSByCategory,ROW()-ROW($B$9))} -> 0 | D20: Y
B21: Process / Industrial | C21: {=INDEX(LC_UPSByCategory,ROW()-ROW($B$9))} -> 0 | D21: Y
B23: TOTAL INCLUDED (kVA) | C23: =SUMIF($D$10:$D$21,"Y",$C$10:$C$21) -> 0
A25: ADDITIONAL / MANUAL LOADS
B26: Description | C26: Qty | D26: kVA each | E26: kVA total | F26: Notes | G26: Unit
E27: =IF(OR(UPS_Loads[[#This Row],[Qty]]="",UPS_Loads[[#This Row],[kVA each]]=""),"",UPS_Loads[[#This Row],[Qty]]*UPS_Loads[[#This Row],[kVA each]])
E28: =IF(OR(UPS_Loads[[#This Row],[Qty]]="",UPS_Loads[[#This Row],[kVA each]]=""),"",UPS_Loads[[#This Row],[Qty]]*UPS_Loads[[#This Row],[kVA each]])
E29: =IF(OR(UPS_Loads[[#This Row],[Qty]]="",UPS_Loads[[#This Row],[kVA each]]=""),"",UPS_Loads[[#This Row],[Qty]]*UPS_Loads[[#This Row],[kVA each]])
E30: =IF(OR(UPS_Loads[[#This Row],[Qty]]="",UPS_Loads[[#This Row],[kVA each]]=""),"",UPS_Loads[[#This Row],[Qty]]*UPS_Loads[[#This Row],[kVA each]])
E31: =IF(OR(UPS_Loads[[#This Row],[Qty]]="",UPS_Loads[[#This Row],[kVA each]]=""),"",UPS_Loads[[#This Row],[Qty]]*UPS_Loads[[#This Row],[kVA each]])
E32: =IF(OR(UPS_Loads[[#This Row],[Qty]]="",UPS_Loads[[#This Row],[kVA each]]=""),"",UPS_Loads[[#This Row],[Qty]]*UPS_Loads[[#This Row],[kVA each]])
E33: =IF(OR(UPS_Loads[[#This Row],[Qty]]="",UPS_Loads[[#This Row],[kVA each]]=""),"",UPS_Loads[[#This Row],[Qty]]*UPS_Loads[[#This Row],[kVA each]])
E34: =IF(OR(UPS_Loads[[#This Row],[Qty]]="",UPS_Loads[[#This Row],[kVA each]]=""),"",UPS_Loads[[#This Row],[Qty]]*UPS_Loads[[#This Row],[kVA each]])
A36: SIZING SUMMARY
B38: Total Critical Load (kVA) | C38: =ROUND(SUM($I$48:$I$53),1) -> 0
B39: Critical Load kW @ Output PF | C39: =ROUND(SUM($J$48:$J$53),1) -> 0
B40: Required Module kVA = Σ per-unit (Load × Margin) | C40: =ROUND(SUM($K$48:$K$53),1) -> 0
B41: TOTAL SUGGESTED UPS (kVA) — all units | C41: =IF(SUM($L$48:$L$53)=0,"—",SUM($L$48:$L$53)) -> —
B42: Module Configuration | C42: =IF(COUNTIF($B$48:$B$53,"?*")<=1,IF($M$48="","1 module",$M$48),COUNTIF($B$48:$B$53,"?*")&" units — see UNITS table") -> 1 module
A44: Battery/runtime sizing per manufacturer data at the runtime target. Verify inrush & bypass ratings for downstream panels.
A46: UPS UNITS — multi-module / multi-system
B47: Unit Tag | C47: Description | D47: Output PF | E47: Margin (×) | F47: Redundancy | G47: Section kVA | H47: Manual kVA | I47: Critical kVA | J47: Critical kW | K47: Required Module kVA | L47: SUGGESTED kVA | M47: Configuration | N47: Absorb untagged?
B48: UPS-1 | C48: UPS System | D48: 0.9 | E48: 1.25 | F48: N | G48: {=IF($B48="",0,IFERROR(SUMPRODUCT(($D$10:$D$21="Y")*INDEX('Load Calc'!$F$197:$K$208,0,MATCH($B48,'Load Calc'!$F$196:$K$196,0))),0)+IF($N48="Y",SUMPRODUCT(($D$10:$D$21="Y")*'Load Calc'!$L$197:$L$208),0))} -> 0 | H48: =IF($B48="",0,SUMIFS(UPS_Loads[kVA total],UPS_Loads[Unit],$B48)) -> 0 | I48: =ROUND($G48+$H48,1) -> 0 | J48: =ROUND($I48*$D48,1) -> 0 | K48: =ROUND($I48*$E48,1) -> 0 | L48: =IF(OR($B48="",$K48=0),"—",IFERROR(_xlfn.XLOOKUP($K48,UPS_kVA_List,UPS_kVA_List,"> 1100",1),"—")) -> — | M48: {=IF($B48="","",_xlfn.SWITCH($F48,"N","1 module","N+1","2 modules (1 redundant)","2N","2 modules (dual path)","1 module"))} -> 1 module | N48: Y
D49: 0.9 | E49: 1.25 | F49: N | G49: {=IF($B49="",0,IFERROR(SUMPRODUCT(($D$10:$D$21="Y")*INDEX('Load Calc'!$F$197:$K$208,0,MATCH($B49,'Load Calc'!$F$196:$K$196,0))),0)+IF($N49="Y",SUMPRODUCT(($D$10:$D$21="Y")*'Load Calc'!$L$197:$L$208),0))} -> 0 | H49: =IF($B49="",0,SUMIFS(UPS_Loads[kVA total],UPS_Loads[Unit],$B49)) -> 0 | I49: =ROUND($G49+$H49,1) -> 0 | J49: =ROUND($I49*$D49,1) -> 0 | K49: =ROUND($I49*$E49,1) -> 0 | L49: =IF(OR($B49="",$K49=0),"—",IFERROR(_xlfn.XLOOKUP($K49,UPS_kVA_List,UPS_kVA_List,"> 1100",1),"—")) -> — | M49: {=IF($B49="","",_xlfn.SWITCH($F49,"N","1 module","N+1","2 modules (1 redundant)","2N","2 modules (dual path)","1 module"))}
D50: 0.9 | E50: 1.25 | F50: N | G50: {=IF($B50="",0,IFERROR(SUMPRODUCT(($D$10:$D$21="Y")*INDEX('Load Calc'!$F$197:$K$208,0,MATCH($B50,'Load Calc'!$F$196:$K$196,0))),0)+IF($N50="Y",SUMPRODUCT(($D$10:$D$21="Y")*'Load Calc'!$L$197:$L$208),0))} -> 0 | H50: =IF($B50="",0,SUMIFS(UPS_Loads[kVA total],UPS_Loads[Unit],$B50)) -> 0 | I50: =ROUND($G50+$H50,1) -> 0 | J50: =ROUND($I50*$D50,1) -> 0 | K50: =ROUND($I50*$E50,1) -> 0 | L50: =IF(OR($B50="",$K50=0),"—",IFERROR(_xlfn.XLOOKUP($K50,UPS_kVA_List,UPS_kVA_List,"> 1100",1),"—")) -> — | M50: {=IF($B50="","",_xlfn.SWITCH($F50,"N","1 module","N+1","2 modules (1 redundant)","2N","2 modules (dual path)","1 module"))}
D51: 0.9 | E51: 1.25 | F51: N | G51: {=IF($B51="",0,IFERROR(SUMPRODUCT(($D$10:$D$21="Y")*INDEX('Load Calc'!$F$197:$K$208,0,MATCH($B51,'Load Calc'!$F$196:$K$196,0))),0)+IF($N51="Y",SUMPRODUCT(($D$10:$D$21="Y")*'Load Calc'!$L$197:$L$208),0))} -> 0 | H51: =IF($B51="",0,SUMIFS(UPS_Loads[kVA total],UPS_Loads[Unit],$B51)) -> 0 | I51: =ROUND($G51+$H51,1) -> 0 | J51: =ROUND($I51*$D51,1) -> 0 | K51: =ROUND($I51*$E51,1) -> 0 | L51: =IF(OR($B51="",$K51=0),"—",IFERROR(_xlfn.XLOOKUP($K51,UPS_kVA_List,UPS_kVA_List,"> 1100",1),"—")) -> — | M51: {=IF($B51="","",_xlfn.SWITCH($F51,"N","1 module","N+1","2 modules (1 redundant)","2N","2 modules (dual path)","1 module"))}
D52: 0.9 | E52: 1.25 | F52: N | G52: {=IF($B52="",0,IFERROR(SUMPRODUCT(($D$10:$D$21="Y")*INDEX('Load Calc'!$F$197:$K$208,0,MATCH($B52,'Load Calc'!$F$196:$K$196,0))),0)+IF($N52="Y",SUMPRODUCT(($D$10:$D$21="Y")*'Load Calc'!$L$197:$L$208),0))} -> 0 | H52: =IF($B52="",0,SUMIFS(UPS_Loads[kVA total],UPS_Loads[Unit],$B52)) -> 0 | I52: =ROUND($G52+$H52,1) -> 0 | J52: =ROUND($I52*$D52,1) -> 0 | K52: =ROUND($I52*$E52,1) -> 0 | L52: =IF(OR($B52="",$K52=0),"—",IFERROR(_xlfn.XLOOKUP($K52,UPS_kVA_List,UPS_kVA_List,"> 1100",1),"—")) -> — | M52: {=IF($B52="","",_xlfn.SWITCH($F52,"N","1 module","N+1","2 modules (1 redundant)","2N","2 modules (dual path)","1 module"))}
D53: 0.9 | E53: 1.25 | F53: N | G53: {=IF($B53="",0,IFERROR(SUMPRODUCT(($D$10:$D$21="Y")*INDEX('Load Calc'!$F$197:$K$208,0,MATCH($B53,'Load Calc'!$F$196:$K$196,0))),0)+IF($N53="Y",SUMPRODUCT(($D$10:$D$21="Y")*'Load Calc'!$L$197:$L$208),0))} -> 0 | H53: =IF($B53="",0,SUMIFS(UPS_Loads[kVA total],UPS_Loads[Unit],$B53)) -> 0 | I53: =ROUND($G53+$H53,1) -> 0 | J53: =ROUND($I53*$D53,1) -> 0 | K53: =ROUND($I53*$E53,1) -> 0 | L53: =IF(OR($B53="",$K53=0),"—",IFERROR(_xlfn.XLOOKUP($K53,UPS_kVA_List,UPS_kVA_List,"> 1100",1),"—")) -> — | M53: {=IF($B53="","",_xlfn.SWITCH($F53,"N","1 module","N+1","2 modules (1 redundant)","2N","2 modules (dual path)","1 module"))}
A55: UPS SYSTEMS — DISTRIBUTION (created by ribbon ▸ New UPS System)
B56: Tag (UPS unit) | C56: Input From | D56: Output Board | E56: Bypass | F56: Volts | G56: Output Load (kVA) | H56: Unit Sized (kVA) | I56: Margin (×) | J56: Calc Rating (kVA) | K56: Rating Override (kVA) | L56: RATING (kVA) | M56: Output FLA (A) | N56: Efficiency | O56: Recharge Allow. | P56: Input kVA | Q56: Input A | R56: Input OCPD (A) | S56: Output OCPD (A) | T56: Inverter Fault (× FLA) | U56: Inverter Fault (A) | V56: SCCR Override (A) | W56: SCCR Used (A) | X56: Fault at UPS (A) | Y56: SCCR Check
F57: =IF($B57="","",IFERROR(_xlfn.XLOOKUP($D57,Dashboard!$A$101:$A$350,Dashboard!$C$101:$C$350,""),"")) | G57: =IF($B57="","",0) | H57: =IF($B57="","",IFERROR(N(_xlfn.XLOOKUP($B57,$B$48:$B$53,$L$48:$L$53,0)),0)) | I57: =IF($B57="","",IFERROR(_xlfn.XLOOKUP($B57,$B$48:$B$53,$E$48:$E$53,$F$6),$F$6)) | J57: =IF($B57="","",_xlfn.LET(_xlpm.need,MAX(N($G57)*N($I57),N($H57)),IF(_xlpm.need=0,"—",IFERROR(_xlfn.XLOOKUP(_xlpm.need,UPS_kVA_List,UPS_kVA_List,"> 1100",1),"—")))) | L57: =IF($B57="","",IF(N($K57)>0,$K57,$J57)) | M57: =IF(NOT(ISNUMBER($L57)),"",_xlfn.LET(_xlpm.v,IFERROR(_xlfn.XLOOKUP($F57,Xfmr_VoltStr,Xfmr_BaseV),""),_xlpm.p,IFERROR(_xlfn.XLOOKUP($F57,Xfmr_VoltStr,Xfmr_Ph),3),IF(N(_xlpm.v)=0,"",ROUND($L57*1000/(_xlpm.v*IF(_xlpm.p=3,SQRT(3),1)),1)))) | N57: 0.95 | O57: 0.15 | P57: =IF(NOT(ISNUMBER($L57)),"",ROUND($L57/IF(N($N57)=0,1,$N57)*(1+N($O57)),1)) | Q57: =IF(NOT(ISNUMBER($P57)),"",_xlfn.LET(_xlpm.vs,IFERROR(_xlfn.XLOOKUP($B57,Dashboard!$A$101:$A$350,Dashboard!$C$101:$C$350,$F57),$F57),_xlpm.v,IFERROR(_xlfn.XLOOKUP(_xlpm.vs,Xfmr_VoltStr,Xfmr_BaseV),""),_xlpm.p,IFERROR(_xlfn.XLOOKUP(_xlpm.vs,Xfmr_VoltStr,Xfmr_Ph),3),IF(N(_xlpm.v)=0,"",ROUND($P57*1000/(_xlpm.v*IF(_xlpm.p=3,SQRT(3),1)),1)))) | R57: =IF(NOT(ISNUMBER($Q57)),"",IFERROR(_xlfn.XLOOKUP($Q57*1.25,OCPD_List,OCPD_List,"> 6000",1),"—")) | S57: =IF(NOT(ISNUMBER($M57)),"",IFERROR(_xlfn.XLOOKUP($M57*1.25,OCPD_List,OCPD_List,"> 6000",1),"—")) | T57: 2 | U57: =IF(NOT(ISNUMBER($M57)),"",ROUND($M57*N($T57),0)) | W57: =IF($B57="","",IF(N($V57)>0,$V57,$N$6)) | X57: =IF($B57="","",IFERROR(_xlfn.XLOOKUP($B57,'Short Circuit'!$A$6:$A$255,'Short Circuit'!$Q$6:$Q$255,""),"")) | Y57: =IF(OR($B57="",NOT(ISNUMBER($W57)),NOT(ISNUMBER($X57))),"",IF($W57>=$X57,"✔ SCCR OK","✖ SCCR below fault — raise SCCR / series device"))
F58: =IF($B58="","",IFERROR(_xlfn.XLOOKUP($D58,Dashboard!$A$101:$A$350,Dashboard!$C$101:$C$350,""),"")) | G58: =IF($B58="","",0) | H58: =IF($B58="","",IFERROR(N(_xlfn.XLOOKUP($B58,$B$48:$B$53,$L$48:$L$53,0)),0)) | I58: =IF($B58="","",IFERROR(_xlfn.XLOOKUP($B58,$B$48:$B$53,$E$48:$E$53,$F$6),$F$6)) | J58: =IF($B58="","",_xlfn.LET(_xlpm.need,MAX(N($G58)*N($I58),N($H58)),IF(_xlpm.need=0,"—",IFERROR(_xlfn.XLOOKUP(_xlpm.need,UPS_kVA_List,UPS_kVA_List,"> 1100",1),"—")))) | L58: =IF($B58="","",IF(N($K58)>0,$K58,$J58)) | M58: =IF(NOT(ISNUMBER($L58)),"",_xlfn.LET(_xlpm.v,IFERROR(_xlfn.XLOOKUP($F58,Xfmr_VoltStr,Xfmr_BaseV),""),_xlpm.p,IFERROR(_xlfn.XLOOKUP($F58,Xfmr_VoltStr,Xfmr_Ph),3),IF(N(_xlpm.v)=0,"",ROUND($L58*1000/(_xlpm.v*IF(_xlpm.p=3,SQRT(3),1)),1)))) | N58: 0.95 | O58: 0.15 | P58: =IF(NOT(ISNUMBER($L58)),"",ROUND($L58/IF(N($N58)=0,1,$N58)*(1+N($O58)),1)) | Q58: =IF(NOT(ISNUMBER($P58)),"",_xlfn.LET(_xlpm.vs,IFERROR(_xlfn.XLOOKUP($B58,Dashboard!$A$101:$A$350,Dashboard!$C$101:$C$350,$F58),$F58),_xlpm.v,IFERROR(_xlfn.XLOOKUP(_xlpm.vs,Xfmr_VoltStr,Xfmr_BaseV),""),_xlpm.p,IFERROR(_xlfn.XLOOKUP(_xlpm.vs,Xfmr_VoltStr,Xfmr_Ph),3),IF(N(_xlpm.v)=0,"",ROUND($P58*1000/(_xlpm.v*IF(_xlpm.p=3,SQRT(3),1)),1)))) | R58: =IF(NOT(ISNUMBER($Q58)),"",IFERROR(_xlfn.XLOOKUP($Q58*1.25,OCPD_List,OCPD_List,"> 6000",1),"—")) | S58: =IF(NOT(ISNUMBER($M58)),"",IFERROR(_xlfn.XLOOKUP($M58*1.25,OCPD_List,OCPD_List,"> 6000",1),"—")) | T58: 2 | U58: =IF(NOT(ISNUMBER($M58)),"",ROUND($M58*N($T58),0)) | W58: =IF($B58="","",IF(N($V58)>0,$V58,$N$6)) | X58: =IF($B58="","",IFERROR(_xlfn.XLOOKUP($B58,'Short Circuit'!$A$6:$A$255,'Short Circuit'!$Q$6:$Q$255,""),"")) | Y58: =IF(OR($B58="",NOT(ISNUMBER($W58)),NOT(ISNUMBER($X58))),"",IF($W58>=$X58,"✔ SCCR OK","✖ SCCR below fault — raise SCCR / series device"))
F59: =IF($B59="","",IFERROR(_xlfn.XLOOKUP($D59,Dashboard!$A$101:$A$350,Dashboard!$C$101:$C$350,""),"")) | G59: =IF($B59="","",0) | H59: =IF($B59="","",IFERROR(N(_xlfn.XLOOKUP($B59,$B$48:$B$53,$L$48:$L$53,0)),0)) | I59: =IF($B59="","",IFERROR(_xlfn.XLOOKUP($B59,$B$48:$B$53,$E$48:$E$53,$F$6),$F$6)) | J59: =IF($B59="","",_xlfn.LET(_xlpm.need,MAX(N($G59)*N($I59),N($H59)),IF(_xlpm.need=0,"—",IFERROR(_xlfn.XLOOKUP(_xlpm.need,UPS_kVA_List,UPS_kVA_List,"> 1100",1),"—")))) | L59: =IF($B59="","",IF(N($K59)>0,$K59,$J59)) | M59: =IF(NOT(ISNUMBER($L59)),"",_xlfn.LET(_xlpm.v,IFERROR(_xlfn.XLOOKUP($F59,Xfmr_VoltStr,Xfmr_BaseV),""),_xlpm.p,IFERROR(_xlfn.XLOOKUP($F59,Xfmr_VoltStr,Xfmr_Ph),3),IF(N(_xlpm.v)=0,"",ROUND($L59*1000/(_xlpm.v*IF(_xlpm.p=3,SQRT(3),1)),1)))) | N59: 0.95 | O59: 0.15 | P59: =IF(NOT(ISNUMBER($L59)),"",ROUND($L59/IF(N($N59)=0,1,$N59)*(1+N($O59)),1)) | Q59: =IF(NOT(ISNUMBER($P59)),"",_xlfn.LET(_xlpm.vs,IFERROR(_xlfn.XLOOKUP($B59,Dashboard!$A$101:$A$350,Dashboard!$C$101:$C$350,$F59),$F59),_xlpm.v,IFERROR(_xlfn.XLOOKUP(_xlpm.vs,Xfmr_VoltStr,Xfmr_BaseV),""),_xlpm.p,IFERROR(_xlfn.XLOOKUP(_xlpm.vs,Xfmr_VoltStr,Xfmr_Ph),3),IF(N(_xlpm.v)=0,"",ROUND($P59*1000/(_xlpm.v*IF(_xlpm.p=3,SQRT(3),1)),1)))) | R59: =IF(NOT(ISNUMBER($Q59)),"",IFERROR(_xlfn.XLOOKUP($Q59*1.25,OCPD_List,OCPD_List,"> 6000",1),"—")) | S59: =IF(NOT(ISNUMBER($M59)),"",IFERROR(_xlfn.XLOOKUP($M59*1.25,OCPD_List,OCPD_List,"> 6000",1),"—")) | T59: 2 | U59: =IF(NOT(ISNUMBER($M59)),"",ROUND($M59*N($T59),0)) | W59: =IF($B59="","",IF(N($V59)>0,$V59,$N$6)) | X59: =IF($B59="","",IFERROR(_xlfn.XLOOKUP($B59,'Short Circuit'!$A$6:$A$255,'Short Circuit'!$Q$6:$Q$255,""),"")) | Y59: =IF(OR($B59="",NOT(ISNUMBER($W59)),NOT(ISNUMBER($X59))),"",IF($W59>=$X59,"✔ SCCR OK","✖ SCCR below fault — raise SCCR / series device"))
F60: =IF($B60="","",IFERROR(_xlfn.XLOOKUP($D60,Dashboard!$A$101:$A$350,Dashboard!$C$101:$C$350,""),"")) | G60: =IF($B60="","",0) | H60: =IF($B60="","",IFERROR(N(_xlfn.XLOOKUP($B60,$B$48:$B$53,$L$48:$L$53,0)),0)) | I60: =IF($B60="","",IFERROR(_xlfn.XLOOKUP($B60,$B$48:$B$53,$E$48:$E$53,$F$6),$F$6)) | J60: =IF($B60="","",_xlfn.LET(_xlpm.need,MAX(N($G60)*N($I60),N($H60)),IF(_xlpm.need=0,"—",IFERROR(_xlfn.XLOOKUP(_xlpm.need,UPS_kVA_List,UPS_kVA_List,"> 1100",1),"—")))) | L60: =IF($B60="","",IF(N($K60)>0,$K60,$J60)) | M60: =IF(NOT(ISNUMBER($L60)),"",_xlfn.LET(_xlpm.v,IFERROR(_xlfn.XLOOKUP($F60,Xfmr_VoltStr,Xfmr_BaseV),""),_xlpm.p,IFERROR(_xlfn.XLOOKUP($F60,Xfmr_VoltStr,Xfmr_Ph),3),IF(N(_xlpm.v)=0,"",ROUND($L60*1000/(_xlpm.v*IF(_xlpm.p=3,SQRT(3),1)),1)))) | N60: 0.95 | O60: 0.15 | P60: =IF(NOT(ISNUMBER($L60)),"",ROUND($L60/IF(N($N60)=0,1,$N60)*(1+N($O60)),1)) | Q60: =IF(NOT(ISNUMBER($P60)),"",_xlfn.LET(_xlpm.vs,IFERROR(_xlfn.XLOOKUP($B60,Dashboard!$A$101:$A$350,Dashboard!$C$101:$C$350,$F60),$F60),_xlpm.v,IFERROR(_xlfn.XLOOKUP(_xlpm.vs,Xfmr_VoltStr,Xfmr_BaseV),""),_xlpm.p,IFERROR(_xlfn.XLOOKUP(_xlpm.vs,Xfmr_VoltStr,Xfmr_Ph),3),IF(N(_xlpm.v)=0,"",ROUND($P60*1000/(_xlpm.v*IF(_xlpm.p=3,SQRT(3),1)),1)))) | R60: =IF(NOT(ISNUMBER($Q60)),"",IFERROR(_xlfn.XLOOKUP($Q60*1.25,OCPD_List,OCPD_List,"> 6000",1),"—")) | S60: =IF(NOT(ISNUMBER($M60)),"",IFERROR(_xlfn.XLOOKUP($M60*1.25,OCPD_List,OCPD_List,"> 6000",1),"—")) | T60: 2 | U60: =IF(NOT(ISNUMBER($M60)),"",ROUND($M60*N($T60),0)) | W60: =IF($B60="","",IF(N($V60)>0,$V60,$N$6)) | X60: =IF($B60="","",IFERROR(_xlfn.XLOOKUP($B60,'Short Circuit'!$A$6:$A$255,'Short Circuit'!$Q$6:$Q$255,""),"")) | Y60: =IF(OR($B60="",NOT(ISNUMBER($W60)),NOT(ISNUMBER($X60))),"",IF($W60>=$X60,"✔ SCCR OK","✖ SCCR below fault — raise SCCR / series device"))
F61: =IF($B61="","",IFERROR(_xlfn.XLOOKUP($D61,Dashboard!$A$101:$A$350,Dashboard!$C$101:$C$350,""),"")) | G61: =IF($B61="","",0) | H61: =IF($B61="","",IFERROR(N(_xlfn.XLOOKUP($B61,$B$48:$B$53,$L$48:$L$53,0)),0)) | I61: =IF($B61="","",IFERROR(_xlfn.XLOOKUP($B61,$B$48:$B$53,$E$48:$E$53,$F$6),$F$6)) | J61: =IF($B61="","",_xlfn.LET(_xlpm.need,MAX(N($G61)*N($I61),N($H61)),IF(_xlpm.need=0,"—",IFERROR(_xlfn.XLOOKUP(_xlpm.need,UPS_kVA_List,UPS_kVA_List,"> 1100",1),"—")))) | L61: =IF($B61="","",IF(N($K61)>0,$K61,$J61)) | M61: =IF(NOT(ISNUMBER($L61)),"",_xlfn.LET(_xlpm.v,IFERROR(_xlfn.XLOOKUP($F61,Xfmr_VoltStr,Xfmr_BaseV),""),_xlpm.p,IFERROR(_xlfn.XLOOKUP($F61,Xfmr_VoltStr,Xfmr_Ph),3),IF(N(_xlpm.v)=0,"",ROUND($L61*1000/(_xlpm.v*IF(_xlpm.p=3,SQRT(3),1)),1)))) | N61: 0.95 | O61: 0.15 | P61: =IF(NOT(ISNUMBER($L61)),"",ROUND($L61/IF(N($N61)=0,1,$N61)*(1+N($O61)),1)) | Q61: =IF(NOT(ISNUMBER($P61)),"",_xlfn.LET(_xlpm.vs,IFERROR(_xlfn.XLOOKUP($B61,Dashboard!$A$101:$A$350,Dashboard!$C$101:$C$350,$F61),$F61),_xlpm.v,IFERROR(_xlfn.XLOOKUP(_xlpm.vs,Xfmr_VoltStr,Xfmr_BaseV),""),_xlpm.p,IFERROR(_xlfn.XLOOKUP(_xlpm.vs,Xfmr_VoltStr,Xfmr_Ph),3),IF(N(_xlpm.v)=0,"",ROUND($P61*1000/(_xlpm.v*IF(_xlpm.p=3,SQRT(3),1)),1)))) | R61: =IF(NOT(ISNUMBER($Q61)),"",IFERROR(_xlfn.XLOOKUP($Q61*1.25,OCPD_List,OCPD_List,"> 6000",1),"—")) | S61: =IF(NOT(ISNUMBER($M61)),"",IFERROR(_xlfn.XLOOKUP($M61*1.25,OCPD_List,OCPD_List,"> 6000",1),"—")) | T61: 2 | U61: =IF(NOT(ISNUMBER($M61)),"",ROUND($M61*N($T61),0)) | W61: =IF($B61="","",IF(N($V61)>0,$V61,$N$6)) | X61: =IF($B61="","",IFERROR(_xlfn.XLOOKUP($B61,'Short Circuit'!$A$6:$A$255,'Short Circuit'!$Q$6:$Q$255,""),"")) | Y61: =IF(OR($B61="",NOT(ISNUMBER($W61)),NOT(ISNUMBER($X61))),"",IF($W61>=$X61,"✔ SCCR OK","✖ SCCR below fault — raise SCCR / series device"))
F62: =IF($B62="","",IFERROR(_xlfn.XLOOKUP($D62,Dashboard!$A$101:$A$350,Dashboard!$C$101:$C$350,""),"")) | G62: =IF($B62="","",0) | H62: =IF($B62="","",IFERROR(N(_xlfn.XLOOKUP($B62,$B$48:$B$53,$L$48:$L$53,0)),0)) | I62: =IF($B62="","",IFERROR(_xlfn.XLOOKUP($B62,$B$48:$B$53,$E$48:$E$53,$F$6),$F$6)) | J62: =IF($B62="","",_xlfn.LET(_xlpm.need,MAX(N($G62)*N($I62),N($H62)),IF(_xlpm.need=0,"—",IFERROR(_xlfn.XLOOKUP(_xlpm.need,UPS_kVA_List,UPS_kVA_List,"> 1100",1),"—")))) | L62: =IF($B62="","",IF(N($K62)>0,$K62,$J62)) | M62: =IF(NOT(ISNUMBER($L62)),"",_xlfn.LET(_xlpm.v,IFERROR(_xlfn.XLOOKUP($F62,Xfmr_VoltStr,Xfmr_BaseV),""),_xlpm.p,IFERROR(_xlfn.XLOOKUP($F62,Xfmr_VoltStr,Xfmr_Ph),3),IF(N(_xlpm.v)=0,"",ROUND($L62*1000/(_xlpm.v*IF(_xlpm.p=3,SQRT(3),1)),1)))) | N62: 0.95 | O62: 0.15 | P62: =IF(NOT(ISNUMBER($L62)),"",ROUND($L62/IF(N($N62)=0,1,$N62)*(1+N($O62)),1)) | Q62: =IF(NOT(ISNUMBER($P62)),"",_xlfn.LET(_xlpm.vs,IFERROR(_xlfn.XLOOKUP($B62,Dashboard!$A$101:$A$350,Dashboard!$C$101:$C$350,$F62),$F62),_xlpm.v,IFERROR(_xlfn.XLOOKUP(_xlpm.vs,Xfmr_VoltStr,Xfmr_BaseV),""),_xlpm.p,IFERROR(_xlfn.XLOOKUP(_xlpm.vs,Xfmr_VoltStr,Xfmr_Ph),3),IF(N(_xlpm.v)=0,"",ROUND($P62*1000/(_xlpm.v*IF(_xlpm.p=3,SQRT(3),1)),1)))) | R62: =IF(NOT(ISNUMBER($Q62)),"",IFERROR(_xlfn.XLOOKUP($Q62*1.25,OCPD_List,OCPD_List,"> 6000",1),"—")) | S62: =IF(NOT(ISNUMBER($M62)),"",IFERROR(_xlfn.XLOOKUP($M62*1.25,OCPD_List,OCPD_List,"> 6000",1),"—")) | T62: 2 | U62: =IF(NOT(ISNUMBER($M62)),"",ROUND($M62*N($T62),0)) | W62: =IF($B62="","",IF(N($V62)>0,$V62,$N$6)) | X62: =IF($B62="","",IFERROR(_xlfn.XLOOKUP($B62,'Short Circuit'!$A$6:$A$255,'Short Circuit'!$Q$6:$Q$255,""),"")) | Y62: =IF(OR($B62="",NOT(ISNUMBER($W62)),NOT(ISNUMBER($X62))),"",IF($W62>=$X62,"✔ SCCR OK","✖ SCCR below fault — raise SCCR / series device"))
F63: =IF($B63="","",IFERROR(_xlfn.XLOOKUP($D63,Dashboard!$A$101:$A$350,Dashboard!$C$101:$C$350,""),"")) | G63: =IF($B63="","",0) | H63: =IF($B63="","",IFERROR(N(_xlfn.XLOOKUP($B63,$B$48:$B$53,$L$48:$L$53,0)),0)) | I63: =IF($B63="","",IFERROR(_xlfn.XLOOKUP($B63,$B$48:$B$53,$E$48:$E$53,$F$6),$F$6)) | J63: =IF($B63="","",_xlfn.LET(_xlpm.need,MAX(N($G63)*N($I63),N($H63)),IF(_xlpm.need=0,"—",IFERROR(_xlfn.XLOOKUP(_xlpm.need,UPS_kVA_List,UPS_kVA_List,"> 1100",1),"—")))) | L63: =IF($B63="","",IF(N($K63)>0,$K63,$J63)) | M63: =IF(NOT(ISNUMBER($L63)),"",_xlfn.LET(_xlpm.v,IFERROR(_xlfn.XLOOKUP($F63,Xfmr_VoltStr,Xfmr_BaseV),""),_xlpm.p,IFERROR(_xlfn.XLOOKUP($F63,Xfmr_VoltStr,Xfmr_Ph),3),IF(N(_xlpm.v)=0,"",ROUND($L63*1000/(_xlpm.v*IF(_xlpm.p=3,SQRT(3),1)),1)))) | N63: 0.95 | O63: 0.15 | P63: =IF(NOT(ISNUMBER($L63)),"",ROUND($L63/IF(N($N63)=0,1,$N63)*(1+N($O63)),1)) | Q63: =IF(NOT(ISNUMBER($P63)),"",_xlfn.LET(_xlpm.vs,IFERROR(_xlfn.XLOOKUP($B63,Dashboard!$A$101:$A$350,Dashboard!$C$101:$C$350,$F63),$F63),_xlpm.v,IFERROR(_xlfn.XLOOKUP(_xlpm.vs,Xfmr_VoltStr,Xfmr_BaseV),""),_xlpm.p,IFERROR(_xlfn.XLOOKUP(_xlpm.vs,Xfmr_VoltStr,Xfmr_Ph),3),IF(N(_xlpm.v)=0,"",ROUND($P63*1000/(_xlpm.v*IF(_xlpm.p=3,SQRT(3),1)),1)))) | R63: =IF(NOT(ISNUMBER($Q63)),"",IFERROR(_xlfn.XLOOKUP($Q63*1.25,OCPD_List,OCPD_List,"> 6000",1),"—")) | S63: =IF(NOT(ISNUMBER($M63)),"",IFERROR(_xlfn.XLOOKUP($M63*1.25,OCPD_List,OCPD_List,"> 6000",1),"—")) | T63: 2 | U63: =IF(NOT(ISNUMBER($M63)),"",ROUND($M63*N($T63),0)) | W63: =IF($B63="","",IF(N($V63)>0,$V63,$N$6)) | X63: =IF($B63="","",IFERROR(_xlfn.XLOOKUP($B63,'Short Circuit'!$A$6:$A$255,'Short Circuit'!$Q$6:$Q$255,""),"")) | Y63: =IF(OR($B63="",NOT(ISNUMBER($W63)),NOT(ISNUMBER($X63))),"",IF($W63>=$X63,"✔ SCCR OK","✖ SCCR below fault — raise SCCR / series device"))
F64: =IF($B64="","",IFERROR(_xlfn.XLOOKUP($D64,Dashboard!$A$101:$A$350,Dashboard!$C$101:$C$350,""),"")) | G64: =IF($B64="","",0) | H64: =IF($B64="","",IFERROR(N(_xlfn.XLOOKUP($B64,$B$48:$B$53,$L$48:$L$53,0)),0)) | I64: =IF($B64="","",IFERROR(_xlfn.XLOOKUP($B64,$B$48:$B$53,$E$48:$E$53,$F$6),$F$6)) | J64: =IF($B64="","",_xlfn.LET(_xlpm.need,MAX(N($G64)*N($I64),N($H64)),IF(_xlpm.need=0,"—",IFERROR(_xlfn.XLOOKUP(_xlpm.need,UPS_kVA_List,UPS_kVA_List,"> 1100",1),"—")))) | L64: =IF($B64="","",IF(N($K64)>0,$K64,$J64)) | M64: =IF(NOT(ISNUMBER($L64)),"",_xlfn.LET(_xlpm.v,IFERROR(_xlfn.XLOOKUP($F64,Xfmr_VoltStr,Xfmr_BaseV),""),_xlpm.p,IFERROR(_xlfn.XLOOKUP($F64,Xfmr_VoltStr,Xfmr_Ph),3),IF(N(_xlpm.v)=0,"",ROUND($L64*1000/(_xlpm.v*IF(_xlpm.p=3,SQRT(3),1)),1)))) | N64: 0.95 | O64: 0.15 | P64: =IF(NOT(ISNUMBER($L64)),"",ROUND($L64/IF(N($N64)=0,1,$N64)*(1+N($O64)),1)) | Q64: =IF(NOT(ISNUMBER($P64)),"",_xlfn.LET(_xlpm.vs,IFERROR(_xlfn.XLOOKUP($B64,Dashboard!$A$101:$A$350,Dashboard!$C$101:$C$350,$F64),$F64),_xlpm.v,IFERROR(_xlfn.XLOOKUP(_xlpm.vs,Xfmr_VoltStr,Xfmr_BaseV),""),_xlpm.p,IFERROR(_xlfn.XLOOKUP(_xlpm.vs,Xfmr_VoltStr,Xfmr_Ph),3),IF(N(_xlpm.v)=0,"",ROUND($P64*1000/(_xlpm.v*IF(_xlpm.p=3,SQRT(3),1)),1)))) | R64: =IF(NOT(ISNUMBER($Q64)),"",IFERROR(_xlfn.XLOOKUP($Q64*1.25,OCPD_List,OCPD_List,"> 6000",1),"—")) | S64: =IF(NOT(ISNUMBER($M64)),"",IFERROR(_xlfn.XLOOKUP($M64*1.25,OCPD_List,OCPD_List,"> 6000",1),"—")) | T64: 2 | U64: =IF(NOT(ISNUMBER($M64)),"",ROUND($M64*N($T64),0)) | W64: =IF($B64="","",IF(N($V64)>0,$V64,$N$6)) | X64: =IF($B64="","",IFERROR(_xlfn.XLOOKUP($B64,'Short Circuit'!$A$6:$A$255,'Short Circuit'!$Q$6:$Q$255,""),"")) | Y64: =IF(OR($B64="",NOT(ISNUMBER($W64)),NOT(ISNUMBER($X64))),"",IF($W64>=$X64,"✔ SCCR OK","✖ SCCR below fault — raise SCCR / series device"))
A66: Bypass: with a static / maintenance bypass the upstream fault passes through to the output; with None the output fault is limited to the inverter (× FLA). Typical SCCR and inverter limits — verify with the UPS manufacturer.

Sheet Transformers
A1: TRANSFORMER SCHEDULE | AG1: BACKGROUND CALCULATIONS — collapsed by default; nothing here is an input | BO1: DETECTION — every registry edge where the voltage changes needs a transformer
A2: Auto-created from the Equipment Registry: every feed where the voltage changes generates a transformer, and its row appears here on its own — one row shows when the project has no transformers, then rows appear and disappear as connections change. Everything from Tag through Bonding Jumper is derived and locked. The only inputs on this sheet are Source X/R (S), %Z (T) and Load Loss (U) per row, plus Notes (R) and the override columns (AM:AS). A gold %Z cell means that transformer is still calculating on the NEC_Data default — enter the submittal value. A gold Pri OCPD cell means estimated inrush exceeds 10x the selected device, so check the trip curve. System voltages, standard defaults and the inrush multiplier all live on NEC_Data. Columns V onward are background calculation — grouped and collapsed; expand only to audit. | BO2: =_xlfn.LET(_xlpm.n,IF(INDEX(_xlfn.ANCHORARRAY($BO$4),1,1)="",0,ROWS(_xlfn.ANCHORARRAY($BO$4))),IF(_xlpm.n=0,"— no voltage changes detected —",_xlpm.n&" transformer(s) detected")) -> — no voltage changes detected — | BV2: Unrecognised registry voltages (add them to the config list)
A3: Identification | C3: Voltage | F3: Capacity | H3: Construction | M3: Overcurrent Protection | O3: Grounding & Bonding | Q3: Loading & Notes | S3: Fault Duty | W3: Design Inputs | Z3: Overrides (blank = use derived) | BO3: Child (Serves) | BP3: Parent (fed from) | BQ3: Pri V | BR3: Sec V | BS3: Ph | BT3: Load kVA | BV3: {=_xlfn.LET(_xlpm.vlt,Dashboard!$C$101:$C$350,_xlpm.tag,Dashboard!$A$101:$A$350,_xlpm.bad,(_xlpm.tag<>"")*(_xlpm.vlt<>"")*ISNA(MATCH(_xlpm.vlt,Xfmr_VoltStr,0)),IF(SUM(_xlpm.bad)=0,"✓ all voltages recognised",_xlfn.TEXTJOIN(", ",TRUE,_xlfn._xlws.FILTER(_xlpm.tag&" ("&_xlpm.vlt&")",_xlpm.bad=1))))} -> ✓ all voltages recognised
A4: Tag | B4: Serves | C4: Ph | D4: Pri V | E4: Sec V | F4: Load kVA | G4: Std kVA | H4: Pri Conn | I4: Sec Conn | J4: Type / Rise | K4: Taps | L4: Enclosure | M4: Pri OCPD (A) | N4: Sec OCPD (A) | O4: {="GEC "&NECREF("250.66")} -> GEC 250.66 | P4: {="Bonding Jumper "&NECREF("250.102")&"(C)(1)"} -> Bonding Jumper 250.102(C)(1) | Q4: % Loaded | R4: Notes | S4: %Z total | T4: Sec Fault Sym (A) | U4: Sec AIC Req (A) | V4: Inrush (A) | W4: Source X/R | X4: %Z | Y4: Load Loss (kW) | Z4: Pri OCPD Override (A) | AA4: Sec OCPD Override (A) | AB4: Pri Conn Override | AC4: Sec Conn Override | AD4: Type/Rise Override | AE4: Taps Override | AF4: Enclosure Override | AG4: %R | AH4: X/R | AI4: %X | AJ4: Pri FLA (A) | AK4: Sec FLA (A) | AL4: Pri Avail (A) | AM4: %R total | AN4: %X total | AO4: %Z total | AP4: Sec Fault Sym (A) | AQ4: Asym Peak (A) | AR4: Inrush (A) | AS4: Sec AIC Req (A) | AT4: Sec Sets | AU4: Sec Cond (basis) | AV4: {="GEC "&NECREF("250.66")} -> GEC 250.66 | AW4: {="SBJ "&NECREF("250.102")&"(C)(1)"} -> SBJ 250.102(C)(1) | AX4: %Z eff | AY4: Src X/R eff | AZ4: Inrush check | BO4: {=_xlfn.LET(_xlpm.tag,Dashboard!$A$101:$A$350,_xlpm.vlt,Dashboard!$C$101:$C$350,_xlpm.fed,Dashboard!$D$101:$D$350,_xlpm.kva,Dashboard!$F$101:$F$350,_xlpm.outv,Dashboard!$N$101:$N$350,_xlpm.cv,IFERROR(_xlfn.XLOOKUP(_xlpm.vlt,Xfmr_VoltStr,Xfmr_BaseV),""),_xlpm.pvlt,IFERROR(_xlfn.XLOOKUP(_xlpm.fed,_xlpm.tag,IF(_xlpm.outv<>"",_xlpm.outv,_xlpm.vlt)),""),_xlpm.pv,IFERROR(_xlfn.XLOOKUP(_xlpm.pvlt,Xfmr_VoltStr,Xfmr_BaseV),""),_xlpm.ph,IFERROR(_xlfn.XLOOKUP(_xlpm.vlt,Xfmr_VoltStr,Xfmr_Ph),""),_xlpm.keep,(_xlpm.tag<>"")*(_xlpm.fed<>"")*ISNUMBER(_xlpm.cv)*ISNUMBER(_xlpm.pv)*(_xlpm.cv<>_xlpm.pv),IF(SUM(_xlpm.keep)=0,"",_xlfn._xlws.FILTER(_xlfn.HSTACK(_xlpm.tag,_xlpm.fed,_xlpm.pv,_xlpm.cv,_xlpm.ph,_xlpm.kva),_xlpm.keep=1)))}
A6: {=IFERROR(IF(INDEX(_xlfn.ANCHORARRAY($BO$4),ROW()-5,1)="","","T-"&INDEX(_xlfn.ANCHORARRAY($BO$4),ROW()-5,1)),"")} | B6: {=IFERROR(IF(INDEX(_xlfn.ANCHORARRAY($BO$4),ROW()-5,1)="","",INDEX(_xlfn.ANCHORARRAY($BO$4),ROW()-5,1)),"")} | C6: {=IFERROR(INDEX(_xlfn.ANCHORARRAY($BO$4),ROW()-5,5),"")} | D6: {=IFERROR(INDEX(_xlfn.ANCHORARRAY($BO$4),ROW()-5,3),"")} | E6: {=IFERROR(INDEX(_xlfn.ANCHORARRAY($BO$4),ROW()-5,4),"")} | F6: {=IFERROR(INDEX(_xlfn.ANCHORARRAY($BO$4),ROW()-5,6),"")} | G6: {=IF($F6="","",_xlfn.LET(_xlpm.ov,N(IFERROR(_xlfn.XLOOKUP($B6,Dashboard!$A$101:$A$350,Dashboard!$O$101:$O$350,0),0)),_xlpm.need,MAX(N($F6),_xlpm.ov*N($E6)*IF($C6=3,SQRT(3),1)/1000),IFERROR(INDEX(IF($C6=1,Xfmr1_kVA,Xfmr3_kVA),MATCH(TRUE,IF($C6=1,Xfmr1_kVA,Xfmr3_kVA)>=_xlpm.need,0)),"OVER")))} | H6: =IF($AB6<>"",$AB6,IF($D6="","",IFERROR(_xlfn.XLOOKUP($D6,Xfmr_BaseV,Xfmr_Conn),""))) | I6: =IF($AC6<>"",$AC6,IF($E6="","",IFERROR(_xlfn.XLOOKUP($E6,Xfmr_BaseV,Xfmr_Conn),""))) | J6: =IF($AD6<>"",$AD6,IF($B6="","",Xfmr_DefType)) | K6: =IF($AE6<>"",$AE6,IF($B6="","",Xfmr_DefTaps)) | L6: =IF($AF6<>"",$AF6,IF($B6="","",Xfmr_DefEncl)) | M6: {=IF($Z6<>"",$Z6,IFERROR(IF($AJ6="","",INDEX(OCPD_List,MATCH(TRUE,OCPD_List>=1.25*$AJ6,0))),"—"))} | N6: {=IF($AA6<>"",$AA6,IFERROR(IF($AK6="","",INDEX(OCPD_List,MATCH(TRUE,OCPD_List>=1.25*$AK6,0))),"—"))} | O6: =IF($A6="","",$AV6) | P6: =IF($A6="","",$AW6) | Q6: =IF(OR($F6="",$G6="",$G6="OVER"),"",$F6/$G6) | S6: =IF($A6="","",$AO6) | T6: =IF($A6="","",$AP6) | U6: =IF($A6="","",$AS6) | V6: =IF($A6="","",$AR6) | AG6: =IF(OR($AX6="",$G6="",$G6="OVER"),"",$AX6/SQRT(1+$AH6^2)) | AH6: =IF(OR($AX6="",$G6="",$G6="OVER"),"",IF(AND($Y6<>"",$Y6>0),SQRT(MAX($AX6^2-($Y6/$G6*100)^2,0))/($Y6/$G6*100),IFERROR(INDEX(XR_Typ,MATCH($G6,XR_kVA,1)),3))) | AI6: =IF(OR($AX6="",$G6="",$G6="OVER"),"",$AX6*$AH6/SQRT(1+$AH6^2)) | AJ6: =IF(OR($G6="",$G6="OVER",$D6=""),"",$G6*1000/(IF($C6=3,SQRT3,1)*$D6)) | AK6: =IF(OR($G6="",$G6="OVER",$E6=""),"",$G6*1000/(IF($C6=3,SQRT3,1)*$E6)) | AL6: {=IFERROR(IF(INDEX(_xlfn.ANCHORARRAY($BO$4),ROW()-5,2)="","",_xlfn.XLOOKUP(INDEX(_xlfn.ANCHORARRAY($BO$4),ROW()-5,2),'Short Circuit'!$A$6:$A$255,'Short Circuit'!$J$6:$J$255,"")),"")} | AM6: =IF(OR($AX6="",$AJ6=""),"",$AG6+IF(OR($AL6="",$AL6=0),0,($AJ6/$AL6*100)/SQRT(1+$AY6^2))) | AN6: =IF(OR($AX6="",$AJ6=""),"",$AI6+IF(OR($AL6="",$AL6=0),0,($AJ6/$AL6*100)*$AY6/SQRT(1+$AY6^2))) | AO6: =IF($AM6="","",SQRT($AM6^2+$AN6^2)) | AP6: =IF(OR($AK6="",$AO6=""),"",$AK6*100/$AO6) | AQ6: =IF($AP6="","",$AP6*SQRT(2)*(1+EXP(-PI()/($AN6/$AM6)))) | AR6: =IF($AJ6="","",$AJ6*Xfmr_Inrush) | AS6: {=IFERROR(IF($AP6="","",INDEX(AIC_List,MATCH(TRUE,AIC_List>=$AP6,0))),"⚠ > 200 kA")} | AT6: =IF($AK6="","",MAX(1,ROUNDUP(1.25*$AK6/475,0))) | AU6: {=IFERROR(IF($AK6="","",INDEX(Ampacity_Size,MATCH(TRUE,Ampacity_Cu>=1.25*$AK6/$AT6,0))),"—")} | AV6: {=IF($AU6="","",IFERROR(INDEX(Gec_Cu,MATCH(TRUE,Gec_CM>=INDEX(Ampacity_CM,MATCH($AU6,Ampacity_Size,0))*$AT6,0)),"—"))} | AW6: {=IF($AU6="","",IFERROR(IF(INDEX(Ampacity_CM,MATCH($AU6,Ampacity_Size,0))*$AT6>1100000,"12.5% of phase area",INDEX(Gec_Cu,MATCH(TRUE,Gec_CM>=INDEX(Ampacity_CM,MATCH($AU6,Ampacity_Size,0))*$AT6,0))),"—"))} | AX6: =IF($B6="","",IF($X6<>"",$X6,Xfmr_DefZ)) | AY6: =IF($B6="","",IF($W6<>"",$W6,Xfmr_DefXR)) | AZ6: =IF(OR($AR6="",$M6="",$M6="—"),"",IF($AR6>10*$M6,"Inrush "&TEXT($AR6,"#,##0")&"A exceeds 10x the "&TEXT($M6,"#,##0")&"A primary device — check the trip curve or raise the instantaneous setting",""))
A7: {=IFERROR(IF(INDEX(_xlfn.ANCHORARRAY($BO$4),ROW()-5,1)="","","T-"&INDEX(_xlfn.ANCHORARRAY($BO$4),ROW()-5,1)),"")} | B7: {=IFERROR(IF(INDEX(_xlfn.ANCHORARRAY($BO$4),ROW()-5,1)="","",INDEX(_xlfn.ANCHORARRAY($BO$4),ROW()-5,1)),"")} | C7: {=IFERROR(INDEX(_xlfn.ANCHORARRAY($BO$4),ROW()-5,5),"")} | D7: {=IFERROR(INDEX(_xlfn.ANCHORARRAY($BO$4),ROW()-5,3),"")} | E7: {=IFERROR(INDEX(_xlfn.ANCHORARRAY($BO$4),ROW()-5,4),"")} | F7: {=IFERROR(INDEX(_xlfn.ANCHORARRAY($BO$4),ROW()-5,6),"")} | G7: {=IF($F7="","",_xlfn.LET(_xlpm.ov,N(IFERROR(_xlfn.XLOOKUP($B7,Dashboard!$A$101:$A$350,Dashboard!$O$101:$O$350,0),0)),_xlpm.need,MAX(N($F7),_xlpm.ov*N($E7)*IF($C7=3,SQRT(3),1)/1000),IFERROR(INDEX(IF($C7=1,Xfmr1_kVA,Xfmr3_kVA),MATCH(TRUE,IF($C7=1,Xfmr1_kVA,Xfmr3_kVA)>=_xlpm.need,0)),"OVER")))} | H7: =IF($AB7<>"",$AB7,IF($D7="","",IFERROR(_xlfn.XLOOKUP($D7,Xfmr_BaseV,Xfmr_Conn),""))) | I7: =IF($AC7<>"",$AC7,IF($E7="","",IFERROR(_xlfn.XLOOKUP($E7,Xfmr_BaseV,Xfmr_Conn),""))) | J7: =IF($AD7<>"",$AD7,IF($B7="","",Xfmr_DefType)) | K7: =IF($AE7<>"",$AE7,IF($B7="","",Xfmr_DefTaps)) | L7: =IF($AF7<>"",$AF7,IF($B7="","",Xfmr_DefEncl)) | M7: {=IF($Z7<>"",$Z7,IFERROR(IF($AJ7="","",INDEX(OCPD_List,MATCH(TRUE,OCPD_List>=1.25*$AJ7,0))),"—"))} | N7: {=IF($AA7<>"",$AA7,IFERROR(IF($AK7="","",INDEX(OCPD_List,MATCH(TRUE,OCPD_List>=1.25*$AK7,0))),"—"))} | O7: =IF($A7="","",$AV7) | P7: =IF($A7="","",$AW7) | Q7: =IF(OR($F7="",$G7="",$G7="OVER"),"",$F7/$G7) | S7: =IF($A7="","",$AO7) | T7: =IF($A7="","",$AP7) | U7: =IF($A7="","",$AS7) | V7: =IF($A7="","",$AR7) | AG7: =IF(OR($AX7="",$G7="",$G7="OVER"),"",$AX7/SQRT(1+$AH7^2)) | AH7: =IF(OR($AX7="",$G7="",$G7="OVER"),"",IF(AND($Y7<>"",$Y7>0),SQRT(MAX($AX7^2-($Y7/$G7*100)^2,0))/($Y7/$G7*100),IFERROR(INDEX(XR_Typ,MATCH($G7,XR_kVA,1)),3))) | AI7: =IF(OR($AX7="",$G7="",$G7="OVER"),"",$AX7*$AH7/SQRT(1+$AH7^2)) | AJ7: =IF(OR($G7="",$G7="OVER",$D7=""),"",$G7*1000/(IF($C7=3,SQRT3,1)*$D7)) | AK7: =IF(OR($G7="",$G7="OVER",$E7=""),"",$G7*1000/(IF($C7=3,SQRT3,1)*$E7)) | AL7: {=IFERROR(IF(INDEX(_xlfn.ANCHORARRAY($BO$4),ROW()-5,2)="","",_xlfn.XLOOKUP(INDEX(_xlfn.ANCHORARRAY($BO$4),ROW()-5,2),'Short Circuit'!$A$6:$A$255,'Short Circuit'!$J$6:$J$255,"")),"")} | AM7: =IF(OR($AX7="",$AJ7=""),"",$AG7+IF(OR($AL7="",$AL7=0),0,($AJ7/$AL7*100)/SQRT(1+$AY7^2))) | AN7: =IF(OR($AX7="",$AJ7=""),"",$AI7+IF(OR($AL7="",$AL7=0),0,($AJ7/$AL7*100)*$AY7/SQRT(1+$AY7^2))) | AO7: =IF($AM7="","",SQRT($AM7^2+$AN7^2)) | AP7: =IF(OR($AK7="",$AO7=""),"",$AK7*100/$AO7) | AQ7: =IF($AP7="","",$AP7*SQRT(2)*(1+EXP(-PI()/($AN7/$AM7)))) | AR7: =IF($AJ7="","",$AJ7*Xfmr_Inrush) | AS7: {=IFERROR(IF($AP7="","",INDEX(AIC_List,MATCH(TRUE,AIC_List>=$AP7,0))),"⚠ > 200 kA")} | AT7: =IF($AK7="","",MAX(1,ROUNDUP(1.25*$AK7/475,0))) | AU7: {=IFERROR(IF($AK7="","",INDEX(Ampacity_Size,MATCH(TRUE,Ampacity_Cu>=1.25*$AK7/$AT7,0))),"—")} | AV7: {=IF($AU7="","",IFERROR(INDEX(Gec_Cu,MATCH(TRUE,Gec_CM>=INDEX(Ampacity_CM,MATCH($AU7,Ampacity_Size,0))*$AT7,0)),"—"))} | AW7: {=IF($AU7="","",IFERROR(IF(INDEX(Ampacity_CM,MATCH($AU7,Ampacity_Size,0))*$AT7>1100000,"12.5% of phase area",INDEX(Gec_Cu,MATCH(TRUE,Gec_CM>=INDEX(Ampacity_CM,MATCH($AU7,Ampacity_Size,0))*$AT7,0))),"—"))} | AX7: =IF($B7="","",IF($X7<>"",$X7,Xfmr_DefZ)) | AY7: =IF($B7="","",IF($W7<>"",$W7,Xfmr_DefXR)) | AZ7: =IF(OR($AR7="",$M7="",$M7="—"),"",IF($AR7>10*$M7,"Inrush "&TEXT($AR7,"#,##0")&"A exceeds 10x the "&TEXT($M7,"#,##0")&"A primary device — check the trip curve or raise the instantaneous setting",""))
A8: {=IFERROR(IF(INDEX(_xlfn.ANCHORARRAY($BO$4),ROW()-5,1)="","","T-"&INDEX(_xlfn.ANCHORARRAY($BO$4),ROW()-5,1)),"")} | B8: {=IFERROR(IF(INDEX(_xlfn.ANCHORARRAY($BO$4),ROW()-5,1)="","",INDEX(_xlfn.ANCHORARRAY($BO$4),ROW()-5,1)),"")} | C8: {=IFERROR(INDEX(_xlfn.ANCHORARRAY($BO$4),ROW()-5,5),"")} | D8: {=IFERROR(INDEX(_xlfn.ANCHORARRAY($BO$4),ROW()-5,3),"")} | E8: {=IFERROR(INDEX(_xlfn.ANCHORARRAY($BO$4),ROW()-5,4),"")} | F8: {=IFERROR(INDEX(_xlfn.ANCHORARRAY($BO$4),ROW()-5,6),"")} | G8: {=IF($F8="","",_xlfn.LET(_xlpm.ov,N(IFERROR(_xlfn.XLOOKUP($B8,Dashboard!$A$101:$A$350,Dashboard!$O$101:$O$350,0),0)),_xlpm.need,MAX(N($F8),_xlpm.ov*N($E8)*IF($C8=3,SQRT(3),1)/1000),IFERROR(INDEX(IF($C8=1,Xfmr1_kVA,Xfmr3_kVA),MATCH(TRUE,IF($C8=1,Xfmr1_kVA,Xfmr3_kVA)>=_xlpm.need,0)),"OVER")))} | H8: =IF($AB8<>"",$AB8,IF($D8="","",IFERROR(_xlfn.XLOOKUP($D8,Xfmr_BaseV,Xfmr_Conn),""))) | I8: =IF($AC8<>"",$AC8,IF($E8="","",IFERROR(_xlfn.XLOOKUP($E8,Xfmr_BaseV,Xfmr_Conn),""))) | J8: =IF($AD8<>"",$AD8,IF($B8="","",Xfmr_DefType)) | K8: =IF($AE8<>"",$AE8,IF($B8="","",Xfmr_DefTaps)) | L8: =IF($AF8<>"",$AF8,IF($B8="","",Xfmr_DefEncl)) | M8: {=IF($Z8<>"",$Z8,IFERROR(IF($AJ8="","",INDEX(OCPD_List,MATCH(TRUE,OCPD_List>=1.25*$AJ8,0))),"—"))} | N8: {=IF($AA8<>"",$AA8,IFERROR(IF($AK8="","",INDEX(OCPD_List,MATCH(TRUE,OCPD_List>=1.25*$AK8,0))),"—"))} | O8: =IF($A8="","",$AV8) | P8: =IF($A8="","",$AW8) | Q8: =IF(OR($F8="",$G8="",$G8="OVER"),"",$F8/$G8) | S8: =IF($A8="","",$AO8) | T8: =IF($A8="","",$AP8) | U8: =IF($A8="","",$AS8) | V8: =IF($A8="","",$AR8) | AG8: =IF(OR($AX8="",$G8="",$G8="OVER"),"",$AX8/SQRT(1+$AH8^2)) | AH8: =IF(OR($AX8="",$G8="",$G8="OVER"),"",IF(AND($Y8<>"",$Y8>0),SQRT(MAX($AX8^2-($Y8/$G8*100)^2,0))/($Y8/$G8*100),IFERROR(INDEX(XR_Typ,MATCH($G8,XR_kVA,1)),3))) | AI8: =IF(OR($AX8="",$G8="",$G8="OVER"),"",$AX8*$AH8/SQRT(1+$AH8^2)) | AJ8: =IF(OR($G8="",$G8="OVER",$D8=""),"",$G8*1000/(IF($C8=3,SQRT3,1)*$D8)) | AK8: =IF(OR($G8="",$G8="OVER",$E8=""),"",$G8*1000/(IF($C8=3,SQRT3,1)*$E8)) | AL8: {=IFERROR(IF(INDEX(_xlfn.ANCHORARRAY($BO$4),ROW()-5,2)="","",_xlfn.XLOOKUP(INDEX(_xlfn.ANCHORARRAY($BO$4),ROW()-5,2),'Short Circuit'!$A$6:$A$255,'Short Circuit'!$J$6:$J$255,"")),"")} | AM8: =IF(OR($AX8="",$AJ8=""),"",$AG8+IF(OR($AL8="",$AL8=0),0,($AJ8/$AL8*100)/SQRT(1+$AY8^2))) | AN8: =IF(OR($AX8="",$AJ8=""),"",$AI8+IF(OR($AL8="",$AL8=0),0,($AJ8/$AL8*100)*$AY8/SQRT(1+$AY8^2))) | AO8: =IF($AM8="","",SQRT($AM8^2+$AN8^2)) | AP8: =IF(OR($AK8="",$AO8=""),"",$AK8*100/$AO8) | AQ8: =IF($AP8="","",$AP8*SQRT(2)*(1+EXP(-PI()/($AN8/$AM8)))) | AR8: =IF($AJ8="","",$AJ8*Xfmr_Inrush) | AS8: {=IFERROR(IF($AP8="","",INDEX(AIC_List,MATCH(TRUE,AIC_List>=$AP8,0))),"⚠ > 200 kA")} | AT8: =IF($AK8="","",MAX(1,ROUNDUP(1.25*$AK8/475,0))) | AU8: {=IFERROR(IF($AK8="","",INDEX(Ampacity_Size,MATCH(TRUE,Ampacity_Cu>=1.25*$AK8/$AT8,0))),"—")} | AV8: {=IF($AU8="","",IFERROR(INDEX(Gec_Cu,MATCH(TRUE,Gec_CM>=INDEX(Ampacity_CM,MATCH($AU8,Ampacity_Size,0))*$AT8,0)),"—"))} | AW8: {=IF($AU8="","",IFERROR(IF(INDEX(Ampacity_CM,MATCH($AU8,Ampacity_Size,0))*$AT8>1100000,"12.5% of phase area",INDEX(Gec_Cu,MATCH(TRUE,Gec_CM>=INDEX(Ampacity_CM,MATCH($AU8,Ampacity_Size,0))*$AT8,0))),"—"))} | AX8: =IF($B8="","",IF($X8<>"",$X8,Xfmr_DefZ)) | AY8: =IF($B8="","",IF($W8<>"",$W8,Xfmr_DefXR)) | AZ8: =IF(OR($AR8="",$M8="",$M8="—"),"",IF($AR8>10*$M8,"Inrush "&TEXT($AR8,"#,##0")&"A exceeds 10x the "&TEXT($M8,"#,##0")&"A primary device — check the trip curve or raise the instantaneous setting",""))
